Workbook

Sheet Sheet1
C1: HNL | D1: USD
B2: Initial Valuation (,000) | C2: 440000 | D2: =C2/26.4 -> 16666.667
B3: Down Payment (,000) | C3: 200000 | D3: =C3/26.4 -> 7575.7576
B4: Payment Period Yrs | C4: 10
B5: Interest Rate | C5: 0.085
B6: Montly Payments | C6: =(C2-C3)*(C5/12)*((1+(C5/12))^(C4*12))/((1+(C5/12))^(C4*12)-1) -> 2975.6565 | D6: =C6/26.4 -> 112.71426
B8: Scenarios | C8: #1 | D8: #2 | E8: #3
B9: Expected Sale Price | C9: 1000000 | D9: =(1+4.5%)^C4*C2 -> 683306.55 | E9: =(1+8.5%)^C4*C2 -> 994832.71
B10: Expected Sale Price USD | C10: =C9/((26.4)*(1+3.5%)^C4) -> 26852.985 | D10: =D9/((26.4)*(1+3.5%)^C4) -> 18348.821 | E10: =E9/((26.4)*(1+3.5%)^C4) -> 26714.228
B11: Annual Return | C11: =(C9/GETPIVOTDATA("Out-Of-Pocket ",$B$14))^(1/$C$4)-1 -> 0.060250139 | D11: =(D9/GETPIVOTDATA("Out-Of-Pocket ",$B$14))^(1/$C$4)-1 -> 0.020633682 | E11: =(E9/GETPIVOTDATA("Out-Of-Pocket ",$B$14))^(1/$C$4)-1 -> 0.059700999
B12: GM% | C12: =(C9-GETPIVOTDATA("Out-Of-Pocket ",$B$14))/C9 -> 0.44292122 | D12: =(D9-GETPIVOTDATA("Out-Of-Pocket ",$B$14))/D9 -> 0.1847308 | E12: =(E9-GETPIVOTDATA("Out-Of-Pocket ",$B$14))/E9 -> 0.44002768
B14: Yrs
B15: Capital | C15: 200000
B16: Principal | C16: 240000
B17: Interest | C17: 117078.78
B18: Out-Of-Pocket | C18: 557078.78
B19: Max of Out-of-Pocket USD Equiv | C19: 15701.475
B20: Debt Balance | C20: 8.9949026e-10
B21: Equity | C21: 440000

Sheet CALC
A1: Year | B1: Months | C1: Capital | D1: Interest | E1: Principal | F1: Out-of-Pocket | G1: Out-of-Pocket USD Equiv | H1: Balance | I1: Equity
A2: =IF(ISBLANK(B2),"",CEILING(B2/12,1)) -> 0 | B2: 0 | C2: =Sheet1!C3 -> 200000 | F2: =C2+D2+E2 -> 200000 | G2: =IFERROR(F2/(26.4*(1+3%)^A2),G1) -> 7575.7576 | H2: =Sheet1!C2-C2 -> 240000 | I2: =C2+E2 -> 200000
A3: =IF(ISBLANK(B3),"",CEILING(B3/12,1)) -> 1 | B3: {=_xlfn.SEQUENCE(12*Sheet1!C4,1,1,1)} -> 1 | D3: =H2*Sheet1!$C$5/12 -> 1700 | E3: =IF(H2<0.01,0,Sheet1!$C$6-D3) -> 1275.6565 | F3: =F2+D3+E3 -> 202975.66 | G3: =IFERROR(F3/(26.4*(1+3%)^A3),G2) -> 7464.5358 | H3: =H2-E3 -> 238724.34 | I3: =E3+I2 -> 201275.66
A4: =IF(ISBLANK(B4),"",CEILING(B4/12,1)) -> 1 | B4: 2 | D4: =H3*Sheet1!$C$5/12 -> 1690.9641 | E4: =IF(H3<0.01,0,Sheet1!$C$6-D4) -> 1284.6924 | F4: =F3+D4+E4 -> 205951.31 | G4: =IFERROR(F4/(26.4*(1+3%)^A4),G3) -> 7573.9671 | H4: =H3-E4 -> 237439.65 | I4: =E4+I3 -> 202560.35
A5: =IF(ISBLANK(B5),"",CEILING(B5/12,1)) -> 1 | B5: 3 | D5: =H4*Sheet1!$C$5/12 -> 1681.8642 | E5: =IF(H4<0.01,0,Sheet1!$C$6-D5) -> 1293.7923 | F5: =F4+D5+E5 -> 208926.97 | G5: =IFERROR(F5/(26.4*(1+3%)^A5),G4) -> 7683.3984 | H5: =H4-E5 -> 236145.86 | I5: =E5+I4 -> 203854.14
A6: =IF(ISBLANK(B6),"",CEILING(B6/12,1)) -> 1 | B6: 4 | D6: =H5*Sheet1!$C$5/12 -> 1672.6998 | E6: =IF(H5<0.01,0,Sheet1!$C$6-D6) -> 1302.9567 | F6: =F5+D6+E6 -> 211902.63 | G6: =IFERROR(F6/(26.4*(1+3%)^A6),G5) -> 7792.8297 | H6: =H5-E6 -> 234842.9 | I6: =E6+I5 -> 205157.1
A7: =IF(ISBLANK(B7),"",CEILING(B7/12,1)) -> 1 | B7: 5 | D7: =H6*Sheet1!$C$5/12 -> 1663.4706 | E7: =IF(H6<0.01,0,Sheet1!$C$6-D7) -> 1312.186 | F7: =F6+D7+E7 -> 214878.28 | G7: =IFERROR(F7/(26.4*(1+3%)^A7),G6) -> 7902.2611 | H7: =H6-E7 -> 233530.72 | I7: =E7+I6 -> 206469.28
A8: =IF(ISBLANK(B8),"",CEILING(B8/12,1)) -> 1 | B8: 6 | D8: =H7*Sheet1!$C$5/12 -> 1654.1759 | E8: =IF(H7<0.01,0,Sheet1!$C$6-D8) -> 1321.4806 | F8: =F7+D8+E8 -> 217853.94 | G8: =IFERROR(F8/(26.4*(1+3%)^A8),G7) -> 8011.6924 | H8: =H7-E8 -> 232209.24 | I8: =E8+I7 -> 207790.76
A9: =IF(ISBLANK(B9),"",CEILING(B9/12,1)) -> 1 | B9: 7 | D9: =H8*Sheet1!$C$5/12 -> 1644.8154 | E9: =IF(H8<0.01,0,Sheet1!$C$6-D9) -> 1330.8411 | F9: =F8+D9+E9 -> 220829.6 | G9: =IFERROR(F9/(26.4*(1+3%)^A9),G8) -> 8121.1237 | H9: =H8-E9 -> 230878.39 | I9: =E9+I8 -> 209121.61
A10: =IF(ISBLANK(B10),"",CEILING(B10/12,1)) -> 1 | B10: 8 | D10: =H9*Sheet1!$C$5/12 -> 1635.3886 | E10: =IF(H9<0.01,0,Sheet1!$C$6-D10) -> 1340.2679 | F10: =F9+D10+E10 -> 223805.25 | G10: =IFERROR(F10/(26.4*(1+3%)^A10),G9) -> 8230.555 | H10: =H9-E10 -> 229538.13 | I10: =E10+I9 -> 210461.87
A11: =IF(ISBLANK(B11),"",CEILING(B11/12,1)) -> 1 | B11: 9 | D11: =H10*Sheet1!$C$5/12 -> 1625.8951 | E11: =IF(H10<0.01,0,Sheet1!$C$6-D11) -> 1349.7615 | F11: =F10+D11+E11 -> 226780.91 | G11: =IFERROR(F11/(26.4*(1+3%)^A11),G10) -> 8339.9863 | H11: =H10-E11 -> 228188.36 | I11: =E11+I10 -> 211811.64
A12: =IF(ISBLANK(B12),"",CEILING(B12/12,1)) -> 1 | B12: 10 | D12: =H11*Sheet1!$C$5/12 -> 1616.3343 | E12: =IF(H11<0.01,0,Sheet1!$C$6-D12) -> 1359.3223 | F12: =F11+D12+E12 -> 229756.57 | G12: =IFERROR(F12/(26.4*(1+3%)^A12),G11) -> 8449.4177 | H12: =H11-E12 -> 226829.04 | I12: =E12+I11 -> 213170.96
A13: =IF(ISBLANK(B13),"",CEILING(B13/12,1)) -> 1 | B13: 11 | D13: =H12*Sheet1!$C$5/12 -> 1606.7057 | E13: =IF(H12<0.01,0,Sheet1!$C$6-D13) -> 1368.9508 | F13: =F12+D13+E13 -> 232732.22 | G13: =IFERROR(F13/(26.4*(1+3%)^A13),G12) -> 8558.849 | H13: =H12-E13 -> 225460.09 | I13: =E13+I12 -> 214539.91
A14: =IF(ISBLANK(B14),"",CEILING(B14/12,1)) -> 1 | B14: 12 | D14: =H13*Sheet1!$C$5/12 -> 1597.009 | E14: =IF(H13<0.01,0,Sheet1!$C$6-D14) -> 1378.6475 | F14: =F13+D14+E14 -> 235707.88 | G14: =IFERROR(F14/(26.4*(1+3%)^A14),G13) -> 8668.2803 | H14: =H13-E14 -> 224081.44 | I14: =E14+I13 -> 215918.56
A15: =IF(ISBLANK(B15),"",CEILING(B15/12,1)) -> 2 | B15: 13 | D15: =H14*Sheet1!$C$5/12 -> 1587.2436 | E15: =IF(H14<0.01,0,Sheet1!$C$6-D15) -> 1388.413 | F15: =F14+D15+E15 -> 238683.53 | G15: =IFERROR(F15/(26.4*(1+3%)^A15),G14) -> 8522.0501 | H15: =H14-E15 -> 222693.03 | I15: =E15+I14 -> 217306.97
... A122: =IF(ISBLANK(B122),"",CEILING(B122/12,1)) -> 10 | B122: 120 | D122: =H121*Sheet1!$C$5/12 -> 20.929318 | E122: =IF(H121<0.01,0,Sheet1!$C$6-D122) -> 2954.7272 | F122: =F121+D122+E122 -> 557078.78 | G122: =IFERROR(F122/(26.4*(1+3%)^A122),G121) -> 15701.475 | H122: =H121-E122 -> 8.9949026e-10 | I122: =E122+I121 -> 440000
A123: =IF(ISBLANK(B123),"",CEILING(B123/12,1)) | D123: =H122*Sheet1!$C$5/12 -> 6.3713893e-12 | E123: =IF(H122<0.01,0,Sheet1!$C$6-D123) -> 0 | F123: =F122+D123+E123 -> 557078.78 | G123: =IFERROR(F123/(26.4*(1+3%)^A123),G122) -> 15701.475 | H123: =H122-E123 -> 8.9949026e-10 | I123: =E123+I122 -> 440000
A124: =IF(ISBLANK(B124),"",CEILING(B124/12,1)) | D124: =H123*Sheet1!$C$5/12 -> 6.3713893e-12 | E124: =IF(H123<0.01,0,Sheet1!$C$6-D124) -> 0 | F124: =F123+D124+E124 -> 557078.78 | G124: =IFERROR(F124/(26.4*(1+3%)^A124),G123) -> 15701.475 | H124: =H123-E124 -> 8.9949026e-10 | I124: =E124+I123 -> 440000
A125: =IF(ISBLANK(B125),"",CEILING(B125/12,1)) | D125: =H124*Sheet1!$C$5/12 -> 6.3713893e-12 | E125: =IF(H124<0.01,0,Sheet1!$C$6-D125) -> 0 | F125: =F124+D125+E125 -> 557078.78 | G125: =IFERROR(F125/(26.4*(1+3%)^A125),G124) -> 15701.475 | H125: =H124-E125 -> 8.9949026e-10 | I125: =E125+I124 -> 440000
A126: =IF(ISBLANK(B126),"",CEILING(B126/12,1)) | D126: =H125*Sheet1!$C$5/12 -> 6.3713893e-12 | E126: =IF(H125<0.01,0,Sheet1!$C$6-D126) -> 0 | F126: =F125+D126+E126 -> 557078.78 | G126: =IFERROR(F126/(26.4*(1+3%)^A126),G125) -> 15701.475 | H126: =H125-E126 -> 8.9949026e-10 | I126: =E126+I125 -> 440000
A127: =IF(ISBLANK(B127),"",CEILING(B127/12,1)) | D127: =H126*Sheet1!$C$5/12 -> 6.3713893e-12 | E127: =IF(H126<0.01,0,Sheet1!$C$6-D127) -> 0 | F127: =F126+D127+E127 -> 557078.78 | G127: =IFERROR(F127/(26.4*(1+3%)^A127),G126) -> 15701.475 | H127: =H126-E127 -> 8.9949026e-10 | I127: =E127+I126 -> 440000
A128: =IF(ISBLANK(B128),"",CEILING(B128/12,1)) | D128: =H127*Sheet1!$C$5/12 -> 6.3713893e-12 | E128: =IF(H127<0.01,0,Sheet1!$C$6-D128) -> 0 | F128: =F127+D128+E128 -> 557078.78 | G128: =IFERROR(F128/(26.4*(1+3%)^A128),G127) -> 15701.475 | H128: =H127-E128 -> 8.9949026e-10 | I128: =E128+I127 -> 440000
A129: =IF(ISBLANK(B129),"",CEILING(B129/12,1)) | D129: =H128*Sheet1!$C$5/12 -> 6.3713893e-12 | E129: =IF(H128<0.01,0,Sheet1!$C$6-D129) -> 0 | F129: =F128+D129+E129 -> 557078.78 | G129: =IFERROR(F129/(26.4*(1+3%)^A129),G128) -> 15701.475 | H129: =H128-E129 -> 8.9949026e-10 | I129: =E129+I128 -> 440000
A130: =IF(ISBLANK(B130),"",CEILING(B130/12,1)) | D130: =H129*Sheet1!$C$5/12 -> 6.3713893e-12 | E130: =IF(H129<0.01,0,Sheet1!$C$6-D130) -> 0 | F130: =F129+D130+E130 -> 557078.78 | G130: =IFERROR(F130/(26.4*(1+3%)^A130),G129) -> 15701.475 | H130: =H129-E130 -> 8.9949026e-10 | I130: =E130+I129 -> 440000
A131: =IF(ISBLANK(B131),"",CEILING(B131/12,1)) | D131: =H130*Sheet1!$C$5/12 -> 6.3713893e-12 | E131: =IF(H130<0.01,0,Sheet1!$C$6-D131) -> 0 | F131: =F130+D131+E131 -> 557078.78 | G131: =IFERROR(F131/(26.4*(1+3%)^A131),G130) -> 15701.475 | H131: =H130-E131 -> 8.9949026e-10 | I131: =E131+I130 -> 440000
A132: =IF(ISBLANK(B132),"",CEILING(B132/12,1)) | D132: =H131*Sheet1!$C$5/12 -> 6.3713893e-12 | E132: =IF(H131<0.01,0,Sheet1!$C$6-D132) -> 0 | F132: =F131+D132+E132 -> 557078.78 | G132: =IFERROR(F132/(26.4*(1+3%)^A132),G131) -> 15701.475 | H132: =H131-E132 -> 8.9949026e-10 | I132: =E132+I131 -> 440000
A133: =IF(ISBLANK(B133),"",CEILING(B133/12,1)) | D133: =H132*Sheet1!$C$5/12 -> 6.3713893e-12 | E133: =IF(H132<0.01,0,Sheet1!$C$6-D133) -> 0 | F133: =F132+D133+E133 -> 557078.78 | G133: =IFERROR(F133/(26.4*(1+3%)^A133),G132) -> 15701.475 | H133: =H132-E133 -> 8.9949026e-10 | I133: =E133+I132 -> 440000
A134: =IF(ISBLANK(B134),"",CEILING(B134/12,1)) | D134: =H133*Sheet1!$C$5/12 -> 6.3713893e-12 | E134: =IF(H133<0.01,0,Sheet1!$C$6-D134) -> 0 | F134: =F133+D134+E134 -> 557078.78 | G134: =IFERROR(F134/(26.4*(1+3%)^A134),G133) -> 15701.475 | H134: =H133-E134 -> 8.9949026e-10 | I134: =E134+I133 -> 440000
... A361: =IF(ISBLANK(B361),"",CEILING(B361/12,1)) | D361: =H360*Sheet1!$C$5/12 -> 6.3713893e-12 | E361: =IF(H360<0.01,0,Sheet1!$C$6-D361) -> 0 | F361: =F360+D361+E361 -> 557078.78 | G361: =IFERROR(F361/(26.4*(1+3%)^A361),G360) -> 15701.475 | H361: =H360-E361 -> 8.9949026e-10 | I361: =E361+I360 -> 440000
A362: =IF(ISBLANK(B362),"",CEILING(B362/12,1)) | D362: =H361*Sheet1!$C$5/12 -> 6.3713893e-12 | E362: =IF(H361<0.01,0,Sheet1!$C$6-D362) -> 0 | F362: =F361+D362+E362 -> 557078.78 | G362: =IFERROR(F362/(26.4*(1+3%)^A362),G361) -> 15701.475 | H362: =H361-E362 -> 8.9949026e-10 | I362: =E362+I361 -> 440000 | K362: =F362/G362 -> 35.479392
