Workbook

Sheet Sheet2
A1: TICK | B1: (All)
A2: CURR | B2: (All)
A4: Sum of VALUE
A5: Row Labels | B5: 2016 | C5: 2017 | D5: 2018 | E5: 2019 | F5: 2020 | G5: 2021 | H5: 2022 | I5: 2023 | J5: 2024 | K5: Grand Total
A6: Revenue | B6: 4958000000 | C6: 5509000000 | D6: 7370000000 | E6: 6547000000 | F6: 4442000000 | G6: 8154000000 | H6: 12158000000 | I6: 8289000000 | J6: 9749000000 | K6: 67176000000
A7: Investment income | B7: 8000000 | C7: 19000000 | D7: 22000000 | E7: 13000000 | F7: 7000000 | G7: 8000000 | H7: 10000000 | I7: 10000000 | J7: 12000000 | K7: 109000000
A8: Other Revenue | B8: -417000000 | C8: -397000000 | D8: 0 | E8: 43000000 | F8: 0 | G8: 161000000 | H8: 1073000000 | I8: 0 | J8: 0 | K8: 463000000
A9: Revenue | B9: 5367000000 | C9: 5887000000 | D9: 7348000000 | E9: 6491000000 | F9: 4435000000 | G9: 7985000000 | H9: 11075000000 | I9: 8279000000 | J9: 9737000000 | K9: 66604000000
A10: Cost of Revenue | B10: 8624000000 | C10: 7718000000 | D10: 8384000000 | E10: 9150000000 | F10: 7060000000 | G10: 8890000000 | H10: 9640000000 | I10: 8104000000 | J10: 10870000000 | K10: 78440000000
A11: Gross Profit | B11: 1055000000 | C11: 2028000000 | D11: 3156000000 | E11: 1916000000 | F11: 905000000 | G11: 3540000000 | H11: 6255000000 | I11: 4227000000 | J11: 4302000000 | K11: 27384000000
A12: Operating Expenses | B12: 1199000000 | C12: 1181000000 | D12: 1187000000 | E12: 1471000000 | F12: 732000000 | G12: 848000000 | H12: 1173000000 | I12: 869000000 | J12: 1103000000 | K12: 9763000000
A13: Operating Income | B13: -144000000 | C13: 847000000 | D13: 1969000000 | E13: 445000000 | F13: 173000000 | G13: 2692000000 | H13: 5082000000 | I13: 3358000000 | J13: 3199000000 | K13: 17621000000
A14: Operating Income | B14: -144000000 | C14: 847000000 | D14: 1969000000 | E14: 445000000 | F14: 173000000 | G14: 2692000000 | H14: 5082000000 | I14: 3358000000 | J14: 3199000000 | K14: 17621000000
A15: Interest & Other | B15: 1000000 | C15: 1000000 | D15: 94000000 | E15: 13000000 | F15: 7000000 | G15: -96000000 | H15: 10000000 | I15: 10000000 | J15: 12000000 | K15: 52000000
A16: Interest Expense | B16: 417000000 | C16: 397000000 | D16: 478000000 | E16: 400000000 | F16: 434000000 | G16: 418000000 | H16: 322000000 | I16: 331000000 | J16: 379000000 | K16: 3576000000
A17: Net Int. Income | B17: -416000000 | C17: -396000000 | D17: -384000000 | E17: -387000000 | F17: -427000000 | G17: -514000000 | H17: -312000000 | I17: -321000000 | J17: -367000000 | K17: -3524000000
... A23: Grand Total | B23: 10924000000 | C23: 20424000000 | D23: 24116000000 | E23: 11345000000 | F23: -1145000000 | G23: 29034000000 | H23: 49460000000 | I23: 33478000000 | J23: 33109000000 | K23: 210745000000
A27: GP% | B27: =B11/B9 -> 0.19657164 | C27: =C11/C9 -> 0.34448785 | D27: =D11/D9 -> 0.42950463 | E27: =E11/E9 -> 0.29517794 | F27: =F11/F9 -> 0.20405862 | G27: =G11/G9 -> 0.44333125 | H27: =H11/H9 -> 0.56478555 | I27: =I11/I9 -> 0.51056891 | J27: =J11/J9 -> 0.44181986 | K27: =K11/K6 -> 0.40764559 | L27: =L11/L6 -> #DIV/0! | M27: =M11/M6 -> #DIV/0! | N27: =N11/N6 -> #DIV/0! | O27: =O11/O6 -> #DIV/0! | P27: =P11/P6 -> #DIV/0! | Q27: =Q11/Q6 -> #DIV/0! | R27: =R11/R6 -> #DIV/0! | ... V27: =V11/V6 -> #DIV/0!
A28: Net Income % | B28: =B21/B9 -> -0.49282653 | C28: =C21/C9 -> 0.47681332 | D28: =D21/D9 -> 0.044365814 | E28: =E21/E9 -> -0.90325065 | F28: =F21/F9 -> -2.1844419 | G28: =G21/G9 -> 0.31772073 | H28: =H21/H9 -> 0.70031603 | I28: =I21/I9 -> 0.73221404 | J28: =J21/J9 -> 0.19739139 | K28: =K21/K6 -> 0.047844468 | L28: =L21/L6 -> #DIV/0! | M28: =M21/M6 -> #DIV/0! | N28: =N21/N6 -> #DIV/0! | O28: =O21/O6 -> #DIV/0! | P28: =P21/P6 -> #DIV/0! | Q28: =Q21/Q6 -> #DIV/0! | R28: =R21/R6 -> #DIV/0! | ... V28: =V21/V6 -> #DIV/0!
A29: # Shares Millions | B29: 379 | C29: 381 | D29: 375 | E29: 376 | F29: 377 | G29: 347 | H29: 312 | I29: 304 | J29: 365 | K29: =SUM(B29:J29) -> 3216
A30: EPS | B30: =B21/(B29*1000000) -> -6.9788918 | C30: =C21/(C29*1000000) -> 7.3674541 | D30: =D21/(D29*1000000) -> 0.86933333 | E30: =E21/(E29*1000000) -> -15.593085 | F30: =F21/(F29*1000000) -> -25.697613 | G30: =G21/(G29*1000000) -> 7.3112392 | H30: =H21/(H29*1000000) -> 24.858974 | I30: =I21/(I29*1000000) -> 19.940789 | ... K30: =K21/(K29*1000000) -> 0.99937811
A31: SPS | B31: =B9/(B29*1000000) -> 14.16095 | C31: =C9/(C29*1000000) -> 15.451444 | D31: =D9/(D29*1000000) -> 19.594667 | E31: =E9/(E29*1000000) -> 17.263298 | F31: =F9/(F29*1000000) -> 11.763926 | G31: =G9/(G29*1000000) -> 23.011527 | H31: =H9/(H29*1000000) -> 35.496795 | I31: =I9/(I29*1000000) -> 27.233553 | ... K31: =K9/(K29*1000000) -> 20.710199

Sheet MAP
A1: Section | B1: Row Label | C1: Section | D1: Description / Notes | E1: Short Name
A2: Revenue | B2: totalRevenue | C2: Revenue | D2: Total sales and operating revenue | E2: Revenue
A3: Revenue | B3: investmentIncomeNet | C3: Revenue | D3: Net investment income | E3: Investment income
A4: Revenue | B4: interestIncome | C4: Revenue | D4: Interest earned | E4: Investment income
A5: Revenue | B5: nonInterestIncome | C5: Revenue | D5: Other non-interest income | E5: Other Revenue
A6: Revenue | B6: otherNonOperatingIncome | C6: Revenue | D6: Other income not from core operations | E6: Other Revenue
A7: Cost of Revenue | B7: costOfRevenue | C7: Cost of Revenue | D7: Direct costs of revenue | E7: COGS
A8: Cost of Revenue | B8: costofGoodsAndServicesSold | C8: Cost of Revenue | D8: Direct costs of goods/services sold | E8: COGS
A9: Gross Profit | B9: grossProfit | C9: Gross Profit | D9: Revenue minus cost of revenue | E9: Gross Profit
A10: Operating Expenses | B10: sellingGeneralAndAdministrative | C10: Operating Expenses | D10: SG&A expenses | E10: SG&A
A11: Operating Expenses | B11: researchAndDevelopment | C11: Operating Expenses | D11: R&D expenses | E11: R&D
A12: Operating Expenses | B12: operatingExpenses | C12: Operating Expenses | D12: Other operating expenses | E12: OPEX
... A25: Comprehensive Income | B25: comprehensiveIncomeNetOfTax | C25: Comprehensive Income | D25: Net comprehensive income after tax | E25: Comp. Income

Sheet Sheet1
A1: TICK | B1: DATE | C1: CURR | D1: DATUM | E1: VALUE | F1: RECORD_DATE | G1: DATUM_LVL1 | H1: DATUM_LVL2
A2: APA | B2: 45657 | C2: USD | D2: grossProfit | E2: 4302000000 | F2: 45986.119 | G2: =VLOOKUP(D2,MAP!B:C,2,0) -> Gross Profit | H2: =VLOOKUP(D2,MAP!B:G,4,0) -> Gross Profit
A3: APA | B3: 45291 | C3: USD | D3: grossProfit | E3: 4227000000 | F3: 45986.119 | G3: =VLOOKUP(D3,MAP!B:C,2,0) -> Gross Profit | H3: =VLOOKUP(D3,MAP!B:G,4,0) -> Gross Profit
A4: APA | B4: 44926 | C4: USD | D4: grossProfit | E4: 6255000000 | F4: 45986.119 | G4: =VLOOKUP(D4,MAP!B:C,2,0) -> Gross Profit | H4: =VLOOKUP(D4,MAP!B:G,4,0) -> Gross Profit
A5: APA | B5: 44561 | C5: USD | D5: grossProfit | E5: 3540000000 | F5: 45986.119 | G5: =VLOOKUP(D5,MAP!B:C,2,0) -> Gross Profit | H5: =VLOOKUP(D5,MAP!B:G,4,0) -> Gross Profit
A6: APA | B6: 44196 | C6: USD | D6: grossProfit | E6: 905000000 | F6: 45986.119 | G6: =VLOOKUP(D6,MAP!B:C,2,0) -> Gross Profit | H6: =VLOOKUP(D6,MAP!B:G,4,0) -> Gross Profit
A7: APA | B7: 43830 | C7: USD | D7: grossProfit | E7: 1916000000 | F7: 45986.119 | G7: =VLOOKUP(D7,MAP!B:C,2,0) -> Gross Profit | H7: =VLOOKUP(D7,MAP!B:G,4,0) -> Gross Profit
A8: APA | B8: 43465 | C8: USD | D8: grossProfit | E8: 3156000000 | F8: 45986.119 | G8: =VLOOKUP(D8,MAP!B:C,2,0) -> Gross Profit | H8: =VLOOKUP(D8,MAP!B:G,4,0) -> Gross Profit
A9: APA | B9: 43100 | C9: USD | D9: grossProfit | E9: 2028000000 | F9: 45986.119 | G9: =VLOOKUP(D9,MAP!B:C,2,0) -> Gross Profit | H9: =VLOOKUP(D9,MAP!B:G,4,0) -> Gross Profit
A10: APA | B10: 42735 | C10: USD | D10: grossProfit | E10: 1055000000 | F10: 45986.119 | G10: =VLOOKUP(D10,MAP!B:C,2,0) -> Gross Profit | H10: =VLOOKUP(D10,MAP!B:G,4,0) -> Gross Profit
A11: APA | B11: 42369 | C11: USD | D11: grossProfit | E11: -25054000000 | F11: 45986.119 | G11: =VLOOKUP(D11,MAP!B:C,2,0) -> Gross Profit | H11: =VLOOKUP(D11,MAP!B:G,4,0) -> Gross Profit
A12: APA | B12: 42004 | C12: USD | D12: grossProfit | E12: 839000000 | F12: 45986.119 | G12: =VLOOKUP(D12,MAP!B:C,2,0) -> Gross Profit | H12: =VLOOKUP(D12,MAP!B:G,4,0) -> Gross Profit
A13: APA | B13: 41639 | C13: USD | D13: grossProfit | E13: 6349000000 | F13: 45986.119 | G13: =VLOOKUP(D13,MAP!B:C,2,0) -> Gross Profit | H13: =VLOOKUP(D13,MAP!B:G,4,0) -> Gross Profit
... A121: APA | B121: 38717 | C121: USD | D121: sellingGeneralAndAdministrative | E121: 198272000 | F121: 45986.119 | G121: =VLOOKUP(D121,MAP!B:C,2,0) -> Operating Expenses | H121: =VLOOKUP(D121,MAP!B:G,4,0) -> SG&A
A122: APA | B122: 45657 | C122: USD | D122: researchAndDevelopment | F122: 45986.119 | G122: =VLOOKUP(D122,MAP!B:C,2,0) -> Operating Expenses | H122: =VLOOKUP(D122,MAP!B:G,4,0) -> R&D
A123: APA | B123: 45291 | C123: USD | D123: researchAndDevelopment | F123: 45986.119 | G123: =VLOOKUP(D123,MAP!B:C,2,0) -> Operating Expenses | H123: =VLOOKUP(D123,MAP!B:G,4,0) -> R&D
A124: APA | B124: 44926 | C124: USD | D124: researchAndDevelopment | F124: 45986.119 | G124: =VLOOKUP(D124,MAP!B:C,2,0) -> Operating Expenses | H124: =VLOOKUP(D124,MAP!B:G,4,0) -> R&D
A125: APA | B125: 44561 | C125: USD | D125: researchAndDevelopment | F125: 45986.119 | G125: =VLOOKUP(D125,MAP!B:C,2,0) -> Operating Expenses | H125: =VLOOKUP(D125,MAP!B:G,4,0) -> R&D
A126: APA | B126: 44196 | C126: USD | D126: researchAndDevelopment | F126: 45986.119 | G126: =VLOOKUP(D126,MAP!B:C,2,0) -> Operating Expenses | H126: =VLOOKUP(D126,MAP!B:G,4,0) -> R&D
A127: APA | B127: 43830 | C127: USD | D127: researchAndDevelopment | F127: 45986.119 | G127: =VLOOKUP(D127,MAP!B:C,2,0) -> Operating Expenses | H127: =VLOOKUP(D127,MAP!B:G,4,0) -> R&D
A128: APA | B128: 43465 | C128: USD | D128: researchAndDevelopment | E128: 0 | F128: 45986.119 | G128: =VLOOKUP(D128,MAP!B:C,2,0) -> Operating Expenses | H128: =VLOOKUP(D128,MAP!B:G,4,0) -> R&D
A129: APA | B129: 43100 | C129: USD | D129: researchAndDevelopment | E129: 0 | F129: 45986.119 | G129: =VLOOKUP(D129,MAP!B:C,2,0) -> Operating Expenses | H129: =VLOOKUP(D129,MAP!B:G,4,0) -> R&D
A130: APA | B130: 42735 | C130: USD | D130: researchAndDevelopment | E130: 0 | F130: 45986.119 | G130: =VLOOKUP(D130,MAP!B:C,2,0) -> Operating Expenses | H130: =VLOOKUP(D130,MAP!B:G,4,0) -> R&D
A131: APA | B131: 42369 | C131: USD | D131: researchAndDevelopment | E131: 0 | F131: 45986.119 | G131: =VLOOKUP(D131,MAP!B:C,2,0) -> Operating Expenses | H131: =VLOOKUP(D131,MAP!B:G,4,0) -> R&D
A132: APA | B132: 42004 | C132: USD | D132: researchAndDevelopment | E132: 0 | F132: 45986.119 | G132: =VLOOKUP(D132,MAP!B:C,2,0) -> Operating Expenses | H132: =VLOOKUP(D132,MAP!B:G,4,0) -> R&D
A133: APA | B133: 41639 | C133: USD | D133: researchAndDevelopment | E133: 0 | F133: 45986.119 | G133: =VLOOKUP(D133,MAP!B:C,2,0) -> Operating Expenses | H133: =VLOOKUP(D133,MAP!B:G,4,0) -> R&D
A134: APA | B134: 41274 | C134: USD | D134: researchAndDevelopment | E134: 0 | F134: 45986.119 | G134: =VLOOKUP(D134,MAP!B:C,2,0) -> Operating Expenses | H134: =VLOOKUP(D134,MAP!B:G,4,0) -> R&D
A135: APA | B135: 40908 | C135: USD | D135: researchAndDevelopment | E135: 0 | F135: 45986.119 | G135: =VLOOKUP(D135,MAP!B:C,2,0) -> Operating Expenses | H135: =VLOOKUP(D135,MAP!B:G,4,0) -> R&D
A136: APA | B136: 40543 | C136: USD | D136: researchAndDevelopment | E136: 0 | F136: 45986.119 | G136: =VLOOKUP(D136,MAP!B:C,2,0) -> Operating Expenses | H136: =VLOOKUP(D136,MAP!B:G,4,0) -> R&D
A137: APA | B137: 40178 | C137: USD | D137: researchAndDevelopment | E137: 0 | F137: 45986.119 | G137: =VLOOKUP(D137,MAP!B:C,2,0) -> Operating Expenses | H137: =VLOOKUP(D137,MAP!B:G,4,0) -> R&D
A138: APA | B138: 39813 | C138: USD | D138: researchAndDevelopment | F138: 45986.119 | G138: =VLOOKUP(D138,MAP!B:C,2,0) -> Operating Expenses | H138: =VLOOKUP(D138,MAP!B:G,4,0) -> R&D
A139: APA | B139: 39447 | C139: USD | D139: researchAndDevelopment | F139: 45986.119 | G139: =VLOOKUP(D139,MAP!B:C,2,0) -> Operating Expenses | H139: =VLOOKUP(D139,MAP!B:G,4,0) -> R&D
A140: APA | B140: 39082 | C140: USD | D140: researchAndDevelopment | F140: 45986.119 | G140: =VLOOKUP(D140,MAP!B:C,2,0) -> Operating Expenses | H140: =VLOOKUP(D140,MAP!B:G,4,0) -> R&D
A141: APA | B141: 38717 | C141: USD | D141: researchAndDevelopment | F141: 45986.119 | G141: =VLOOKUP(D141,MAP!B:C,2,0) -> Operating Expenses | H141: =VLOOKUP(D141,MAP!B:G,4,0) -> R&D
A142: APA | B142: 45657 | C142: USD | D142: operatingExpenses | E142: 1103000000 | F142: 45986.119 | G142: =VLOOKUP(D142,MAP!B:C,2,0) -> Operating Expenses | H142: =VLOOKUP(D142,MAP!B:G,4,0) -> OPEX
A143: APA | B143: 45291 | C143: USD | D143: operatingExpenses | E143: 869000000 | F143: 45986.119 | G143: =VLOOKUP(D143,MAP!B:C,2,0) -> Operating Expenses | H143: =VLOOKUP(D143,MAP!B:G,4,0) -> OPEX
A144: APA | B144: 44926 | C144: USD | D144: operatingExpenses | E144: 1173000000 | F144: 45986.119 | G144: =VLOOKUP(D144,MAP!B:C,2,0) -> Operating Expenses | H144: =VLOOKUP(D144,MAP!B:G,4,0) -> OPEX
A145: APA | B145: 44561 | C145: USD | D145: operatingExpenses | E145: 848000000 | F145: 45986.119 | G145: =VLOOKUP(D145,MAP!B:C,2,0) -> Operating Expenses | H145: =VLOOKUP(D145,MAP!B:G,4,0) -> OPEX
A146: APA | B146: 44196 | C146: USD | D146: operatingExpenses | E146: 732000000 | F146: 45986.119 | G146: =VLOOKUP(D146,MAP!B:C,2,0) -> Operating Expenses | H146: =VLOOKUP(D146,MAP!B:G,4,0) -> OPEX
A147: APA | B147: 43830 | C147: USD | D147: operatingExpenses | E147: 1471000000 | F147: 45986.119 | G147: =VLOOKUP(D147,MAP!B:C,2,0) -> Operating Expenses | H147: =VLOOKUP(D147,MAP!B:G,4,0) -> OPEX
A148: APA | B148: 43465 | C148: USD | D148: operatingExpenses | E148: 1187000000 | F148: 45986.119 | G148: =VLOOKUP(D148,MAP!B:C,2,0) -> Operating Expenses | H148: =VLOOKUP(D148,MAP!B:G,4,0) -> OPEX
A149: APA | B149: 43100 | C149: USD | D149: operatingExpenses | E149: 1181000000 | F149: 45986.119 | G149: =VLOOKUP(D149,MAP!B:C,2,0) -> Operating Expenses | H149: =VLOOKUP(D149,MAP!B:G,4,0) -> OPEX
A150: APA | B150: 42735 | C150: USD | D150: operatingExpenses | E150: 1199000000 | F150: 45986.119 | G150: =VLOOKUP(D150,MAP!B:C,2,0) -> Operating Expenses | H150: =VLOOKUP(D150,MAP!B:G,4,0) -> OPEX
A151: APA | B151: 42369 | C151: USD | D151: operatingExpenses | E151: 821000000 | F151: 45986.119 | G151: =VLOOKUP(D151,MAP!B:C,2,0) -> Operating Expenses | H151: =VLOOKUP(D151,MAP!B:G,4,0) -> OPEX
A152: APA | B152: 42004 | C152: USD | D152: operatingExpenses | E152: 1475000000 | F152: 45986.119 | G152: =VLOOKUP(D152,MAP!B:C,2,0) -> Operating Expenses | H152: =VLOOKUP(D152,MAP!B:G,4,0) -> OPEX
A153: APA | B153: 41639 | C153: USD | D153: operatingExpenses | E153: 1527000000 | F153: 45986.119 | G153: =VLOOKUP(D153,MAP!B:C,2,0) -> Operating Expenses | H153: =VLOOKUP(D153,MAP!B:G,4,0) -> OPEX
... A161: APA | B161: 38717 | C161: USD | D161: operatingExpenses | E161: 2067212000 | F161: 45986.119 | G161: =VLOOKUP(D161,MAP!B:C,2,0) -> Operating Expenses | H161: =VLOOKUP(D161,MAP!B:G,4,0) -> OPEX
A162: APA | B162: 45657 | C162: USD | D162: investmentIncomeNet | F162: 45986.119 | G162: =VLOOKUP(D162,MAP!B:C,2,0) -> Revenue | H162: =VLOOKUP(D162,MAP!B:G,4,0) -> Investment income
A163: APA | B163: 45291 | C163: USD | D163: investmentIncomeNet | F163: 45986.119 | G163: =VLOOKUP(D163,MAP!B:C,2,0) -> Revenue | H163: =VLOOKUP(D163,MAP!B:G,4,0) -> Investment income
A164: APA | B164: 44926 | C164: USD | D164: investmentIncomeNet | F164: 45986.119 | G164: =VLOOKUP(D164,MAP!B:C,2,0) -> Revenue | H164: =VLOOKUP(D164,MAP!B:G,4,0) -> Investment income
A165: APA | B165: 44561 | C165: USD | D165: investmentIncomeNet | F165: 45986.119 | G165: =VLOOKUP(D165,MAP!B:C,2,0) -> Revenue | H165: =VLOOKUP(D165,MAP!B:G,4,0) -> Investment income
A166: APA | B166: 44196 | C166: USD | D166: investmentIncomeNet | F166: 45986.119 | G166: =VLOOKUP(D166,MAP!B:C,2,0) -> Revenue | H166: =VLOOKUP(D166,MAP!B:G,4,0) -> Investment income
A167: APA | B167: 43830 | C167: USD | D167: investmentIncomeNet | F167: 45986.119 | G167: =VLOOKUP(D167,MAP!B:C,2,0) -> Revenue | H167: =VLOOKUP(D167,MAP!B:G,4,0) -> Investment income
A168: APA | B168: 43465 | C168: USD | D168: investmentIncomeNet | F168: 45986.119 | G168: =VLOOKUP(D168,MAP!B:C,2,0) -> Revenue | H168: =VLOOKUP(D168,MAP!B:G,4,0) -> Investment income
A169: APA | B169: 43100 | C169: USD | D169: investmentIncomeNet | F169: 45986.119 | G169: =VLOOKUP(D169,MAP!B:C,2,0) -> Revenue | H169: =VLOOKUP(D169,MAP!B:G,4,0) -> Investment income
A170: APA | B170: 42735 | C170: USD | D170: investmentIncomeNet | F170: 45986.119 | G170: =VLOOKUP(D170,MAP!B:C,2,0) -> Revenue | H170: =VLOOKUP(D170,MAP!B:G,4,0) -> Investment income
A171: APA | B171: 42369 | C171: USD | D171: investmentIncomeNet | F171: 45986.119 | G171: =VLOOKUP(D171,MAP!B:C,2,0) -> Revenue | H171: =VLOOKUP(D171,MAP!B:G,4,0) -> Investment income
A172: APA | B172: 42004 | C172: USD | D172: investmentIncomeNet | F172: 45986.119 | G172: =VLOOKUP(D172,MAP!B:C,2,0) -> Revenue | H172: =VLOOKUP(D172,MAP!B:G,4,0) -> Investment income
A173: APA | B173: 41639 | C173: USD | D173: investmentIncomeNet | F173: 45986.119 | G173: =VLOOKUP(D173,MAP!B:C,2,0) -> Revenue | H173: =VLOOKUP(D173,MAP!B:G,4,0) -> Investment income
... A181: APA | B181: 38717 | C181: USD | D181: investmentIncomeNet | F181: 45986.119 | G181: =VLOOKUP(D181,MAP!B:C,2,0) -> Revenue | H181: =VLOOKUP(D181,MAP!B:G,4,0) -> Investment income
A182: APA | B182: 45657 | C182: USD | D182: netInterestIncome | E182: -367000000 | F182: 45986.119 | G182: =VLOOKUP(D182,MAP!B:C,2,0) -> Interest & Other | H182: =VLOOKUP(D182,MAP!B:G,4,0) -> Net Int. Income
A183: APA | B183: 45291 | C183: USD | D183: netInterestIncome | E183: -321000000 | F183: 45986.119 | G183: =VLOOKUP(D183,MAP!B:C,2,0) -> Interest & Other | H183: =VLOOKUP(D183,MAP!B:G,4,0) -> Net Int. Income
A184: APA | B184: 44926 | C184: USD | D184: netInterestIncome | E184: -312000000 | F184: 45986.119 | G184: =VLOOKUP(D184,MAP!B:C,2,0) -> Interest & Other | H184: =VLOOKUP(D184,MAP!B:G,4,0) -> Net Int. Income
A185: APA | B185: 44561 | C185: USD | D185: netInterestIncome | E185: -514000000 | F185: 45986.119 | G185: =VLOOKUP(D185,MAP!B:C,2,0) -> Interest & Other | H185: =VLOOKUP(D185,MAP!B:G,4,0) -> Net Int. Income
A186: APA | B186: 44196 | C186: USD | D186: netInterestIncome | E186: -427000000 | F186: 45986.119 | G186: =VLOOKUP(D186,MAP!B:C,2,0) -> Interest & Other | H186: =VLOOKUP(D186,MAP!B:G,4,0) -> Net Int. Income
A187: APA | B187: 43830 | C187: USD | D187: netInterestIncome | E187: -387000000 | F187: 45986.119 | G187: =VLOOKUP(D187,MAP!B:C,2,0) -> Interest & Other | H187: =VLOOKUP(D187,MAP!B:G,4,0) -> Net Int. Income
A188: APA | B188: 43465 | C188: USD | D188: netInterestIncome | E188: -384000000 | F188: 45986.119 | G188: =VLOOKUP(D188,MAP!B:C,2,0) -> Interest & Other | H188: =VLOOKUP(D188,MAP!B:G,4,0) -> Net Int. Income
A189: APA | B189: 43100 | C189: USD | D189: netInterestIncome | E189: -396000000 | F189: 45986.119 | G189: =VLOOKUP(D189,MAP!B:C,2,0) -> Interest & Other | H189: =VLOOKUP(D189,MAP!B:G,4,0) -> Net Int. Income
A190: APA | B190: 42735 | C190: USD | D190: netInterestIncome | E190: -416000000 | F190: 45986.119 | G190: =VLOOKUP(D190,MAP!B:C,2,0) -> Interest & Other | H190: =VLOOKUP(D190,MAP!B:G,4,0) -> Net Int. Income
A191: APA | B191: 42369 | C191: USD | D191: netInterestIncome | F191: 45986.119 | G191: =VLOOKUP(D191,MAP!B:C,2,0) -> Interest & Other | H191: =VLOOKUP(D191,MAP!B:G,4,0) -> Net Int. Income
A192: APA | B192: 42004 | C192: USD | D192: netInterestIncome | F192: 45986.119 | G192: =VLOOKUP(D192,MAP!B:C,2,0) -> Interest & Other | H192: =VLOOKUP(D192,MAP!B:G,4,0) -> Net Int. Income
A193: APA | B193: 41639 | C193: USD | D193: netInterestIncome | F193: 45986.119 | G193: =VLOOKUP(D193,MAP!B:C,2,0) -> Interest & Other | H193: =VLOOKUP(D193,MAP!B:G,4,0) -> Net Int. Income
A194: APA | B194: 41274 | C194: USD | D194: netInterestIncome | F194: 45986.119 | G194: =VLOOKUP(D194,MAP!B:C,2,0) -> Interest & Other | H194: =VLOOKUP(D194,MAP!B:G,4,0) -> Net Int. Income
A195: APA | B195: 40908 | C195: USD | D195: netInterestIncome | F195: 45986.119 | G195: =VLOOKUP(D195,MAP!B:C,2,0) -> Interest & Other | H195: =VLOOKUP(D195,MAP!B:G,4,0) -> Net Int. Income
A196: APA | B196: 40543 | C196: USD | D196: netInterestIncome | F196: 45986.119 | G196: =VLOOKUP(D196,MAP!B:C,2,0) -> Interest & Other | H196: =VLOOKUP(D196,MAP!B:G,4,0) -> Net Int. Income
A197: APA | B197: 40178 | C197: USD | D197: netInterestIncome | F197: 45986.119 | G197: =VLOOKUP(D197,MAP!B:C,2,0) -> Interest & Other | H197: =VLOOKUP(D197,MAP!B:G,4,0) -> Net Int. Income
A198: APA | B198: 39813 | C198: USD | D198: netInterestIncome | F198: 45986.119 | G198: =VLOOKUP(D198,MAP!B:C,2,0) -> Interest & Other | H198: =VLOOKUP(D198,MAP!B:G,4,0) -> Net Int. Income
A199: APA | B199: 39447 | C199: USD | D199: netInterestIncome | F199: 45986.119 | G199: =VLOOKUP(D199,MAP!B:C,2,0) -> Interest & Other | H199: =VLOOKUP(D199,MAP!B:G,4,0) -> Net Int. Income
A200: APA | B200: 39082 | C200: USD | D200: netInterestIncome | F200: 45986.119 | G200: =VLOOKUP(D200,MAP!B:C,2,0) -> Interest & Other | H200: =VLOOKUP(D200,MAP!B:G,4,0) -> Net Int. Income
A201: APA | B201: 38717 | C201: USD | D201: netInterestIncome | F201: 45986.119 | G201: =VLOOKUP(D201,MAP!B:C,2,0) -> Interest & Other | H201: =VLOOKUP(D201,MAP!B:G,4,0) -> Net Int. Income
A202: APA | B202: 45657 | C202: USD | D202: interestIncome | E202: 12000000 | F202: 45986.119 | G202: =VLOOKUP(D202,MAP!B:C,2,0) -> Revenue | H202: =VLOOKUP(D202,MAP!B:G,4,0) -> Investment income
A203: APA | B203: 45291 | C203: USD | D203: interestIncome | E203: 10000000 | F203: 45986.119 | G203: =VLOOKUP(D203,MAP!B:C,2,0) -> Revenue | H203: =VLOOKUP(D203,MAP!B:G,4,0) -> Investment income
A204: APA | B204: 44926 | C204: USD | D204: interestIncome | E204: 10000000 | F204: 45986.119 | G204: =VLOOKUP(D204,MAP!B:C,2,0) -> Revenue | H204: =VLOOKUP(D204,MAP!B:G,4,0) -> Investment income
A205: APA | B205: 44561 | C205: USD | D205: interestIncome | E205: 8000000 | F205: 45986.119 | G205: =VLOOKUP(D205,MAP!B:C,2,0) -> Revenue | H205: =VLOOKUP(D205,MAP!B:G,4,0) -> Investment income
A206: APA | B206: 44196 | C206: USD | D206: interestIncome | E206: 7000000 | F206: 45986.119 | G206: =VLOOKUP(D206,MAP!B:C,2,0) -> Revenue | H206: =VLOOKUP(D206,MAP!B:G,4,0) -> Investment income
A207: APA | B207: 43830 | C207: USD | D207: interestIncome | E207: 13000000 | F207: 45986.119 | G207: =VLOOKUP(D207,MAP!B:C,2,0) -> Revenue | H207: =VLOOKUP(D207,MAP!B:G,4,0) -> Investment income
A208: APA | B208: 43465 | C208: USD | D208: interestIncome | E208: 22000000 | F208: 45986.119 | G208: =VLOOKUP(D208,MAP!B:C,2,0) -> Revenue | H208: =VLOOKUP(D208,MAP!B:G,4,0) -> Investment income
A209: APA | B209: 43100 | C209: USD | D209: interestIncome | E209: 19000000 | F209: 45986.119 | G209: =VLOOKUP(D209,MAP!B:C,2,0) -> Revenue | H209: =VLOOKUP(D209,MAP!B:G,4,0) -> Investment income
A210: APA | B210: 42735 | C210: USD | D210: interestIncome | E210: 8000000 | F210: 45986.119 | G210: =VLOOKUP(D210,MAP!B:C,2,0) -> Revenue | H210: =VLOOKUP(D210,MAP!B:G,4,0) -> Investment income
A211: APA | B211: 42369 | C211: USD | D211: interestIncome | F211: 45986.119 | G211: =VLOOKUP(D211,MAP!B:C,2,0) -> Revenue | H211: =VLOOKUP(D211,MAP!B:G,4,0) -> Investment income
A212: APA | B212: 42004 | C212: USD | D212: interestIncome | F212: 45986.119 | G212: =VLOOKUP(D212,MAP!B:C,2,0) -> Revenue | H212: =VLOOKUP(D212,MAP!B:G,4,0) -> Investment income
A213: APA | B213: 41639 | C213: USD | D213: interestIncome | F213: 45986.119 | G213: =VLOOKUP(D213,MAP!B:C,2,0) -> Revenue | H213: =VLOOKUP(D213,MAP!B:G,4,0) -> Investment income
A214: APA | B214: 41274 | C214: USD | D214: interestIncome | F214: 45986.119 | G214: =VLOOKUP(D214,MAP!B:C,2,0) -> Revenue | H214: =VLOOKUP(D214,MAP!B:G,4,0) -> Investment income
A215: APA | B215: 40908 | C215: USD | D215: interestIncome | F215: 45986.119 | G215: =VLOOKUP(D215,MAP!B:C,2,0) -> Revenue | H215: =VLOOKUP(D215,MAP!B:G,4,0) -> Investment income
A216: APA | B216: 40543 | C216: USD | D216: interestIncome | F216: 45986.119 | G216: =VLOOKUP(D216,MAP!B:C,2,0) -> Revenue | H216: =VLOOKUP(D216,MAP!B:G,4,0) -> Investment income
A217: APA | B217: 40178 | C217: USD | D217: interestIncome | F217: 45986.119 | G217: =VLOOKUP(D217,MAP!B:C,2,0) -> Revenue | H217: =VLOOKUP(D217,MAP!B:G,4,0) -> Investment income
A218: APA | B218: 39813 | C218: USD | D218: interestIncome | F218: 45986.119 | G218: =VLOOKUP(D218,MAP!B:C,2,0) -> Revenue | H218: =VLOOKUP(D218,MAP!B:G,4,0) -> Investment income
A219: APA | B219: 39447 | C219: USD | D219: interestIncome | F219: 45986.119 | G219: =VLOOKUP(D219,MAP!B:C,2,0) -> Revenue | H219: =VLOOKUP(D219,MAP!B:G,4,0) -> Investment income
A220: APA | B220: 39082 | C220: USD | D220: interestIncome | F220: 45986.119 | G220: =VLOOKUP(D220,MAP!B:C,2,0) -> Revenue | H220: =VLOOKUP(D220,MAP!B:G,4,0) -> Investment income
A221: APA | B221: 38717 | C221: USD | D221: interestIncome | F221: 45986.119 | G221: =VLOOKUP(D221,MAP!B:C,2,0) -> Revenue | H221: =VLOOKUP(D221,MAP!B:G,4,0) -> Investment income
...
