Workbook

Sheet Positions
A1: Chapter | B1: Name | C1: Ticker | D1: Date | E1: Volume | F1: Price | G1: Value | H1: Expected Return QoQ% | I1: Volatility | J1: Ranking | K1: Mix % | L1: W/Avg Volatility | M1: Target Price | N1: Target Value | O1: Close Price | P1: Actual Value | Q1: Actual P&L | R1: Tolerance | S1: Unit Profit | T1: Unit Half Loss | U1: Balance Risk | V1: Normalized Risk | W1: Risk Mix | X1: Normalized Risk %
A2: Technology | B2: TSMC | C2: TSM | D2: =IF(ISERROR(VLOOKUP(C2,[1]Sheet1!$C:$C,1,0)),TODAY(),_xlfn.MINIFS([1]Sheet1!$F:$F,[1]Sheet1!$C:$C,C2)) -> 45716.856 | E2: =IFERROR(VLOOKUP(C2,'PBI Open Positions'!A:J,4,0),1E-32) -> 0.5547 | F2: =IFERROR(VLOOKUP(C2,'PBI Open Positions'!A:J,5,0),VLOOKUP(C2,'Stock Selection'!C:H,6,0)) -> 160.52 | G2: =E2*F2 -> 89.040444 | H2: =227.4/F2-1 -> 0.4166459 | I2: 0.37 | J2: =IFERROR(H2/I2,"") -> 1.12607 | K2: =IFERROR(J2/SUBTOTAL(9,$J$2:$J$1048576),"") -> 0.29277227 | L2: =I2*G2 -> 32.944964 | M2: =F2/(1-(F2*(1+H2)-F2)/(F2*(1+H2))) -> 227.4 | N2: =M2*E2 -> 126.13878 | O2: =IFERROR(VLOOKUP(C2,'PBI Open Positions'!A:F,6,0),VLOOKUP(Positions!C2,'Stock Selection'!C:H,6,0)) -> 220.05 | P2: =IFERROR(O2*E2,G2) -> 122.06173 | Q2: =P2-G2 -> 33.021291 | R2: =F2/(1+I2-H2) -> 168.37395 | S2: =M2-F2 -> 66.88 | T2: =0.5*(R2-F2) -> 3.9269774 | U2: =S2+T2 -> 70.806977 | V2: =SUBTOTAL(4,$U$2:$U$10000)-U2 -> -41.277042 | W2: =IFERROR((SUBTOTAL(109,$V$2:$V$1048576)/V2)/SUBTOTAL(109,$V$2:$V$1048576),0) -> 0 | X2: =V2/MAX($V$2:$V$28) -> -0.23902995
A3: ETF | B3: Vanguard Bonds | C3: BND | D3: =IF(ISERROR(VLOOKUP(C3,[1]Sheet1!$C:$C,1,0)),TODAY(),_xlfn.MINIFS([1]Sheet1!$F:$F,[1]Sheet1!$C:$C,C3)) -> 45743.774 | E3: =IFERROR(VLOOKUP(C3,'PBI Open Positions'!A:J,4,0),1E-32) -> 2 | F3: =IFERROR(VLOOKUP(C3,'PBI Open Positions'!A:J,5,0),VLOOKUP(C3,'Stock Selection'!C:H,6,0)) -> 73.5 | G3: =E3*F3 -> 147 | H3: 0.045 | I3: 0.165 | J3: =IFERROR(H3/I3,"") -> 0.27272727 | K3: =IFERROR(J3/SUBTOTAL(9,$J$2:$J$1048576),"") -> 0.070907655 | L3: =I3*G3 -> 24.255 | M3: =F3/(1-(F3*(1+H3)-F3)/(F3*(1+H3))) -> 76.8075 | N3: =M3*E3 -> 153.615 | O3: =IFERROR(VLOOKUP(C3,'PBI Open Positions'!A:F,6,0),VLOOKUP(Positions!C3,'Stock Selection'!C:H,6,0)) -> 73.28 | P3: =IFERROR(O3*E3,G3) -> 146.56 | Q3: =P3-G3 -> -0.44 | R3: =F3/(1+I3-H3) -> 65.625 | S3: =M3-F3 -> 3.3075 | T3: =0.5*(R3-F3) -> -3.9375 | U3: =S3+T3 -> -0.63 | V3: =SUBTOTAL(4,$U$2:$U$10000)-U3 -> 30.159936 | W3: =IFERROR((SUBTOTAL(109,$V$2:$V$1048576)/V3)/SUBTOTAL(109,$V$2:$V$1048576),0) -> 0 | X3: =V3/MAX($V$2:$V$28) -> 0.17465224
A4: ETF | B4: Emergin Markets | C4: VWO | D4: =IF(ISERROR(VLOOKUP(C4,[1]Sheet1!$C:$C,1,0)),TODAY(),_xlfn.MINIFS([1]Sheet1!$F:$F,[1]Sheet1!$C:$C,C4)) -> 45686.833 | E4: =IFERROR(VLOOKUP(C4,'PBI Open Positions'!A:J,4,0),1E-32) -> 4 | F4: =IFERROR(VLOOKUP(C4,'PBI Open Positions'!A:J,5,0),VLOOKUP(C4,'Stock Selection'!C:H,6,0)) -> 45.61 | G4: =E4*F4 -> 182.44 | H4: 0.083 | I4: 0.168 | J4: =IFERROR(H4/I4,"") -> 0.49404762 | K4: =IFERROR(J4/SUBTOTAL(9,$J$2:$J$1048576),"") -> 0.12844978 | L4: =I4*G4 -> 30.64992 | M4: =F4/(1-(F4*(1+H4)-F4)/(F4*(1+H4))) -> 49.39563 | N4: =M4*E4 -> 197.58252 | O4: =IFERROR(VLOOKUP(C4,'PBI Open Positions'!A:F,6,0),VLOOKUP(Positions!C4,'Stock Selection'!C:H,6,0)) -> 49.01 | P4: =IFERROR(O4*E4,G4) -> 196.04 | Q4: =P4-G4 -> 13.6 | R4: =F4/(1+I4-H4) -> 42.036866 | S4: =M4-F4 -> 3.78563 | T4: =0.5*(R4-F4) -> -1.7865668 | U4: =S4+T4 -> 1.9990632 | V4: =SUBTOTAL(4,$U$2:$U$10000)-U4 -> 27.530872 | W4: =IFERROR((SUBTOTAL(109,$V$2:$V$1048576)/V4)/SUBTOTAL(109,$V$2:$V$1048576),0) -> 0 | X4: =V4/MAX($V$2:$V$28) -> 0.15942768
A5: Energy & Utilities | B5: APA | C5: APA | D5: =IF(ISERROR(VLOOKUP(C5,[1]Sheet1!$C:$C,1,0)),TODAY(),_xlfn.MINIFS([1]Sheet1!$F:$F,[1]Sheet1!$C:$C,C5)) -> 45632.877 | E5: =IFERROR(VLOOKUP(C5,'PBI Open Positions'!A:J,4,0),1E-32) -> 6.8599 | F5: =IFERROR(VLOOKUP(C5,'PBI Open Positions'!A:J,5,0),VLOOKUP(C5,'Stock Selection'!C:H,6,0)) -> 18.94 | G5: =E5*F5 -> 129.92651 | H5: =M5/F5-1 -> 0.40337909 | I5: 0.4029 | J5: =IFERROR(H5/I5,"") -> 1.0011891 | K5: =IFERROR(J5/SUBTOTAL(9,$J$2:$J$1048576),"") -> 0.2603039 | L5: =I5*G5 -> 52.347389 | M5: 26.58 | N5: =M5*E5 -> 182.33614 | O5: =IFERROR(VLOOKUP(C5,'PBI Open Positions'!A:F,6,0),VLOOKUP(Positions!C5,'Stock Selection'!C:H,6,0)) -> 18.17 | P5: =IFERROR(O5*E5,G5) -> 124.64438 | Q5: =P5-G5 -> -5.282123 | R5: =F5/(1+I5-H5) -> 18.949078 | S5: =M5-F5 -> 7.64 | T5: =0.5*(R5-F5) -> 0.0045391747 | U5: =S5+T5 -> 7.6445392 | V5: =SUBTOTAL(4,$U$2:$U$10000)-U5 -> 21.885396 | W5: =IFERROR((SUBTOTAL(109,$V$2:$V$1048576)/V5)/SUBTOTAL(109,$V$2:$V$1048576),0) -> 0 | X5: =V5/MAX($V$2:$V$28) -> 0.12673547
A6: Energy & Utilities | B6: First Solar | C6: FSLR | D6: =IF(ISERROR(VLOOKUP(C6,[1]Sheet1!$C:$C,1,0)),TODAY(),_xlfn.MINIFS([1]Sheet1!$F:$F,[1]Sheet1!$C:$C,C6)) -> 45727.872 | E6: =IFERROR(VLOOKUP(C6,'PBI Open Positions'!A:J,4,0),1E-32) -> 0.497 | F6: =IFERROR(VLOOKUP(C6,'PBI Open Positions'!A:J,5,0),VLOOKUP(C6,'Stock Selection'!C:H,6,0)) -> 137.42 | G6: =E6*F6 -> 68.29774 | H6: =196.02/F6-1 -> 0.42642992 | I6: 0.5203 | J6: =IFERROR(H6/I6,"") -> 0.81958471 | K6: =IFERROR(J6/SUBTOTAL(9,$J$2:$J$1048576),"") -> 0.21308771 | L6: =I6*G6 -> 35.535314 | M6: =F6/(1-(F6*(1+H6)-F6)/(F6*(1+H6))) -> 196.02 | N6: =M6*E6 -> 97.42194 | O6: =IFERROR(VLOOKUP(C6,'PBI Open Positions'!A:F,6,0),VLOOKUP(Positions!C6,'Stock Selection'!C:H,6,0)) -> 150.54 | P6: =IFERROR(O6*E6,G6) -> 74.81838 | Q6: =P6-G6 -> 6.52064 | R6: =F6/(1+I6-H6) -> 125.62735 | S6: =M6-F6 -> 58.6 | T6: =0.5*(R6-F6) -> -5.8963246 | U6: =S6+T6 -> 52.703675 | V6: =SUBTOTAL(4,$U$2:$U$10000)-U6 -> -23.17374 | W6: =IFERROR((SUBTOTAL(109,$V$2:$V$1048576)/V6)/SUBTOTAL(109,$V$2:$V$1048576),0) -> 0 | X6: =V6/MAX($V$2:$V$28) -> -0.1341961
A7: ETF | B7: Bitcoin ETF | C7: VBTC.DE | D7: =IF(ISERROR(VLOOKUP(C7,[1]Sheet1!$C:$C,1,0)),TODAY(),_xlfn.MINIFS([1]Sheet1!$F:$F,[1]Sheet1!$C:$C,C7)) -> 45833 | E7: =IFERROR(VLOOKUP(C7,'PBI Open Positions'!A:J,4,0),1E-32) -> 1e-32 | F7: =IFERROR(VLOOKUP(C7,'PBI Open Positions'!A:J,5,0),VLOOKUP(C7,'Stock Selection'!C:H,6,0)) -> 48.34 | G7: =E7*F7 -> 4.834e-31 | H7: 0.1 | I7: 0.2 | J7: =IFERROR(H7/I7,"") -> 0.5 | K7: =IFERROR(J7/SUBTOTAL(9,$J$2:$J$1048576),"") -> 0.12999737 | L7: =I7*G7 -> 9.668e-32 | M7: =F7/(1-(F7*(1+H7)-F7)/(F7*(1+H7))) -> 53.174 | N7: =M7*E7 -> 5.3174e-31 | O7: =IFERROR(VLOOKUP(C7,'PBI Open Positions'!A:F,6,0),VLOOKUP(Positions!C7,'Stock Selection'!C:H,6,0)) -> 48.34 | P7: =IFERROR(O7*E7,G7) -> 4.834e-31 | Q7: =P7-G7 -> 0 | R7: =F7/(1+I7-H7) -> 43.945455 | S7: =M7-F7 -> 4.834 | T7: =0.5*(R7-F7) -> -2.1972727 | U7: =S7+T7 -> 2.6367273 | V7: =SUBTOTAL(4,$U$2:$U$10000)-U7 -> 26.893208 | W7: =IFERROR((SUBTOTAL(109,$V$2:$V$1048576)/V7)/SUBTOTAL(109,$V$2:$V$1048576),0) -> 0 | X7: =V7/MAX($V$2:$V$28) -> 0.15573505
A8: Consumer Defensive | B8: Altaria | C8: MO | D8: =IF(ISERROR(VLOOKUP(C8,[1]Sheet1!$C:$C,1,0)),TODAY(),_xlfn.MINIFS([1]Sheet1!$F:$F,[1]Sheet1!$C:$C,C8)) -> 45518.844 | E8: =IFERROR(VLOOKUP(C8,'PBI Open Positions'!A:J,4,0),1E-32) -> 2.3939 | F8: =IFERROR(VLOOKUP(C8,'PBI Open Positions'!A:J,5,0),VLOOKUP(C8,'Stock Selection'!C:H,6,0)) -> 54.2 | G8: =E8*F8 -> 129.74938 | H8: =16.68%+7%/4 -> 0.1843 | I8: 0.1998 | J8: =IFERROR(H8/I8,"") -> 0.92242242 | K8: =IFERROR(J8/SUBTOTAL(9,$J$2:$J$1048576),"") -> 0.23982497 | L8: =I8*G8 -> 25.923926 | M8: =F8/(1-(F8*(1+H8)-F8)/(F8*(1+H8))) -> 64.18906 | N8: =M8*E8 -> 153.66219 | O8: =IFERROR(VLOOKUP(C8,'PBI Open Positions'!A:F,6,0),VLOOKUP(Positions!C8,'Stock Selection'!C:H,6,0)) -> 59.93 | P8: =IFERROR(O8*E8,G8) -> 143.46643 | Q8: =P8-G8 -> 13.717047 | R8: =F8/(1+I8-H8) -> 53.372723 | S8: =M8-F8 -> 9.98906 | T8: =0.5*(R8-F8) -> -0.4136386 | U8: =S8+T8 -> 9.5754214 | V8: =SUBTOTAL(4,$U$2:$U$10000)-U8 -> 19.954514 | W8: =IFERROR((SUBTOTAL(109,$V$2:$V$1048576)/V8)/SUBTOTAL(109,$V$2:$V$1048576),0) -> 0 | X8: =V8/MAX($V$2:$V$28) -> 0.11555398
A9: Consumer Defensive | B9: Pepsi | C9: PEP | D9: =IF(ISERROR(VLOOKUP(C9,[1]Sheet1!$C:$C,1,0)),TODAY(),_xlfn.MINIFS([1]Sheet1!$F:$F,[1]Sheet1!$C:$C,C9)) -> 45460.885 | E9: =IFERROR(VLOOKUP(C9,'PBI Open Positions'!A:J,4,0),1E-32) -> 0.8085 | F9: =IFERROR(VLOOKUP(C9,'PBI Open Positions'!A:J,5,0),VLOOKUP(C9,'Stock Selection'!C:H,6,0)) -> 147.19 | G9: =E9*F9 -> 119.00311 | H9: 0.0672 | I9: 0.1644 | J9: =IFERROR(H9/I9,"") -> 0.40875912 | K9: =IFERROR(J9/SUBTOTAL(9,$J$2:$J$1048576),"") -> 0.10627522 | L9: =I9*G9 -> 19.564112 | M9: =F9/(1-(F9*(1+H9)-F9)/(F9*(1+H9))) -> 157.08117 | N9: =M9*E9 -> 127.00012 | O9: =IFERROR(VLOOKUP(C9,'PBI Open Positions'!A:F,6,0),VLOOKUP(Positions!C9,'Stock Selection'!C:H,6,0)) -> 131.08 | P9: =IFERROR(O9*E9,G9) -> 105.97818 | Q9: =P9-G9 -> -13.024935 | R9: =F9/(1+I9-H9) -> 134.15057 | S9: =M9-F9 -> 9.891168 | T9: =0.5*(R9-F9) -> -6.5197175 | U9: =S9+T9 -> 3.3714505 | V9: =SUBTOTAL(4,$U$2:$U$10000)-U9 -> 26.158485 | W9: =IFERROR((SUBTOTAL(109,$V$2:$V$1048576)/V9)/SUBTOTAL(109,$V$2:$V$1048576),0) -> 0 | X9: =V9/MAX($V$2:$V$28) -> 0.15148036
A10: Energy & Utilities | B10: YPF | C10: YPF | D10: =IF(ISERROR(VLOOKUP(C10,[1]Sheet1!$C:$C,1,0)),TODAY(),_xlfn.MINIFS([1]Sheet1!$F:$F,[1]Sheet1!$C:$C,C10)) -> 45663.738 | E10: =IFERROR(VLOOKUP(C10,'PBI Open Positions'!A:J,4,0),1E-32) -> 2.4948 | F10: =IFERROR(VLOOKUP(C10,'PBI Open Positions'!A:J,5,0),VLOOKUP(C10,'Stock Selection'!C:H,6,0)) -> 36.06 | G10: =E10*F10 -> 89.962488 | H10: =M10/F10-1 -> 0.38657793 | I10: 0.5311 | J10: =IFERROR(H10/I10,"") -> 0.72788161 | K10: =IFERROR(J10/SUBTOTAL(9,$J$2:$J$1048576),"") -> 0.18924539 | L10: =I10*G10 -> 47.779077 | M10: 50 | N10: =M10*E10 -> 124.74 | O10: =IFERROR(VLOOKUP(C10,'PBI Open Positions'!A:F,6,0),VLOOKUP(Positions!C10,'Stock Selection'!C:H,6,0)) -> 34.37 | P10: =IFERROR(O10*E10,G10) -> 85.746276 | Q10: =P10-G10 -> -4.216212 | R10: =F10/(1+I10-H10) -> 31.506601 | S10: =M10-F10 -> 13.94 | T10: =0.5*(R10-F10) -> -2.2766996 | U10: =S10+T10 -> 11.6633 | V10: =SUBTOTAL(4,$U$2:$U$10000)-U10 -> 17.866635 | W10: =IFERROR((SUBTOTAL(109,$V$2:$V$1048576)/V10)/SUBTOTAL(109,$V$2:$V$1048576),0) -> 0 | X10: =V10/MAX($V$2:$V$28) -> 0.10346335
A11: Technology | B11: Microsoft | C11: MSFT | D11: =IF(ISERROR(VLOOKUP(C11,[1]Sheet1!$C:$C,1,0)),TODAY(),_xlfn.MINIFS([1]Sheet1!$F:$F,[1]Sheet1!$C:$C,C11)) -> 45695.856 | E11: =IFERROR(VLOOKUP(C11,'PBI Open Positions'!A:J,4,0),1E-32) -> 0.001 | F11: =IFERROR(VLOOKUP(C11,'PBI Open Positions'!A:J,5,0),VLOOKUP(C11,'Stock Selection'!C:H,6,0)) -> 410 | G11: =E11*F11 -> 0.41 | H11: 0.15 | I11: 0.1963 | J11: =IFERROR(H11/I11,"") -> 0.76413653 | K11: =IFERROR(J11/SUBTOTAL(9,$J$2:$J$1048576),"") -> 0.19867147 | L11: =I11*G11 -> 0.080483 | M11: =F11/(1-(F11*(1+H11)-F11)/(F11*(1+H11))) -> 471.5 | N11: =M11*E11 -> 0.4715 | O11: =IFERROR(VLOOKUP(C11,'PBI Open Positions'!A:F,6,0),VLOOKUP(Positions!C11,'Stock Selection'!C:H,6,0)) -> 490 | P11: =IFERROR(O11*E11,G11) -> 0.49 | Q11: =P11-G11 -> 0.08 | R11: =F11/(1+I11-H11) -> 391.85702 | S11: =M11-F11 -> 61.5 | T11: =0.5*(R11-F11) -> -9.07149 | U11: =S11+T11 -> 52.42851 | V11: =SUBTOTAL(4,$U$2:$U$10000)-U11 -> -22.898574 | W11: =IFERROR((SUBTOTAL(109,$V$2:$V$1048576)/V11)/SUBTOTAL(109,$V$2:$V$1048576),0) -> 0 | X11: =V11/MAX($V$2:$V$28) -> -0.13260265
A12: Financial Services | B12: ING Group NV | C12: ING | D12: =IF(ISERROR(VLOOKUP(C12,[1]Sheet1!$C:$C,1,0)),TODAY(),_xlfn.MINIFS([1]Sheet1!$F:$F,[1]Sheet1!$C:$C,C12)) -> 45623.75 | E12: =IFERROR(VLOOKUP(C12,'PBI Open Positions'!A:J,4,0),1E-32) -> 4.8753 | F12: =IFERROR(VLOOKUP(C12,'PBI Open Positions'!A:J,5,0),VLOOKUP(C12,'Stock Selection'!C:H,6,0)) -> 17.56 | G12: =E12*F12 -> 85.610268 | H12: 0.0902 | I12: 0.2789 | J12: =IFERROR(H12/I12,"") -> 0.32341341 | K12: =IFERROR(J12/SUBTOTAL(9,$J$2:$J$1048576),"") -> 0.084085784 | L12: =I12*G12 -> 23.876704 | M12: =F12/(1-(F12*(1+H12)-F12)/(F12*(1+H12))) -> 19.143912 | N12: =M12*E12 -> 93.332314 | O12: =IFERROR(VLOOKUP(C12,'PBI Open Positions'!A:F,6,0),VLOOKUP(Positions!C12,'Stock Selection'!C:H,6,0)) -> 21.35 | P12: =IFERROR(O12*E12,G12) -> 104.08766 | Q12: =P12-G12 -> 18.477387 | R12: =F12/(1+I12-H12) -> 14.77244 | S12: =M12-F12 -> 1.583912 | T12: =0.5*(R12-F12) -> -1.3937798 | U12: =S12+T12 -> 0.19013224 | V12: =SUBTOTAL(4,$U$2:$U$10000)-U12 -> 29.339803 | W12: =IFERROR((SUBTOTAL(109,$V$2:$V$1048576)/V12)/SUBTOTAL(109,$V$2:$V$1048576),0) -> 0 | X12: =V12/MAX($V$2:$V$28) -> 0.16990296
A13: Consumer Defensive | B13: Albertson Companies | C13: ACI | D13: =IF(ISERROR(VLOOKUP(C13,[1]Sheet1!$C:$C,1,0)),TODAY(),_xlfn.MINIFS([1]Sheet1!$F:$F,[1]Sheet1!$C:$C,C13)) -> 45693.855 | E13: =IFERROR(VLOOKUP(C13,'PBI Open Positions'!A:J,4,0),1E-32) -> 6 | F13: =IFERROR(VLOOKUP(C13,'PBI Open Positions'!A:J,5,0),VLOOKUP(C13,'Stock Selection'!C:H,6,0)) -> 21.05 | G13: =E13*F13 -> 126.3 | H13: 0.2 | I13: 0.2 | J13: =IFERROR(H13/I13,"") -> 1 | K13: =IFERROR(J13/SUBTOTAL(9,$J$2:$J$1048576),"") -> 0.25999474 | L13: =I13*G13 -> 25.26 | M13: =F13/(1-(F13*(1+H13)-F13)/(F13*(1+H13))) -> 25.26 | N13: =M13*E13 -> 151.56 | O13: =IFERROR(VLOOKUP(C13,'PBI Open Positions'!A:F,6,0),VLOOKUP(Positions!C13,'Stock Selection'!C:H,6,0)) -> 21.68 | P13: =IFERROR(O13*E13,G13) -> 130.08 | Q13: =P13-G13 -> 3.78 | R13: =F13/(1+I13-H13) -> 21.05 | S13: =M13-F13 -> 4.21 | T13: =0.5*(R13-F13) -> 0 | U13: =S13+T13 -> 4.21 | V13: =SUBTOTAL(4,$U$2:$U$10000)-U13 -> 25.319936 | W13: =IFERROR((SUBTOTAL(109,$V$2:$V$1048576)/V13)/SUBTOTAL(109,$V$2:$V$1048576),0) -> 0 | X13: =V13/MAX($V$2:$V$28) -> 0.14662443
A14: Financial Services | B14: Master Card | C14: MA | D14: =IF(ISERROR(VLOOKUP(C14,[1]Sheet1!$C:$C,1,0)),TODAY(),_xlfn.MINIFS([1]Sheet1!$F:$F,[1]Sheet1!$C:$C,C14)) -> 45645.901 | E14: =IFERROR(VLOOKUP(C14,'PBI Open Positions'!A:J,4,0),1E-32) -> 0.0781 | F14: =IFERROR(VLOOKUP(C14,'PBI Open Positions'!A:J,5,0),VLOOKUP(C14,'Stock Selection'!C:H,6,0)) -> 518.05 | G14: =E14*F14 -> 40.459705 | H14: 0.0959 | I14: 0.1865 | J14: =IFERROR(H14/I14,"") -> 0.51420912 | K14: =IFERROR(J14/SUBTOTAL(9,$J$2:$J$1048576),"") -> 0.13369166 | L14: =I14*G14 -> 7.545735 | M14: =F14/(1-(F14*(1+H14)-F14)/(F14*(1+H14))) -> 567.731 | N14: =M14*E14 -> 44.339791 | O14: =IFERROR(VLOOKUP(C14,'PBI Open Positions'!A:F,6,0),VLOOKUP(Positions!C14,'Stock Selection'!C:H,6,0)) -> 556.34 | P14: =IFERROR(O14*E14,G14) -> 43.450154 | Q14: =P14-G14 -> 2.990449 | R14: =F14/(1+I14-H14) -> 475.01375 | S14: =M14-F14 -> 49.680995 | T14: =0.5*(R14-F14) -> -21.518123 | U14: =S14+T14 -> 28.162872 | V14: =SUBTOTAL(4,$U$2:$U$10000)-U14 -> 1.3670636 | W14: =IFERROR((SUBTOTAL(109,$V$2:$V$1048576)/V14)/SUBTOTAL(109,$V$2:$V$1048576),0) -> 0 | X14: =V14/MAX($V$2:$V$28) -> 0.0079164863
A15: Energy & Utilities | B15: NextEra Energy | C15: NEE | D15: =IF(ISERROR(VLOOKUP(C15,[1]Sheet1!$C:$C,1,0)),TODAY(),_xlfn.MINIFS([1]Sheet1!$F:$F,[1]Sheet1!$C:$C,C15)) -> 45511.86 | E15: =IFERROR(VLOOKUP(C15,'PBI Open Positions'!A:J,4,0),1E-32) -> 0.9669 | F15: =IFERROR(VLOOKUP(C15,'PBI Open Positions'!A:J,5,0),VLOOKUP(C15,'Stock Selection'!C:H,6,0)) -> 72.38 | G15: =E15*F15 -> 69.984222 | H15: 0.05 | I15: 0.2786 | J15: =IFERROR(H15/I15,"") -> 0.17946877 | K15: =IFERROR(J15/SUBTOTAL(9,$J$2:$J$1048576),"") -> 0.046660936 | L15: =I15*G15 -> 19.497604 | M15: =F15/(1-(F15*(1+H15)-F15)/(F15*(1+H15))) -> 75.999 | N15: =M15*E15 -> 73.483433 | O15: =IFERROR(VLOOKUP(C15,'PBI Open Positions'!A:F,6,0),VLOOKUP(Positions!C15,'Stock Selection'!C:H,6,0)) -> 71.42 | P15: =IFERROR(O15*E15,G15) -> 69.055998 | Q15: =P15-G15 -> -0.928224 | R15: =F15/(1+I15-H15) -> 58.912583 | S15: =M15-F15 -> 3.619 | T15: =0.5*(R15-F15) -> -6.7337083 | U15: =S15+T15 -> -3.1147083 | V15: =SUBTOTAL(4,$U$2:$U$10000)-U15 -> 32.644644 | W15: =IFERROR((SUBTOTAL(109,$V$2:$V$1048576)/V15)/SUBTOTAL(109,$V$2:$V$1048576),0) -> 0 | X15: =V15/MAX($V$2:$V$28) -> 0.18904086
A16: Consumer Defensive | B16: Kimberly Clark | C16: KMB | D16: =IF(ISERROR(VLOOKUP(C16,[1]Sheet1!$C:$C,1,0)),TODAY(),_xlfn.MINIFS([1]Sheet1!$F:$F,[1]Sheet1!$C:$C,C16)) -> 45544.652 | E16: =IFERROR(VLOOKUP(C16,'PBI Open Positions'!A:J,4,0),1E-32) -> 0.4774 | F16: =IFERROR(VLOOKUP(C16,'PBI Open Positions'!A:J,5,0),VLOOKUP(C16,'Stock Selection'!C:H,6,0)) -> 134.88 | G16: =E16*F16 -> 64.391712 | H16: 0.07 | I16: 0.1834 | J16: =IFERROR(H16/I16,"") -> 0.38167939 | K16: =IFERROR(J16/SUBTOTAL(9,$J$2:$J$1048576),"") -> 0.099234632 | L16: =I16*G16 -> 11.80944 | M16: =F16/(1-(F16*(1+H16)-F16)/(F16*(1+H16))) -> 144.3216 | N16: =M16*E16 -> 68.899132 | O16: =IFERROR(VLOOKUP(C16,'PBI Open Positions'!A:F,6,0),VLOOKUP(Positions!C16,'Stock Selection'!C:H,6,0)) -> 129.91 | P16: =IFERROR(O16*E16,G16) -> 62.019034 | Q16: =P16-G16 -> -2.372678 | R16: =F16/(1+I16-H16) -> 121.14245 | S16: =M16-F16 -> 9.4416 | T16: =0.5*(R16-F16) -> -6.8687767 | U16: =S16+T16 -> 2.5728233 | V16: =SUBTOTAL(4,$U$2:$U$10000)-U16 -> 26.957112 | W16: =IFERROR((SUBTOTAL(109,$V$2:$V$1048576)/V16)/SUBTOTAL(109,$V$2:$V$1048576),0) -> 0 | X16: =V16/MAX($V$2:$V$28) -> 0.15610511
A17: Consumer Defensive | B17: Ingredion | C17: INGR | D17: =IF(ISERROR(VLOOKUP(C17,[1]Sheet1!$C:$C,1,0)),TODAY(),_xlfn.MINIFS([1]Sheet1!$F:$F,[1]Sheet1!$C:$C,C17)) -> 45580.706 | E17: =IFERROR(VLOOKUP(C17,'PBI Open Positions'!A:J,4,0),1E-32) -> 0.3486 | F17: =IFERROR(VLOOKUP(C17,'PBI Open Positions'!A:J,5,0),VLOOKUP(C17,'Stock Selection'!C:H,6,0)) -> 131.93 | G17: =E17*F17 -> 45.990798 | H17: 0.1202 | I17: 0.3371 | J17: =IFERROR(H17/I17,"") -> 0.35657075 | K17: =IFERROR(J17/SUBTOTAL(9,$J$2:$J$1048576),"") -> 0.092706518 | L17: =I17*G17 -> 15.503498 | M17: =F17/(1-(F17*(1+H17)-F17)/(F17*(1+H17))) -> 147.78799 | N17: =M17*E17 -> 51.518892 | O17: =IFERROR(VLOOKUP(C17,'PBI Open Positions'!A:F,6,0),VLOOKUP(Positions!C17,'Stock Selection'!C:H,6,0)) -> 137.46 | P17: =IFERROR(O17*E17,G17) -> 47.918556 | Q17: =P17-G17 -> 1.927758 | R17: =F17/(1+I17-H17) -> 108.41482 | S17: =M17-F17 -> 15.857986 | T17: =0.5*(R17-F17) -> -11.757588 | U17: =S17+T17 -> 4.1003983 | V17: =SUBTOTAL(4,$U$2:$U$10000)-U17 -> 25.429537 | W17: =IFERROR((SUBTOTAL(109,$V$2:$V$1048576)/V17)/SUBTOTAL(109,$V$2:$V$1048576),0) -> 0 | X17: =V17/MAX($V$2:$V$28) -> 0.14725912
A18: ETF | B18: Robotics & AI | C18: BOTZ.L | D18: =IF(ISERROR(VLOOKUP(C18,[1]Sheet1!$C:$C,1,0)),TODAY(),_xlfn.MINIFS([1]Sheet1!$F:$F,[1]Sheet1!$C:$C,C18)) -> 45482.713 | E18: =IFERROR(VLOOKUP(C18,'PBI Open Positions'!A:J,4,0),1E-32) -> 2 | F18: =IFERROR(VLOOKUP(C18,'PBI Open Positions'!A:J,5,0),VLOOKUP(C18,'Stock Selection'!C:H,6,0)) -> 20.93 | G18: =E18*F18 -> 41.86 | H18: 0.035 | I18: 0.165 | J18: =IFERROR(H18/I18,"") -> 0.21212121 | K18: =IFERROR(J18/SUBTOTAL(9,$J$2:$J$1048576),"") -> 0.055150399 | L18: =I18*G18 -> 6.9069 | M18: =F18/(1-(F18*(1+H18)-F18)/(F18*(1+H18))) -> 21.66255 | N18: =M18*E18 -> 43.3251 | O18: =IFERROR(VLOOKUP(C18,'PBI Open Positions'!A:F,6,0),VLOOKUP(Positions!C18,'Stock Selection'!C:H,6,0)) -> 20.58 | P18: =IFERROR(O18*E18,G18) -> 41.16 | Q18: =P18-G18 -> -0.7 | R18: =F18/(1+I18-H18) -> 18.522124 | S18: =M18-F18 -> 0.73255 | T18: =0.5*(R18-F18) -> -1.2039381 | U18: =S18+T18 -> -0.47138805 | V18: =SUBTOTAL(4,$U$2:$U$10000)-U18 -> 30.001324 | W18: =IFERROR((SUBTOTAL(109,$V$2:$V$1048576)/V18)/SUBTOTAL(109,$V$2:$V$1048576),0) -> 0 | X18: =V18/MAX($V$2:$V$28) -> 0.17373374
A19: ETF | B19: Batterey Value-Chain | C19: BATT.AS | D19: =IF(ISERROR(VLOOKUP(C19,[1]Sheet1!$C:$C,1,0)),TODAY(),_xlfn.MINIFS([1]Sheet1!$F:$F,[1]Sheet1!$C:$C,C19)) -> 45484.679 | E19: =IFERROR(VLOOKUP(C19,'PBI Open Positions'!A:J,4,0),1E-32) -> 2 | F19: =IFERROR(VLOOKUP(C19,'PBI Open Positions'!A:J,5,0),VLOOKUP(C19,'Stock Selection'!C:H,6,0)) -> 17.51 | G19: =E19*F19 -> 35.02 | H19: 0.035 | I19: 0.165 | J19: =IFERROR(H19/I19,"") -> 0.21212121 | K19: =IFERROR(J19/SUBTOTAL(9,$J$2:$J$1048576),"") -> 0.055150399 | L19: =I19*G19 -> 5.7783 | M19: =F19/(1-(F19*(1+H19)-F19)/(F19*(1+H19))) -> 18.12285 | N19: =M19*E19 -> 36.2457 | O19: =IFERROR(VLOOKUP(C19,'PBI Open Positions'!A:F,6,0),VLOOKUP(Positions!C19,'Stock Selection'!C:H,6,0)) -> 17.56 | P19: =IFERROR(O19*E19,G19) -> 35.12 | Q19: =P19-G19 -> 0.1 | R19: =F19/(1+I19-H19) -> 15.495575 | S19: =M19-F19 -> 0.61285 | T19: =0.5*(R19-F19) -> -1.0072124 | U19: =S19+T19 -> -0.39436239 | V19: =SUBTOTAL(4,$U$2:$U$10000)-U19 -> 29.924298 | W19: =IFERROR((SUBTOTAL(109,$V$2:$V$1048576)/V19)/SUBTOTAL(109,$V$2:$V$1048576),0) -> 0 | X19: =V19/MAX($V$2:$V$28) -> 0.17328769
A20: Technology | B20: Google | C20: GOOGL | D20: =IF(ISERROR(VLOOKUP(C20,[1]Sheet1!$C:$C,1,0)),TODAY(),_xlfn.MINIFS([1]Sheet1!$F:$F,[1]Sheet1!$C:$C,C20)) -> 45734.856 | E20: =IFERROR(VLOOKUP(C20,'PBI Open Positions'!A:J,4,0),1E-32) -> 0.0282 | F20: =IFERROR(VLOOKUP(C20,'PBI Open Positions'!A:J,5,0),VLOOKUP(C20,'Stock Selection'!C:H,6,0)) -> 160.64 | G20: =E20*F20 -> 4.530048 | H20: =190.41/F20-1 -> 0.18532122 | I20: 0.2679 | J20: =IFERROR(H20/I20,"") -> 0.69175519 | K20: =IFERROR(J20/SUBTOTAL(9,$J$2:$J$1048576),"") -> 0.17985271 | L20: =I20*G20 -> 1.2135999 | M20: =F20/(1-(F20*(1+H20)-F20)/(F20*(1+H20))) -> 190.41 | N20: =M20*E20 -> 5.369562 | O20: =IFERROR(VLOOKUP(C20,'PBI Open Positions'!A:F,6,0),VLOOKUP(Positions!C20,'Stock Selection'!C:H,6,0)) -> 166.67 | P20: =IFERROR(O20*E20,G20) -> 4.700094 | Q20: =P20-G20 -> 0.170046 | R20: =F20/(1+I20-H20) -> 148.38643 | S20: =M20-F20 -> 29.77 | T20: =0.5*(R20-F20) -> -6.1267855 | U20: =S20+T20 -> 23.643215 | V20: =SUBTOTAL(4,$U$2:$U$10000)-U20 -> 5.886721 | W20: =IFERROR((SUBTOTAL(109,$V$2:$V$1048576)/V20)/SUBTOTAL(109,$V$2:$V$1048576),0) -> 0 | X20: =V20/MAX($V$2:$V$28) -> 0.034089231
A21: Healthcare | B21: Agios | C21: AGIO | D21: =IF(ISERROR(VLOOKUP(C21,[1]Sheet1!$C:$C,1,0)),TODAY(),_xlfn.MINIFS([1]Sheet1!$F:$F,[1]Sheet1!$C:$C,C21)) -> 45805.662 | E21: =IFERROR(VLOOKUP(C21,'PBI Open Positions'!A:J,4,0),1E-32) -> 0.0179 | F21: =IFERROR(VLOOKUP(C21,'PBI Open Positions'!A:J,5,0),VLOOKUP(C21,'Stock Selection'!C:H,6,0)) -> 30.73 | G21: =E21*F21 -> 0.550067 | H21: 0.2 | I21: 0.2 | J21: =IFERROR(H21/I21,"") -> 1 | K21: =IFERROR(J21/SUBTOTAL(9,$J$2:$J$1048576),"") -> 0.25999474 | L21: =I21*G21 -> 0.1100134 | M21: =F21/(1-(F21*(1+H21)-F21)/(F21*(1+H21))) -> 36.876 | N21: =M21*E21 -> 0.6600804 | O21: =IFERROR(VLOOKUP(C21,'PBI Open Positions'!A:F,6,0),VLOOKUP(Positions!C21,'Stock Selection'!C:H,6,0)) -> 33.52 | P21: =IFERROR(O21*E21,G21) -> 0.600008 | Q21: =P21-G21 -> 0.049941 | R21: =F21/(1+I21-H21) -> 30.73 | S21: =M21-F21 -> 6.146 | T21: =0.5*(R21-F21) -> 0 | U21: =S21+T21 -> 6.146 | V21: =SUBTOTAL(4,$U$2:$U$10000)-U21 -> 23.383936 | W21: =IFERROR((SUBTOTAL(109,$V$2:$V$1048576)/V21)/SUBTOTAL(109,$V$2:$V$1048576),0) -> 0 | X21: =V21/MAX($V$2:$V$28) -> 0.13541331
A22: Financial Services | B22: BARCLAYS | C22: BCS | D22: =IF(ISERROR(VLOOKUP(C22,[1]Sheet1!$C:$C,1,0)),TODAY(),_xlfn.MINIFS([1]Sheet1!$F:$F,[1]Sheet1!$C:$C,C22)) -> 45764.855 | E22: =IFERROR(VLOOKUP(C22,'PBI Open Positions'!A:J,4,0),1E-32) -> 4.8087 | F22: =IFERROR(VLOOKUP(C22,'PBI Open Positions'!A:J,5,0),VLOOKUP(C22,'Stock Selection'!C:H,6,0)) -> 16.64 | G22: =E22*F22 -> 80.016768 | H22: 0.1857 | I22: 0.346 | J22: =IFERROR(H22/I22,"") -> 0.5367052 | K22: =IFERROR(J22/SUBTOTAL(9,$J$2:$J$1048576),"") -> 0.13954053 | L22: =I22*G22 -> 27.685802 | M22: =F22/(1-(F22*(1+H22)-F22)/(F22*(1+H22))) -> 19.730048 | N22: =M22*E22 -> 94.875882 | O22: =IFERROR(VLOOKUP(C22,'PBI Open Positions'!A:F,6,0),VLOOKUP(Positions!C22,'Stock Selection'!C:H,6,0)) -> 18.25 | P22: =IFERROR(O22*E22,G22) -> 87.758775 | Q22: =P22-G22 -> 7.742007 | R22: =F22/(1+I22-H22) -> 14.341119 | S22: =M22-F22 -> 3.090048 | T22: =0.5*(R22-F22) -> -1.1494407 | U22: =S22+T22 -> 1.9406073 | V22: =SUBTOTAL(4,$U$2:$U$10000)-U22 -> 27.589328 | W22: =IFERROR((SUBTOTAL(109,$V$2:$V$1048576)/V22)/SUBTOTAL(109,$V$2:$V$1048576),0) -> 0 | X22: =V22/MAX($V$2:$V$28) -> 0.15976619
A23: Financial Services | B23: Visa | C23: V | D23: =IF(ISERROR(VLOOKUP(C23,[1]Sheet1!$C:$C,1,0)),TODAY(),_xlfn.MINIFS([1]Sheet1!$F:$F,[1]Sheet1!$C:$C,C23)) -> 45751.745 | E23: =IFERROR(VLOOKUP(C23,'PBI Open Positions'!A:J,4,0),1E-32) -> 0.0624 | F23: =IFERROR(VLOOKUP(C23,'PBI Open Positions'!A:J,5,0),VLOOKUP(C23,'Stock Selection'!C:H,6,0)) -> 339.74 | G23: =E23*F23 -> 21.199776 | H23: 0.1177 | I23: 0.1833 | J23: =IFERROR(H23/I23,"") -> 0.64211675 | K23: =IFERROR(J23/SUBTOTAL(9,$J$2:$J$1048576),"") -> 0.16694697 | L23: =I23*G23 -> 3.8859189 | M23: =F23/(1-(F23*(1+H23)-F23)/(F23*(1+H23))) -> 379.7274 | N23: =M23*E23 -> 23.69499 | O23: =IFERROR(VLOOKUP(C23,'PBI Open Positions'!A:F,6,0),VLOOKUP(Positions!C23,'Stock Selection'!C:H,6,0)) -> 351.6 | P23: =IFERROR(O23*E23,G23) -> 21.93984 | Q23: =P23-G23 -> 0.740064 | R23: =F23/(1+I23-H23) -> 318.82508 | S23: =M23-F23 -> 39.987398 | T23: =0.5*(R23-F23) -> -10.457462 | U23: =S23+T23 -> 29.529936 | V23: =SUBTOTAL(4,$U$2:$U$10000)-U23 -> 0 | W23: =IFERROR((SUBTOTAL(109,$V$2:$V$1048576)/V23)/SUBTOTAL(109,$V$2:$V$1048576),0) -> 0 | X23: =V23/MAX($V$2:$V$28) -> 0
A24: Consumer Defensive | B24: MSG | C24: DAR | D24: =IF(ISERROR(VLOOKUP(C24,[1]Sheet1!$C:$C,1,0)),TODAY(),_xlfn.MINIFS([1]Sheet1!$F:$F,[1]Sheet1!$C:$C,C24)) -> 45796.825 | E24: =IFERROR(VLOOKUP(C24,'PBI Open Positions'!A:J,4,0),1E-32) -> 0.1091 | F24: =IFERROR(VLOOKUP(C24,'PBI Open Positions'!A:J,5,0),VLOOKUP(C24,'Stock Selection'!C:H,6,0)) -> 33.64 | G24: =E24*F24 -> 3.670124 | H24: 0.07 | I24: 0.4 | J24: =IFERROR(H24/I24,"") -> 0.175 | K24: =IFERROR(J24/SUBTOTAL(9,$J$2:$J$1048576),"") -> 0.045499079 | L24: =I24*G24 -> 1.4680496 | M24: =F24/(1-(F24*(1+H24)-F24)/(F24*(1+H24))) -> 35.9948 | N24: =M24*E24 -> 3.9270327 | O24: =IFERROR(VLOOKUP(C24,'PBI Open Positions'!A:F,6,0),VLOOKUP(Positions!C24,'Stock Selection'!C:H,6,0)) -> 38.5 | P24: =IFERROR(O24*E24,G24) -> 4.20035 | Q24: =P24-G24 -> 0.530226 | R24: =F24/(1+I24-H24) -> 25.293233 | S24: =M24-F24 -> 2.3548 | T24: =0.5*(R24-F24) -> -4.1733835 | U24: =S24+T24 -> -1.8185835 | V24: =SUBTOTAL(4,$U$2:$U$10000)-U24 -> 31.348519 | W24: =IFERROR((SUBTOTAL(109,$V$2:$V$1048576)/V24)/SUBTOTAL(109,$V$2:$V$1048576),0) -> 0 | X24: =V24/MAX($V$2:$V$28) -> 0.18153517
A25: Consumer Cyclical | B25: Yum! Brands | C25: YUM | D25: =IF(ISERROR(VLOOKUP(C25,[1]Sheet1!$C:$C,1,0)),TODAY(),_xlfn.MINIFS([1]Sheet1!$F:$F,[1]Sheet1!$C:$C,C25)) -> 45645.901 | E25: =IFERROR(VLOOKUP(C25,'PBI Open Positions'!A:J,4,0),1E-32) -> 0.2482 | F25: =IFERROR(VLOOKUP(C25,'PBI Open Positions'!A:J,5,0),VLOOKUP(C25,'Stock Selection'!C:H,6,0)) -> 141.14 | G25: =E25*F25 -> 35.030948 | H25: 0.07 | I25: 0.1623 | J25: =IFERROR(H25/I25,"") -> 0.43130006 | K25: =IFERROR(J25/SUBTOTAL(9,$J$2:$J$1048576),"") -> 0.11213575 | L25: =I25*G25 -> 5.6855229 | M25: =F25/(1-(F25*(1+H25)-F25)/(F25*(1+H25))) -> 151.0198 | N25: =M25*E25 -> 37.483114 | O25: =IFERROR(VLOOKUP(C25,'PBI Open Positions'!A:F,6,0),VLOOKUP(Positions!C25,'Stock Selection'!C:H,6,0)) -> 142.63 | P25: =IFERROR(O25*E25,G25) -> 35.400766 | Q25: =P25-G25 -> 0.369818 | R25: =F25/(1+I25-H25) -> 129.21359 | S25: =M25-F25 -> 9.8798 | T25: =0.5*(R25-F25) -> -5.963207 | U25: =S25+T25 -> 3.916593 | V25: =SUBTOTAL(4,$U$2:$U$10000)-U25 -> 25.613343 | W25: =IFERROR((SUBTOTAL(109,$V$2:$V$1048576)/V25)/SUBTOTAL(109,$V$2:$V$1048576),0) -> 0 | X25: =V25/MAX($V$2:$V$28) -> 0.14832351
A26: Technology | B26: Apple2 | C26: AAPL | D26: =IF(ISERROR(VLOOKUP(C26,[1]Sheet1!$C:$C,1,0)),TODAY(),_xlfn.MINIFS([1]Sheet1!$F:$F,[1]Sheet1!$C:$C,C26)) -> 45582.74 | E26: =IFERROR(VLOOKUP(C26,'PBI Open Positions'!A:J,4,0),1E-32) -> 0.0001 | F26: =IFERROR(VLOOKUP(C26,'PBI Open Positions'!A:J,5,0),VLOOKUP(C26,'Stock Selection'!C:H,6,0)) -> 200 | G26: =E26*F26 -> 0.02 | H26: 0.15 | I26: 0.2271 | J26: =IFERROR(H26/I26,"") -> 0.66050198 | K26: =IFERROR(J26/SUBTOTAL(9,$J$2:$J$1048576),"") -> 0.17172704 | L26: =I26*G26 -> 0.004542 | M26: =F26/(1-(F26*(1+H26)-F26)/(F26*(1+H26))) -> 230 | N26: =M26*E26 -> 0.023 | O26: =IFERROR(VLOOKUP(C26,'PBI Open Positions'!A:F,6,0),VLOOKUP(Positions!C26,'Stock Selection'!C:H,6,0)) -> 200 | P26: =IFERROR(O26*E26,G26) -> 0.02 | Q26: =P26-G26 -> 0 | R26: =F26/(1+I26-H26) -> 185.68378 | S26: =M26-F26 -> 30 | T26: =0.5*(R26-F26) -> -7.1581097 | U26: =S26+T26 -> 22.84189 | V26: =SUBTOTAL(4,$U$2:$U$10000)-U26 -> 6.6880453 | W26: =IFERROR((SUBTOTAL(109,$V$2:$V$1048576)/V26)/SUBTOTAL(109,$V$2:$V$1048576),0) -> 0 | X26: =V26/MAX($V$2:$V$28) -> 0.038729595
A27: Energy & Utilities | B27: Excelon | C27: EXC | D27: =IF(ISERROR(VLOOKUP(C27,[1]Sheet1!$C:$C,1,0)),TODAY(),_xlfn.MINIFS([1]Sheet1!$F:$F,[1]Sheet1!$C:$C,C27)) -> 45708.68 | E27: =IFERROR(VLOOKUP(C27,'PBI Open Positions'!A:J,4,0),1E-32) -> 0.6951 | F27: =IFERROR(VLOOKUP(C27,'PBI Open Positions'!A:J,5,0),VLOOKUP(C27,'Stock Selection'!C:H,6,0)) -> 43.16 | G27: =E27*F27 -> 30.000516 | H27: 0.05 | I27: 0.2029 | J27: =IFERROR(H27/I27,"") -> 0.24642681 | K27: =IFERROR(J27/SUBTOTAL(9,$J$2:$J$1048576),"") -> 0.064069674 | L27: =I27*G27 -> 6.0871047 | M27: =F27/(1-(F27*(1+H27)-F27)/(F27*(1+H27))) -> 45.318 | N27: =M27*E27 -> 31.500542 | O27: =IFERROR(VLOOKUP(C27,'PBI Open Positions'!A:F,6,0),VLOOKUP(Positions!C27,'Stock Selection'!C:H,6,0)) -> 43.09 | P27: =IFERROR(O27*E27,G27) -> 29.951859 | Q27: =P27-G27 -> -0.048657 | R27: =F27/(1+I27-H27) -> 37.436031 | S27: =M27-F27 -> 2.158 | T27: =0.5*(R27-F27) -> -2.8619846 | U27: =S27+T27 -> -0.70398456 | V27: =SUBTOTAL(4,$U$2:$U$10000)-U27 -> 30.23392 | W27: =IFERROR((SUBTOTAL(109,$V$2:$V$1048576)/V27)/SUBTOTAL(109,$V$2:$V$1048576),0) -> 0 | X27: =V27/MAX($V$2:$V$28) -> 0.17508067
A28: FOREX | B28: Gold | C28: GC=F | D28: =IF(ISERROR(VLOOKUP(C28,[1]Sheet1!$C:$C,1,0)),TODAY(),_xlfn.MINIFS([1]Sheet1!$F:$F,[1]Sheet1!$C:$C,C28)) -> 45833 | E28: =IFERROR(VLOOKUP(C28,'PBI Open Positions'!A:J,4,0),1E-32) -> 1e-32 | F28: =IFERROR(VLOOKUP(C28,'PBI Open Positions'!A:J,5,0),VLOOKUP(C28,'Stock Selection'!C:H,6,0)) -> 3340.3 | G28: =E28*F28 -> 3.3403e-29 | H28: 0.1 | I28: 0.5 | J28: =IFERROR(H28/I28,"") -> 0.2 | K28: =IFERROR(J28/SUBTOTAL(9,$J$2:$J$1048576),"") -> 0.051998947 | L28: =I28*G28 -> 1.67015e-29 | M28: =F28/(1-(F28*(1+H28)-F28)/(F28*(1+H28))) -> 3674.33 | N28: =M28*E28 -> 3.67433e-29 | O28: =IFERROR(VLOOKUP(C28,'PBI Open Positions'!A:F,6,0),VLOOKUP(Positions!C28,'Stock Selection'!C:H,6,0)) -> 3340.3 | P28: =IFERROR(O28*E28,G28) -> 3.3403e-29 | Q28: =P28-G28 -> 0 | R28: =F28/(1+I28-H28) -> 2385.9286 | S28: =M28-F28 -> 334.03 | T28: =0.5*(R28-F28) -> -477.18571 | U28: =S28+T28 -> -143.15571 | V28: =SUBTOTAL(4,$U$2:$U$10000)-U28 -> 172.68565 | W28: =IFERROR((SUBTOTAL(109,$V$2:$V$1048576)/V28)/SUBTOTAL(109,$V$2:$V$1048576),0) -> 0 | X28: =V28/MAX($V$2:$V$28) -> 1
A29: Technology | B29: ASML | C29: ASML | D29: =IF(ISERROR(VLOOKUP(C29,[1]Sheet1!$C:$C,1,0)),TODAY(),_xlfn.MINIFS([1]Sheet1!$F:$F,[1]Sheet1!$C:$C,C29)) -> 45833 | E29: =IFERROR(VLOOKUP(C29,'PBI Open Positions'!A:J,4,0),1E-32) -> 1e-32 | F29: =IFERROR(VLOOKUP(C29,'PBI Open Positions'!A:J,5,0),VLOOKUP(C29,'Stock Selection'!C:H,6,0)) -> 813.36 | G29: =E29*F29 -> 8.1336e-30 | H29: 0.1 | I29: 0.4534 | J29: =IFERROR(H29/I29,"") -> 0.2205558 | K29: =IFERROR(J29/SUBTOTAL(9,$J$2:$J$1048576),"") -> 0.057343347 | L29: =I29*G29 -> 3.6877742e-30 | M29: =F29/(1-(F29*(1+H29)-F29)/(F29*(1+H29))) -> 894.696 | N29: =M29*E29 -> 8.94696e-30 | O29: =IFERROR(VLOOKUP(C29,'PBI Open Positions'!A:F,6,0),VLOOKUP(Positions!C29,'Stock Selection'!C:H,6,0)) -> 813.36 | P29: =IFERROR(O29*E29,G29) -> 8.1336e-30 | Q29: =P29-G29 -> 0 | R29: =F29/(1+I29-H29) -> 600.97532 | S29: =M29-F29 -> 81.336 | T29: =0.5*(R29-F29) -> -106.19234 | U29: =S29+T29 -> -24.856339 | V29: =SUBTOTAL(4,$U$2:$U$10000)-U29 -> 54.386275 | W29: =IFERROR((SUBTOTAL(109,$V$2:$V$1048576)/V29)/SUBTOTAL(109,$V$2:$V$1048576),0) -> 0 | X29: =V29/MAX($V$2:$V$28) -> 0.3149438
A30: Consumer Cyclical | B30: LVMH | C30: MC.PA | D30: =IF(ISERROR(VLOOKUP(C30,[1]Sheet1!$C:$C,1,0)),TODAY(),_xlfn.MINIFS([1]Sheet1!$F:$F,[1]Sheet1!$C:$C,C30)) -> 45833 | E30: =IFERROR(VLOOKUP(C30,'PBI Open Positions'!A:J,4,0),1E-32) -> 1e-32 | F30: =IFERROR(VLOOKUP(C30,'PBI Open Positions'!A:J,5,0),VLOOKUP(C30,'Stock Selection'!C:H,6,0)) -> 453.55 | G30: =E30*F30 -> 4.5355e-30 | H30: 0.05 | I30: 0.28 | J30: =IFERROR(H30/I30,"") -> 0.17857143 | K30: =IFERROR(J30/SUBTOTAL(9,$J$2:$J$1048576),"") -> 0.046427632 | L30: =I30*G30 -> 1.26994e-30 | M30: =F30/(1-(F30*(1+H30)-F30)/(F30*(1+H30))) -> 476.2275 | N30: =M30*E30 -> 4.762275e-30 | O30: =IFERROR(VLOOKUP(C30,'PBI Open Positions'!A:F,6,0),VLOOKUP(Positions!C30,'Stock Selection'!C:H,6,0)) -> 453.55 | P30: =IFERROR(O30*E30,G30) -> 4.5355e-30 | Q30: =P30-G30 -> 0 | R30: =F30/(1+I30-H30) -> 368.73984 | S30: =M30-F30 -> 22.6775 | T30: =0.5*(R30-F30) -> -42.405081 | U30: =S30+T30 -> -19.727581 | V30: =SUBTOTAL(4,$U$2:$U$10000)-U30 -> 49.257517 | W30: =IFERROR((SUBTOTAL(109,$V$2:$V$1048576)/V30)/SUBTOTAL(109,$V$2:$V$1048576),0) -> 0 | X30: =V30/MAX($V$2:$V$28) -> 0.28524383
A31: Healthcare | B31: HCA Healthcare | C31: HCA | D31: =IF(ISERROR(VLOOKUP(C31,[1]Sheet1!$C:$C,1,0)),TODAY(),_xlfn.MINIFS([1]Sheet1!$F:$F,[1]Sheet1!$C:$C,C31)) -> 45833 | E31: =IFERROR(VLOOKUP(C31,'PBI Open Positions'!A:J,4,0),1E-32) -> 1e-32 | F31: =IFERROR(VLOOKUP(C31,'PBI Open Positions'!A:J,5,0),VLOOKUP(C31,'Stock Selection'!C:H,6,0)) -> 379.02 | G31: =E31*F31 -> 3.7902e-30 | H31: 0.2 | I31: 0.2 | J31: =IFERROR(H31/I31,"") -> 1 | K31: =IFERROR(J31/SUBTOTAL(9,$J$2:$J$1048576),"") -> 0.25999474 | L31: =I31*G31 -> 7.5804e-31 | M31: =F31/(1-(F31*(1+H31)-F31)/(F31*(1+H31))) -> 454.824 | N31: =M31*E31 -> 4.54824e-30 | O31: =IFERROR(VLOOKUP(C31,'PBI Open Positions'!A:F,6,0),VLOOKUP(Positions!C31,'Stock Selection'!C:H,6,0)) -> 379.02 | P31: =IFERROR(O31*E31,G31) -> 3.7902e-30 | Q31: =P31-G31 -> 0 | R31: =F31/(1+I31-H31) -> 379.02 | S31: =M31-F31 -> 75.804 | T31: =0.5*(R31-F31) -> 0 | U31: =S31+T31 -> 75.804 | V31: =SUBTOTAL(4,$U$2:$U$10000)-U31 -> -46.274064 | W31: =IFERROR((SUBTOTAL(109,$V$2:$V$1048576)/V31)/SUBTOTAL(109,$V$2:$V$1048576),0) -> 0 | X31: =V31/MAX($V$2:$V$28) -> -0.26796705
A32: Technology | B32: QualComm2 | C32: QCOM | D32: =IF(ISERROR(VLOOKUP(C32,[1]Sheet1!$C:$C,1,0)),TODAY(),_xlfn.MINIFS([1]Sheet1!$F:$F,[1]Sheet1!$C:$C,C32)) -> 45833 | E32: =IFERROR(VLOOKUP(C32,'PBI Open Positions'!A:J,4,0),1E-32) -> 1e-32 | F32: =IFERROR(VLOOKUP(C32,'PBI Open Positions'!A:J,5,0),VLOOKUP(C32,'Stock Selection'!C:H,6,0)) -> 155.71 | G32: =E32*F32 -> 1.5571e-30 | H32: 0.15 | I32: 0.3778 | J32: =IFERROR(H32/I32,"") -> 0.39703547 | K32: =IFERROR(J32/SUBTOTAL(9,$J$2:$J$1048576),"") -> 0.10322713 | L32: =I32*G32 -> 5.8827238e-31 | M32: =F32/(1-(F32*(1+H32)-F32)/(F32*(1+H32))) -> 179.0665 | N32: =M32*E32 -> 1.790665e-30 | O32: =IFERROR(VLOOKUP(C32,'PBI Open Positions'!A:F,6,0),VLOOKUP(Positions!C32,'Stock Selection'!C:H,6,0)) -> 155.71 | P32: =IFERROR(O32*E32,G32) -> 1.5571e-30 | Q32: =P32-G32 -> 0 | R32: =F32/(1+I32-H32) -> 126.82033 | S32: =M32-F32 -> 23.3565 | T32: =0.5*(R32-F32) -> -14.444835 | U32: =S32+T32 -> 8.9116645 | V32: =SUBTOTAL(4,$U$2:$U$10000)-U32 -> 20.618271 | W32: =IFERROR((SUBTOTAL(109,$V$2:$V$1048576)/V32)/SUBTOTAL(109,$V$2:$V$1048576),0) -> 0 | X32: =V32/MAX($V$2:$V$28) -> 0.11939771
... A36: Industrials | B36: 3M | C36: MMM | D36: =IF(ISERROR(VLOOKUP(C36,[1]Sheet1!$C:$C,1,0)),TODAY(),_xlfn.MINIFS([1]Sheet1!$F:$F,[1]Sheet1!$C:$C,C36)) -> 45833 | E36: =IFERROR(VLOOKUP(C36,'PBI Open Positions'!A:J,4,0),1E-32) -> 1e-32 | F36: =IFERROR(VLOOKUP(C36,'PBI Open Positions'!A:J,5,0),VLOOKUP(C36,'Stock Selection'!C:H,6,0)) -> 149.87 | G36: =E36*F36 -> 1.4987e-30 | H36: 0.07 | I36: 0.2 | J36: =IFERROR(H36/I36,"") -> 0.35 | K36: =IFERROR(J36/SUBTOTAL(9,$J$2:$J$1048576),"") -> 0.090998158 | L36: =I36*G36 -> 2.9974e-31 | M36: =F36/(1-(F36*(1+H36)-F36)/(F36*(1+H36))) -> 160.3609 | N36: =M36*E36 -> 1.603609e-30 | O36: =IFERROR(VLOOKUP(C36,'PBI Open Positions'!A:F,6,0),VLOOKUP(Positions!C36,'Stock Selection'!C:H,6,0)) -> 149.87 | P36: =IFERROR(O36*E36,G36) -> 1.4987e-30 | Q36: =P36-G36 -> 0 | R36: =F36/(1+I36-H36) -> 132.62832 | S36: =M36-F36 -> 10.4909 | T36: =0.5*(R36-F36) -> -8.6208407 | U36: =S36+T36 -> 1.8700593 | V36: =SUBTOTAL(4,$U$2:$U$10000)-U36 -> 27.659876 | W36: =IFERROR((SUBTOTAL(109,$V$2:$V$1048576)/V36)/SUBTOTAL(109,$V$2:$V$1048576),0) -> 0 | X36: =V36/MAX($V$2:$V$28) -> 0.16017472
A37: Energy & Utilities | B37: Duke Energy | C37: DUK | D37: =IF(ISERROR(VLOOKUP(C37,[1]Sheet1!$C:$C,1,0)),TODAY(),_xlfn.MINIFS([1]Sheet1!$F:$F,[1]Sheet1!$C:$C,C37)) -> 45833 | E37: =IFERROR(VLOOKUP(C37,'PBI Open Positions'!A:J,4,0),1E-32) -> 1e-32 | F37: =IFERROR(VLOOKUP(C37,'PBI Open Positions'!A:J,5,0),VLOOKUP(C37,'Stock Selection'!C:H,6,0)) -> 116.95 | G37: =E37*F37 -> 1.1695e-30 | H37: =121.15/F37-1 -> 0.035912783 | I37: 0.1768 | J37: =IFERROR(H37/I37,"") -> 0.2031266 | K37: =IFERROR(J37/SUBTOTAL(9,$J$2:$J$1048576),"") -> 0.052811847 | L37: =I37*G37 -> 2.067676e-31 | M37: =F37/(1-(F37*(1+H37)-F37)/(F37*(1+H37))) -> 121.15 | N37: =M37*E37 -> 1.2115e-30 | O37: =IFERROR(VLOOKUP(C37,'PBI Open Positions'!A:F,6,0),VLOOKUP(Positions!C37,'Stock Selection'!C:H,6,0)) -> 116.95 | P37: =IFERROR(O37*E37,G37) -> 1.1695e-30 | Q37: =P37-G37 -> 0 | R37: =F37/(1+I37-H37) -> 102.50794 | S37: =M37-F37 -> 4.2 | T37: =0.5*(R37-F37) -> -7.2210293 | U37: =S37+T37 -> -3.0210293 | V37: =SUBTOTAL(4,$U$2:$U$10000)-U37 -> 32.550965 | W37: =IFERROR((SUBTOTAL(109,$V$2:$V$1048576)/V37)/SUBTOTAL(109,$V$2:$V$1048576),0) -> 0 | X37: =V37/MAX($V$2:$V$28) -> 0.18849838
A38: Consumer Defensive | B38: Walmart | C38: WMT | D38: =IF(ISERROR(VLOOKUP(C38,[1]Sheet1!$C:$C,1,0)),TODAY(),_xlfn.MINIFS([1]Sheet1!$F:$F,[1]Sheet1!$C:$C,C38)) -> 45833 | E38: =IFERROR(VLOOKUP(C38,'PBI Open Positions'!A:J,4,0),1E-32) -> 1e-32 | F38: =IFERROR(VLOOKUP(C38,'PBI Open Positions'!A:J,5,0),VLOOKUP(C38,'Stock Selection'!C:H,6,0)) -> 98 | G38: =E38*F38 -> 9.8e-31 | H38: 0.07 | I38: 0.1725 | J38: =IFERROR(H38/I38,"") -> 0.4057971 | K38: =IFERROR(J38/SUBTOTAL(9,$J$2:$J$1048576),"") -> 0.10550511 | L38: =I38*G38 -> 1.6905e-31 | M38: =F38/(1-(F38*(1+H38)-F38)/(F38*(1+H38))) -> 104.86 | N38: =M38*E38 -> 1.0486e-30 | O38: =IFERROR(VLOOKUP(C38,'PBI Open Positions'!A:F,6,0),VLOOKUP(Positions!C38,'Stock Selection'!C:H,6,0)) -> 98 | P38: =IFERROR(O38*E38,G38) -> 9.8e-31 | Q38: =P38-G38 -> 0 | R38: =F38/(1+I38-H38) -> 88.888889 | S38: =M38-F38 -> 6.86 | T38: =0.5*(R38-F38) -> -4.5555556 | U38: =S38+T38 -> 2.3044444 | V38: =SUBTOTAL(4,$U$2:$U$10000)-U38 -> 27.225491 | W38: =IFERROR((SUBTOTAL(109,$V$2:$V$1048576)/V38)/SUBTOTAL(109,$V$2:$V$1048576),0) -> 0 | X38: =V38/MAX($V$2:$V$28) -> 0.15765926
A39: Technology | B39: Palantir | C39: PLTR | D39: =IF(ISERROR(VLOOKUP(C39,[1]Sheet1!$C:$C,1,0)),TODAY(),_xlfn.MINIFS([1]Sheet1!$F:$F,[1]Sheet1!$C:$C,C39)) -> 45833 | E39: =IFERROR(VLOOKUP(C39,'PBI Open Positions'!A:J,4,0),1E-32) -> 1e-32 | F39: =IFERROR(VLOOKUP(C39,'PBI Open Positions'!A:J,5,0),VLOOKUP(C39,'Stock Selection'!C:H,6,0)) -> 143.23 | G39: =E39*F39 -> 1.4323e-30 | H39: 0.15 | I39: 0.673 | J39: =IFERROR(H39/I39,"") -> 0.22288262 | K39: =IFERROR(J39/SUBTOTAL(9,$J$2:$J$1048576),"") -> 0.057948307 | L39: =I39*G39 -> 9.639379e-31 | M39: =F39/(1-(F39*(1+H39)-F39)/(F39*(1+H39))) -> 164.7145 | N39: =M39*E39 -> 1.647145e-30 | O39: =IFERROR(VLOOKUP(C39,'PBI Open Positions'!A:F,6,0),VLOOKUP(Positions!C39,'Stock Selection'!C:H,6,0)) -> 143.23 | P39: =IFERROR(O39*E39,G39) -> 1.4323e-30 | Q39: =P39-G39 -> 0 | R39: =F39/(1+I39-H39) -> 94.044649 | S39: =M39-F39 -> 21.4845 | T39: =0.5*(R39-F39) -> -24.592676 | U39: =S39+T39 -> -3.1081756 | V39: =SUBTOTAL(4,$U$2:$U$10000)-U39 -> 32.638111 | W39: =IFERROR((SUBTOTAL(109,$V$2:$V$1048576)/V39)/SUBTOTAL(109,$V$2:$V$1048576),0) -> 0 | X39: =V39/MAX($V$2:$V$28) -> 0.18900303
A40: Consumer Cyclical | B40: Aptive Autoparts | C40: APTV | D40: =IF(ISERROR(VLOOKUP(C40,[1]Sheet1!$C:$C,1,0)),TODAY(),_xlfn.MINIFS([1]Sheet1!$F:$F,[1]Sheet1!$C:$C,C40)) -> 45833 | E40: =IFERROR(VLOOKUP(C40,'PBI Open Positions'!A:J,4,0),1E-32) -> 1e-32 | F40: =IFERROR(VLOOKUP(C40,'PBI Open Positions'!A:J,5,0),VLOOKUP(C40,'Stock Selection'!C:H,6,0)) -> 68.45 | G40: =E40*F40 -> 6.845e-31 | H40: 0.07 | I40: 0.19 | J40: =IFERROR(H40/I40,"") -> 0.36842105 | K40: =IFERROR(J40/SUBTOTAL(9,$J$2:$J$1048576),"") -> 0.095787535 | L40: =I40*G40 -> 1.30055e-31 | M40: =F40/(1-(F40*(1+H40)-F40)/(F40*(1+H40))) -> 73.2415 | N40: =M40*E40 -> 7.32415e-31 | O40: =IFERROR(VLOOKUP(C40,'PBI Open Positions'!A:F,6,0),VLOOKUP(Positions!C40,'Stock Selection'!C:H,6,0)) -> 68.45 | P40: =IFERROR(O40*E40,G40) -> 6.845e-31 | Q40: =P40-G40 -> 0 | R40: =F40/(1+I40-H40) -> 61.116071 | S40: =M40-F40 -> 4.7915 | T40: =0.5*(R40-F40) -> -3.6669643 | U40: =S40+T40 -> 1.1245357 | V40: =SUBTOTAL(4,$U$2:$U$10000)-U40 -> 28.4054 | W40: =IFERROR((SUBTOTAL(109,$V$2:$V$1048576)/V40)/SUBTOTAL(109,$V$2:$V$1048576),0) -> 0 | X40: =V40/MAX($V$2:$V$28) -> 0.16449195
A41: Consumer Cyclical | B41: Yum China Holding | C41: YUMC | D41: =IF(ISERROR(VLOOKUP(C41,[1]Sheet1!$C:$C,1,0)),TODAY(),_xlfn.MINIFS([1]Sheet1!$F:$F,[1]Sheet1!$C:$C,C41)) -> 45833 | E41: =IFERROR(VLOOKUP(C41,'PBI Open Positions'!A:J,4,0),1E-32) -> 1e-32 | F41: =IFERROR(VLOOKUP(C41,'PBI Open Positions'!A:J,5,0),VLOOKUP(C41,'Stock Selection'!C:H,6,0)) -> 44.4 | G41: =E41*F41 -> 4.44e-31 | H41: 0.07 | I41: 0.4 | J41: =IFERROR(H41/I41,"") -> 0.175 | K41: =IFERROR(J41/SUBTOTAL(9,$J$2:$J$1048576),"") -> 0.045499079 | L41: =I41*G41 -> 1.776e-31 | M41: =F41/(1-(F41*(1+H41)-F41)/(F41*(1+H41))) -> 47.508 | N41: =M41*E41 -> 4.7508e-31 | O41: =IFERROR(VLOOKUP(C41,'PBI Open Positions'!A:F,6,0),VLOOKUP(Positions!C41,'Stock Selection'!C:H,6,0)) -> 44.4 | P41: =IFERROR(O41*E41,G41) -> 4.44e-31 | Q41: =P41-G41 -> 0 | R41: =F41/(1+I41-H41) -> 33.383459 | S41: =M41-F41 -> 3.108 | T41: =0.5*(R41-F41) -> -5.5082707 | U41: =S41+T41 -> -2.4002707 | V41: =SUBTOTAL(4,$U$2:$U$10000)-U41 -> 31.930206 | W41: =IFERROR((SUBTOTAL(109,$V$2:$V$1048576)/V41)/SUBTOTAL(109,$V$2:$V$1048576),0) -> 0 | X41: =V41/MAX($V$2:$V$28) -> 0.18490365
A42: Energy & Utilities | B42: PG&E | C42: PCG | D42: =IF(ISERROR(VLOOKUP(C42,[1]Sheet1!$C:$C,1,0)),TODAY(),_xlfn.MINIFS([1]Sheet1!$F:$F,[1]Sheet1!$C:$C,C42)) -> 45833 | E42: =IFERROR(VLOOKUP(C42,'PBI Open Positions'!A:J,4,0),1E-32) -> 1e-32 | F42: =IFERROR(VLOOKUP(C42,'PBI Open Positions'!A:J,5,0),VLOOKUP(C42,'Stock Selection'!C:H,6,0)) -> 14.16 | G42: =E42*F42 -> 1.416e-31 | H42: 0.1 | I42: 0.2255 | J42: =IFERROR(H42/I42,"") -> 0.44345898 | K42: =IFERROR(J42/SUBTOTAL(9,$J$2:$J$1048576),"") -> 0.115297 | L42: =I42*G42 -> 3.19308e-32 | M42: =F42/(1-(F42*(1+H42)-F42)/(F42*(1+H42))) -> 15.576 | N42: =M42*E42 -> 1.5576e-31 | O42: =IFERROR(VLOOKUP(C42,'PBI Open Positions'!A:F,6,0),VLOOKUP(Positions!C42,'Stock Selection'!C:H,6,0)) -> 14.16 | P42: =IFERROR(O42*E42,G42) -> 1.416e-31 | Q42: =P42-G42 -> 0 | R42: =F42/(1+I42-H42) -> 12.581075 | S42: =M42-F42 -> 1.416 | T42: =0.5*(R42-F42) -> -0.78946246 | U42: =S42+T42 -> 0.62653754 | V42: =SUBTOTAL(4,$U$2:$U$10000)-U42 -> 28.903398 | W42: =IFERROR((SUBTOTAL(109,$V$2:$V$1048576)/V42)/SUBTOTAL(109,$V$2:$V$1048576),0) -> 0 | X42: =V42/MAX($V$2:$V$28) -> 0.1673758
A43: Technology | B43: Jinko Solar | C43: JKS | D43: =IF(ISERROR(VLOOKUP(C43,[1]Sheet1!$C:$C,1,0)),TODAY(),_xlfn.MINIFS([1]Sheet1!$F:$F,[1]Sheet1!$C:$C,C43)) -> 45833 | E43: =IFERROR(VLOOKUP(C43,'PBI Open Positions'!A:J,4,0),1E-32) -> 1e-32 | F43: =IFERROR(VLOOKUP(C43,'PBI Open Positions'!A:J,5,0),VLOOKUP(C43,'Stock Selection'!C:H,6,0)) -> 20.44 | G43: =E43*F43 -> 2.044e-31 | H43: 0.05 | I43: 0.6681 | J43: =IFERROR(H43/I43,"") -> 0.074839096 | K43: =IFERROR(J43/SUBTOTAL(9,$J$2:$J$1048576),"") -> 0.019457771 | L43: =I43*G43 -> 1.3655964e-31 | M43: =F43/(1-(F43*(1+H43)-F43)/(F43*(1+H43))) -> 21.462 | N43: =M43*E43 -> 2.1462e-31 | O43: =IFERROR(VLOOKUP(C43,'PBI Open Positions'!A:F,6,0),VLOOKUP(Positions!C43,'Stock Selection'!C:H,6,0)) -> 20.44 | P43: =IFERROR(O43*E43,G43) -> 2.044e-31 | Q43: =P43-G43 -> 0 | R43: =F43/(1+I43-H43) -> 12.632099 | S43: =M43-F43 -> 1.022 | T43: =0.5*(R43-F43) -> -3.9039503 | U43: =S43+T43 -> -2.8819503 | V43: =SUBTOTAL(4,$U$2:$U$10000)-U43 -> 32.411886 | W43: =IFERROR((SUBTOTAL(109,$V$2:$V$1048576)/V43)/SUBTOTAL(109,$V$2:$V$1048576),0) -> 0 | X43: =V43/MAX($V$2:$V$28) -> 0.18769299
A44: FOREX | B44: Mexican Peso | C44: MXN=X | D44: =IF(ISERROR(VLOOKUP(C44,[1]Sheet1!$C:$C,1,0)),TODAY(),_xlfn.MINIFS([1]Sheet1!$F:$F,[1]Sheet1!$C:$C,C44)) -> 45833 | E44: =IFERROR(VLOOKUP(C44,'PBI Open Positions'!A:J,4,0),1E-32) -> 1e-32 | F44: =IFERROR(VLOOKUP(C44,'PBI Open Positions'!A:J,5,0),VLOOKUP(C44,'Stock Selection'!C:H,6,0)) -> 18.98 | G44: =E44*F44 -> 1.898e-31 | H44: 0.1 | I44: 0.15 | J44: =IFERROR(H44/I44,"") -> 0.66666667 | K44: =IFERROR(J44/SUBTOTAL(9,$J$2:$J$1048576),"") -> 0.17332982 | L44: =I44*G44 -> 2.847e-32 | M44: 21.2 | N44: =M44*E44 -> 2.12e-31 | O44: =IFERROR(VLOOKUP(C44,'PBI Open Positions'!A:F,6,0),VLOOKUP(Positions!C44,'Stock Selection'!C:H,6,0)) -> 18.98 | P44: =IFERROR(O44*E44,G44) -> 1.898e-31 | Q44: =P44-G44 -> 0 | R44: =F44/(1+I44-H44) -> 18.07619 | S44: =M44-F44 -> 2.22 | T44: =0.5*(R44-F44) -> -0.45190476 | U44: =S44+T44 -> 1.7680952 | V44: =SUBTOTAL(4,$U$2:$U$10000)-U44 -> 27.76184 | W44: =IFERROR((SUBTOTAL(109,$V$2:$V$1048576)/V44)/SUBTOTAL(109,$V$2:$V$1048576),0) -> 0 | X44: =V44/MAX($V$2:$V$28) -> 0.16076518
A45: Energy & Utilities | B45: SolarWinds | C45: SWI.US | D45: =IF(ISERROR(VLOOKUP(C45,[1]Sheet1!$C:$C,1,0)),TODAY(),_xlfn.MINIFS([1]Sheet1!$F:$F,[1]Sheet1!$C:$C,C45)) -> 45833 | E45: =IFERROR(VLOOKUP(C45,'PBI Open Positions'!A:J,4,0),1E-32) -> 1e-32 | F45: 18.49 | G45: =E45*F45 -> 1.849e-31 | H45: 0.29 | I45: 0.3551 | J45: =IFERROR(H45/I45,"") -> 0.81667136 | K45: =IFERROR(J45/SUBTOTAL(9,$J$2:$J$1048576),"") -> 0.21233026 | L45: =I45*G45 -> 6.565799e-32 | M45: =F45/(1-(F45*(1+H45)-F45)/(F45*(1+H45))) -> 23.8521 | N45: =M45*E45 -> 2.38521e-31 | O45: =IFERROR(VLOOKUP(C45,'PBI Open Positions'!A:F,6,0),VLOOKUP(Positions!C45,'Stock Selection'!C:H,6,0)) -> 0 | P45: =IFERROR(O45*E45,G45) -> 0 | Q45: =P45-G45 -> -1.849e-31 | R45: =F45/(1+I45-H45) -> 17.359872 | S45: =M45-F45 -> 5.3621 | T45: =0.5*(R45-F45) -> -0.56506384 | U45: =S45+T45 -> 4.7970362 | V45: =SUBTOTAL(4,$U$2:$U$10000)-U45 -> 24.732899 | W45: =IFERROR((SUBTOTAL(109,$V$2:$V$1048576)/V45)/SUBTOTAL(109,$V$2:$V$1048576),0) -> 0 | X45: =V45/MAX($V$2:$V$28) -> 0.14322498
A46: Technology | B46: Canadian Solar | C46: CSIQ | D46: =IF(ISERROR(VLOOKUP(C46,[1]Sheet1!$C:$C,1,0)),TODAY(),_xlfn.MINIFS([1]Sheet1!$F:$F,[1]Sheet1!$C:$C,C46)) -> 45833 | E46: =IFERROR(VLOOKUP(C46,'PBI Open Positions'!A:J,4,0),1E-32) -> 1e-32 | F46: =IFERROR(VLOOKUP(C46,'PBI Open Positions'!A:J,5,0),VLOOKUP(C46,'Stock Selection'!C:H,6,0)) -> 10.61 | G46: =E46*F46 -> 1.061e-31 | H46: 0.05 | I46: 0.7217 | J46: =IFERROR(H46/I46,"") -> 0.069280865 | K46: =IFERROR(J46/SUBTOTAL(9,$J$2:$J$1048576),"") -> 0.01801266 | L46: =I46*G46 -> 7.657237e-32 | M46: =F46/(1-(F46*(1+H46)-F46)/(F46*(1+H46))) -> 11.1405 | N46: =M46*E46 -> 1.11405e-31 | O46: =IFERROR(VLOOKUP(C46,'PBI Open Positions'!A:F,6,0),VLOOKUP(Positions!C46,'Stock Selection'!C:H,6,0)) -> 10.61 | P46: =IFERROR(O46*E46,G46) -> 1.061e-31 | Q46: =P46-G46 -> 0 | R46: =F46/(1+I46-H46) -> 6.3468326 | S46: =M46-F46 -> 0.5305 | T46: =0.5*(R46-F46) -> -2.1315837 | U46: =S46+T46 -> -1.6010837 | V46: =SUBTOTAL(4,$U$2:$U$10000)-U46 -> 31.131019 | W46: =IFERROR((SUBTOTAL(109,$V$2:$V$1048576)/V46)/SUBTOTAL(109,$V$2:$V$1048576),0) -> 0 | X46: =V46/MAX($V$2:$V$28) -> 0.18027566
A47: Technology | B47: Maxeon Solar | C47: MAXN | D47: =IF(ISERROR(VLOOKUP(C47,[1]Sheet1!$C:$C,1,0)),TODAY(),_xlfn.MINIFS([1]Sheet1!$F:$F,[1]Sheet1!$C:$C,C47)) -> 45833 | E47: =IFERROR(VLOOKUP(C47,'PBI Open Positions'!A:J,4,0),1E-32) -> 1e-32 | F47: =IFERROR(VLOOKUP(C47,'PBI Open Positions'!A:J,5,0),VLOOKUP(C47,'Stock Selection'!C:H,6,0)) -> 2.92 | G47: =E47*F47 -> 2.92e-32 | H47: 0 | I47: 1.8652 | J47: =IFERROR(H47/I47,"") -> 0 | K47: =IFERROR(J47/SUBTOTAL(9,$J$2:$J$1048576),"") -> 0 | L47: =I47*G47 -> 5.446384e-32 | M47: =F47/(1-(F47*(1+H47)-F47)/(F47*(1+H47))) -> 2.92 | N47: =M47*E47 -> 2.92e-32 | O47: =IFERROR(VLOOKUP(C47,'PBI Open Positions'!A:F,6,0),VLOOKUP(Positions!C47,'Stock Selection'!C:H,6,0)) -> 2.92 | P47: =IFERROR(O47*E47,G47) -> 2.92e-32 | Q47: =P47-G47 -> 0 | R47: =F47/(1+I47-H47) -> 1.0191261 | S47: =M47-F47 -> 0 | T47: =0.5*(R47-F47) -> -0.95043697 | U47: =S47+T47 -> -0.95043697 | V47: =SUBTOTAL(4,$U$2:$U$10000)-U47 -> 30.480373 | W47: =IFERROR((SUBTOTAL(109,$V$2:$V$1048576)/V47)/SUBTOTAL(109,$V$2:$V$1048576),0) -> 0 | X47: =V47/MAX($V$2:$V$28) -> 0.17650785
A48: Financial Services | B48: BBVA | C48: BBVA.MC | D48: =IF(ISERROR(VLOOKUP(C48,[1]Sheet1!$C:$C,1,0)),TODAY(),_xlfn.MINIFS([1]Sheet1!$F:$F,[1]Sheet1!$C:$C,C48)) -> 45785.67 | E48: =IFERROR(VLOOKUP(C48,'PBI Open Positions'!A:J,4,0),1E-32) -> 6.0332 | F48: =IFERROR(VLOOKUP(C48,'PBI Open Positions'!A:J,5,0),VLOOKUP(C48,'Stock Selection'!C:H,6,0)) -> 14.92 | G48: =E48*F48 -> 90.015344 | H48: 0.1177 | I48: 0.1833 | J48: =IFERROR(H48/I48,"") -> 0.64211675 | K48: =IFERROR(J48/SUBTOTAL(9,$J$2:$J$1048576),"") -> 0.16694697 | L48: =I48*G48 -> 16.499813 | M48: =F48/(1-(F48*(1+H48)-F48)/(F48*(1+H48))) -> 16.676084 | N48: =M48*E48 -> 100.61015 | O48: =IFERROR(VLOOKUP(C48,'PBI Open Positions'!A:F,6,0),VLOOKUP(Positions!C48,'Stock Selection'!C:H,6,0)) -> 15.14 | P48: =IFERROR(O48*E48,G48) -> 91.342648 | Q48: =P48-G48 -> 1.327304 | R48: =F48/(1+I48-H48) -> 14.001502 | S48: =M48-F48 -> 1.756084 | T48: =0.5*(R48-F48) -> -0.45924925 | U48: =S48+T48 -> 1.2968348 | V48: =SUBTOTAL(4,$U$2:$U$10000)-U48 -> 28.233101 | W48: =IFERROR((SUBTOTAL(109,$V$2:$V$1048576)/V48)/SUBTOTAL(109,$V$2:$V$1048576),0) -> 0 | X48: =V48/MAX($V$2:$V$28) -> 0.16349419
A49: Financial Services | B49: BANCOLOMBIA | C49: CIB | D49: =IF(ISERROR(VLOOKUP(C49,[1]Sheet1!$C:$C,1,0)),TODAY(),_xlfn.MINIFS([1]Sheet1!$F:$F,[1]Sheet1!$C:$C,C49)) -> 45789.649 | E49: =IFERROR(VLOOKUP(C49,'PBI Open Positions'!A:J,4,0),1E-32) -> 1.5439 | F49: =IFERROR(VLOOKUP(C49,'PBI Open Positions'!A:J,5,0),VLOOKUP(C49,'Stock Selection'!C:H,6,0)) -> 42.09 | G49: =E49*F49 -> 64.982751 | H49: 0.1177 | I49: 0.1833 | J49: =IFERROR(H49/I49,"") -> 0.64211675 | K49: =IFERROR(J49/SUBTOTAL(9,$J$2:$J$1048576),"") -> 0.16694697 | L49: =I49*G49 -> 11.911338 | M49: =F49/(1-(F49*(1+H49)-F49)/(F49*(1+H49))) -> 47.043993 | N49: =M49*E49 -> 72.631221 | O49: =IFERROR(VLOOKUP(C49,'PBI Open Positions'!A:F,6,0),VLOOKUP(Positions!C49,'Stock Selection'!C:H,6,0)) -> 44.92 | P49: =IFERROR(O49*E49,G49) -> 69.351988 | Q49: =P49-G49 -> 4.369237 | R49: =F49/(1+I49-H49) -> 39.498874 | S49: =M49-F49 -> 4.953993 | T49: =0.5*(R49-F49) -> -1.2955631 | U49: =S49+T49 -> 3.6584299 | V49: =SUBTOTAL(4,$U$2:$U$10000)-U49 -> 25.871506 | W49: =IFERROR((SUBTOTAL(109,$V$2:$V$1048576)/V49)/SUBTOTAL(109,$V$2:$V$1048576),0) -> 0 | X49: =V49/MAX($V$2:$V$28) -> 0.1498185
A50: MISC | C50: AEP | D50: =IF(ISERROR(VLOOKUP(C50,[1]Sheet1!$C:$C,1,0)),TODAY(),_xlfn.MINIFS([1]Sheet1!$F:$F,[1]Sheet1!$C:$C,C50)) -> 45833 | E50: =IFERROR(VLOOKUP(C50,'PBI Open Positions'!A:J,4,0),1E-32) -> 1e-32 | F50: =IFERROR(VLOOKUP(C50,'PBI Open Positions'!A:J,5,0),VLOOKUP(C50,'Stock Selection'!C:H,6,0)) -> 103.28 | G50: =E50*F50 -> 1.0328e-30 | H50: 0.05 | I50: 0.1833 | J50: =IFERROR(H50/I50,"") -> 0.27277687 | K50: =IFERROR(J50/SUBTOTAL(9,$J$2:$J$1048576),"") -> 0.07092055 | L50: =I50*G50 -> 1.8931224e-31 | M50: =F50/(1-(F50*(1+H50)-F50)/(F50*(1+H50))) -> 108.444 | N50: =M50*E50 -> 1.08444e-30 | O50: =IFERROR(VLOOKUP(C50,'PBI Open Positions'!A:F,6,0),VLOOKUP(Positions!C50,'Stock Selection'!C:H,6,0)) -> 103.28 | P50: =IFERROR(O50*E50,G50) -> 1.0328e-30 | Q50: =P50-G50 -> 0 | R50: =F50/(1+I50-H50) -> 91.132092 | S50: =M50-F50 -> 5.164 | T50: =0.5*(R50-F50) -> -6.0739539 | U50: =S50+T50 -> -0.90995394 | V50: =SUBTOTAL(4,$U$2:$U$10000)-U50 -> 30.439889 | W50: =IFERROR((SUBTOTAL(109,$V$2:$V$1048576)/V50)/SUBTOTAL(109,$V$2:$V$1048576),0) -> 0 | X50: =V50/MAX($V$2:$V$28) -> 0.17627342
A51: MISC | C51: AVGO | D51: =IF(ISERROR(VLOOKUP(C51,[1]Sheet1!$C:$C,1,0)),TODAY(),_xlfn.MINIFS([1]Sheet1!$F:$F,[1]Sheet1!$C:$C,C51)) -> 45833 | E51: =IFERROR(VLOOKUP(C51,'PBI Open Positions'!A:J,4,0),1E-32) -> 1e-32 | F51: =IFERROR(VLOOKUP(C51,'PBI Open Positions'!A:J,5,0),VLOOKUP(C51,'Stock Selection'!C:H,6,0)) -> 0 | G51: =E51*F51 -> 0 | H51: 0.05 | I51: 0.1833 | J51: =IFERROR(H51/I51,"") -> 0.27277687 | K51: =IFERROR(J51/SUBTOTAL(9,$J$2:$J$1048576),"") -> 0.07092055 | L51: =I51*G51 -> 0 | M51: =F51/(1-(F51*(1+H51)-F51)/(F51*(1+H51))) -> #DIV/0! | N51: =M51*E51 -> #DIV/0! | O51: =IFERROR(VLOOKUP(C51,'PBI Open Positions'!A:F,6,0),VLOOKUP(Positions!C51,'Stock Selection'!C:H,6,0)) -> 0 | P51: =IFERROR(O51*E51,G51) -> 0 | Q51: =P51-G51 -> 0 | R51: =F51/(1+I51-H51) -> 0 | S51: =M51-F51 -> #DIV/0! | T51: =0.5*(R51-F51) -> 0 | U51: =S51+T51 -> #DIV/0! | V51: =SUBTOTAL(4,$U$2:$U$10000)-U51 -> #DIV/0! | W51: =IFERROR((SUBTOTAL(109,$V$2:$V$1048576)/V51)/SUBTOTAL(109,$V$2:$V$1048576),0) -> 0 | X51: =V51/MAX($V$2:$V$28) -> #DIV/0!
A52: MISC | C52: FLOA.L | D52: =IF(ISERROR(VLOOKUP(C52,[1]Sheet1!$C:$C,1,0)),TODAY(),_xlfn.MINIFS([1]Sheet1!$F:$F,[1]Sheet1!$C:$C,C52)) -> 45833 | E52: =IFERROR(VLOOKUP(C52,'PBI Open Positions'!A:J,4,0),1E-32) -> 1e-32 | F52: =IFERROR(VLOOKUP(C52,'PBI Open Positions'!A:J,5,0),VLOOKUP(C52,'Stock Selection'!C:H,6,0)) -> 6.27 | G52: =E52*F52 -> 6.27e-32 | H52: 0.05 | I52: 0.1833 | J52: =IFERROR(H52/I52,"") -> 0.27277687 | K52: =IFERROR(J52/SUBTOTAL(9,$J$2:$J$1048576),"") -> 0.07092055 | L52: =I52*G52 -> 1.149291e-32 | M52: =F52/(1-(F52*(1+H52)-F52)/(F52*(1+H52))) -> 6.5835 | N52: =M52*E52 -> 6.5835e-32 | O52: =IFERROR(VLOOKUP(C52,'PBI Open Positions'!A:F,6,0),VLOOKUP(Positions!C52,'Stock Selection'!C:H,6,0)) -> 6.27 | P52: =IFERROR(O52*E52,G52) -> 6.27e-32 | Q52: =P52-G52 -> 0 | R52: =F52/(1+I52-H52) -> 5.5325157 | S52: =M52-F52 -> 0.3135 | T52: =0.5*(R52-F52) -> -0.36874217 | U52: =S52+T52 -> -0.055242169 | V52: =SUBTOTAL(4,$U$2:$U$10000)-U52 -> 29.585178 | W52: =IFERROR((SUBTOTAL(109,$V$2:$V$1048576)/V52)/SUBTOTAL(109,$V$2:$V$1048576),0) -> 0 | X52: =V52/MAX($V$2:$V$28) -> 0.17132389
A53: MISC | C53: GILD | D53: =IF(ISERROR(VLOOKUP(C53,[1]Sheet1!$C:$C,1,0)),TODAY(),_xlfn.MINIFS([1]Sheet1!$F:$F,[1]Sheet1!$C:$C,C53)) -> 45833 | E53: =IFERROR(VLOOKUP(C53,'PBI Open Positions'!A:J,4,0),1E-32) -> 1e-32 | F53: =IFERROR(VLOOKUP(C53,'PBI Open Positions'!A:J,5,0),VLOOKUP(C53,'Stock Selection'!C:H,6,0)) -> 107.2 | G53: =E53*F53 -> 1.072e-30 | H53: 0.05 | I53: 0.1833 | J53: =IFERROR(H53/I53,"") -> 0.27277687 | K53: =IFERROR(J53/SUBTOTAL(9,$J$2:$J$1048576),"") -> 0.07092055 | L53: =I53*G53 -> 1.964976e-31 | M53: =F53/(1-(F53*(1+H53)-F53)/(F53*(1+H53))) -> 112.56 | N53: =M53*E53 -> 1.1256e-30 | O53: =IFERROR(VLOOKUP(C53,'PBI Open Positions'!A:F,6,0),VLOOKUP(Positions!C53,'Stock Selection'!C:H,6,0)) -> 107.2 | P53: =IFERROR(O53*E53,G53) -> 1.072e-30 | Q53: =P53-G53 -> 0 | R53: =F53/(1+I53-H53) -> 94.591017 | S53: =M53-F53 -> 5.36 | T53: =0.5*(R53-F53) -> -6.3044913 | U53: =S53+T53 -> -0.94449131 | V53: =SUBTOTAL(4,$U$2:$U$10000)-U53 -> 30.474427 | W53: =IFERROR((SUBTOTAL(109,$V$2:$V$1048576)/V53)/SUBTOTAL(109,$V$2:$V$1048576),0) -> 0 | X53: =V53/MAX($V$2:$V$28) -> 0.17647342
A54: MISC | C54: LEVI | D54: =IF(ISERROR(VLOOKUP(C54,[1]Sheet1!$C:$C,1,0)),TODAY(),_xlfn.MINIFS([1]Sheet1!$F:$F,[1]Sheet1!$C:$C,C54)) -> 45833 | E54: =IFERROR(VLOOKUP(C54,'PBI Open Positions'!A:J,4,0),1E-32) -> 1e-32 | F54: =IFERROR(VLOOKUP(C54,'PBI Open Positions'!A:J,5,0),VLOOKUP(C54,'Stock Selection'!C:H,6,0)) -> 18.62 | G54: =E54*F54 -> 1.862e-31 | H54: 0.05 | I54: 0.1833 | J54: =IFERROR(H54/I54,"") -> 0.27277687 | K54: =IFERROR(J54/SUBTOTAL(9,$J$2:$J$1048576),"") -> 0.07092055 | L54: =I54*G54 -> 3.413046e-32 | M54: =F54/(1-(F54*(1+H54)-F54)/(F54*(1+H54))) -> 19.551 | N54: =M54*E54 -> 1.9551e-31 | O54: =IFERROR(VLOOKUP(C54,'PBI Open Positions'!A:F,6,0),VLOOKUP(Positions!C54,'Stock Selection'!C:H,6,0)) -> 18.62 | P54: =IFERROR(O54*E54,G54) -> 1.862e-31 | Q54: =P54-G54 -> 0 | R54: =F54/(1+I54-H54) -> 16.429895 | S54: =M54-F54 -> 0.931 | T54: =0.5*(R54-F54) -> -1.0950525 | U54: =S54+T54 -> -0.1640525 | V54: =SUBTOTAL(4,$U$2:$U$10000)-U54 -> 29.693988 | W54: =IFERROR((SUBTOTAL(109,$V$2:$V$1048576)/V54)/SUBTOTAL(109,$V$2:$V$1048576),0) -> 0 | X54: =V54/MAX($V$2:$V$28) -> 0.171954
A55: MISC | C55: MC.PA | D55: =IF(ISERROR(VLOOKUP(C55,[1]Sheet1!$C:$C,1,0)),TODAY(),_xlfn.MINIFS([1]Sheet1!$F:$F,[1]Sheet1!$C:$C,C55)) -> 45833 | E55: =IFERROR(VLOOKUP(C55,'PBI Open Positions'!A:J,4,0),1E-32) -> 1e-32 | F55: =IFERROR(VLOOKUP(C55,'PBI Open Positions'!A:J,5,0),VLOOKUP(C55,'Stock Selection'!C:H,6,0)) -> 453.55 | G55: =E55*F55 -> 4.5355e-30 | H55: 0.05 | I55: 0.1833 | J55: =IFERROR(H55/I55,"") -> 0.27277687 | K55: =IFERROR(J55/SUBTOTAL(9,$J$2:$J$1048576),"") -> 0.07092055 | L55: =I55*G55 -> 8.3135715e-31 | M55: =F55/(1-(F55*(1+H55)-F55)/(F55*(1+H55))) -> 476.2275 | N55: =M55*E55 -> 4.762275e-30 | O55: =IFERROR(VLOOKUP(C55,'PBI Open Positions'!A:F,6,0),VLOOKUP(Positions!C55,'Stock Selection'!C:H,6,0)) -> 453.55 | P55: =IFERROR(O55*E55,G55) -> 4.5355e-30 | Q55: =P55-G55 -> 0 | R55: =F55/(1+I55-H55) -> 400.20295 | S55: =M55-F55 -> 22.6775 | T55: =0.5*(R55-F55) -> -26.673526 | U55: =S55+T55 -> -3.9960264 | V55: =SUBTOTAL(4,$U$2:$U$10000)-U55 -> 33.525962 | W55: =IFERROR((SUBTOTAL(109,$V$2:$V$1048576)/V55)/SUBTOTAL(109,$V$2:$V$1048576),0) -> 0 | X55: =V55/MAX($V$2:$V$28) -> 0.19414446
A56: MISC | C56: PANW | D56: =IF(ISERROR(VLOOKUP(C56,[1]Sheet1!$C:$C,1,0)),TODAY(),_xlfn.MINIFS([1]Sheet1!$F:$F,[1]Sheet1!$C:$C,C56)) -> 45833 | E56: =IFERROR(VLOOKUP(C56,'PBI Open Positions'!A:J,4,0),1E-32) -> 1e-32 | F56: =IFERROR(VLOOKUP(C56,'PBI Open Positions'!A:J,5,0),VLOOKUP(C56,'Stock Selection'!C:H,6,0)) -> 0 | G56: =E56*F56 -> 0 | H56: 0.05 | I56: 0.1833 | J56: =IFERROR(H56/I56,"") -> 0.27277687 | K56: =IFERROR(J56/SUBTOTAL(9,$J$2:$J$1048576),"") -> 0.07092055 | L56: =I56*G56 -> 0 | M56: =F56/(1-(F56*(1+H56)-F56)/(F56*(1+H56))) -> #DIV/0! | N56: =M56*E56 -> #DIV/0! | O56: =IFERROR(VLOOKUP(C56,'PBI Open Positions'!A:F,6,0),VLOOKUP(Positions!C56,'Stock Selection'!C:H,6,0)) -> 0 | P56: =IFERROR(O56*E56,G56) -> 0 | Q56: =P56-G56 -> 0 | R56: =F56/(1+I56-H56) -> 0 | S56: =M56-F56 -> #DIV/0! | T56: =0.5*(R56-F56) -> 0 | U56: =S56+T56 -> #DIV/0! | V56: =SUBTOTAL(4,$U$2:$U$10000)-U56 -> #DIV/0! | W56: =IFERROR((SUBTOTAL(109,$V$2:$V$1048576)/V56)/SUBTOTAL(109,$V$2:$V$1048576),0) -> 0 | X56: =V56/MAX($V$2:$V$28) -> #DIV/0!
A57: MISC | C57: SDIA.L | D57: =IF(ISERROR(VLOOKUP(C57,[1]Sheet1!$C:$C,1,0)),TODAY(),_xlfn.MINIFS([1]Sheet1!$F:$F,[1]Sheet1!$C:$C,C57)) -> 45833 | E57: =IFERROR(VLOOKUP(C57,'PBI Open Positions'!A:J,4,0),1E-32) -> 1e-32 | F57: =IFERROR(VLOOKUP(C57,'PBI Open Positions'!A:J,5,0),VLOOKUP(C57,'Stock Selection'!C:H,6,0)) -> 6.13 | G57: =E57*F57 -> 6.13e-32 | H57: 0.05 | I57: 0.1833 | J57: =IFERROR(H57/I57,"") -> 0.27277687 | K57: =IFERROR(J57/SUBTOTAL(9,$J$2:$J$1048576),"") -> 0.07092055 | L57: =I57*G57 -> 1.123629e-32 | M57: =F57/(1-(F57*(1+H57)-F57)/(F57*(1+H57))) -> 6.4365 | N57: =M57*E57 -> 6.4365e-32 | O57: =IFERROR(VLOOKUP(C57,'PBI Open Positions'!A:F,6,0),VLOOKUP(Positions!C57,'Stock Selection'!C:H,6,0)) -> 6.13 | P57: =IFERROR(O57*E57,G57) -> 6.13e-32 | Q57: =P57-G57 -> 0 | R57: =F57/(1+I57-H57) -> 5.4089826 | S57: =M57-F57 -> 0.3065 | T57: =0.5*(R57-F57) -> -0.36050869 | U57: =S57+T57 -> -0.054008691 | V57: =SUBTOTAL(4,$U$2:$U$10000)-U57 -> 29.583944 | W57: =IFERROR((SUBTOTAL(109,$V$2:$V$1048576)/V57)/SUBTOTAL(109,$V$2:$V$1048576),0) -> 0 | X57: =V57/MAX($V$2:$V$28) -> 0.17131675
A58: MISC | C58: SHELL.AS | D58: =IF(ISERROR(VLOOKUP(C58,[1]Sheet1!$C:$C,1,0)),TODAY(),_xlfn.MINIFS([1]Sheet1!$F:$F,[1]Sheet1!$C:$C,C58)) -> 45833 | E58: =IFERROR(VLOOKUP(C58,'PBI Open Positions'!A:J,4,0),1E-32) -> 1e-32 | F58: =IFERROR(VLOOKUP(C58,'PBI Open Positions'!A:J,5,0),VLOOKUP(C58,'Stock Selection'!C:H,6,0)) -> 30.42 | G58: =E58*F58 -> 3.042e-31 | H58: 0.05 | I58: 0.1833 | J58: =IFERROR(H58/I58,"") -> 0.27277687 | K58: =IFERROR(J58/SUBTOTAL(9,$J$2:$J$1048576),"") -> 0.07092055 | L58: =I58*G58 -> 5.575986e-32 | M58: =F58/(1-(F58*(1+H58)-F58)/(F58*(1+H58))) -> 31.941 | N58: =M58*E58 -> 3.1941e-31 | O58: =IFERROR(VLOOKUP(C58,'PBI Open Positions'!A:F,6,0),VLOOKUP(Positions!C58,'Stock Selection'!C:H,6,0)) -> 30.42 | P58: =IFERROR(O58*E58,G58) -> 3.042e-31 | Q58: =P58-G58 -> 0 | R58: =F58/(1+I58-H58) -> 26.841966 | S58: =M58-F58 -> 1.521 | T58: =0.5*(R58-F58) -> -1.789017 | U58: =S58+T58 -> -0.26801703 | V58: =SUBTOTAL(4,$U$2:$U$10000)-U58 -> 29.797953 | W58: =IFERROR((SUBTOTAL(109,$V$2:$V$1048576)/V58)/SUBTOTAL(109,$V$2:$V$1048576),0) -> 0 | X58: =V58/MAX($V$2:$V$28) -> 0.17255604
A59: MISC | C59: SMFG | D59: =IF(ISERROR(VLOOKUP(C59,[1]Sheet1!$C:$C,1,0)),TODAY(),_xlfn.MINIFS([1]Sheet1!$F:$F,[1]Sheet1!$C:$C,C59)) -> 45833 | E59: =IFERROR(VLOOKUP(C59,'PBI Open Positions'!A:J,4,0),1E-32) -> 1e-32 | F59: =IFERROR(VLOOKUP(C59,'PBI Open Positions'!A:J,5,0),VLOOKUP(C59,'Stock Selection'!C:H,6,0)) -> 15.17 | G59: =E59*F59 -> 1.517e-31 | H59: 0.05 | I59: 0.1833 | J59: =IFERROR(H59/I59,"") -> 0.27277687 | K59: =IFERROR(J59/SUBTOTAL(9,$J$2:$J$1048576),"") -> 0.07092055 | L59: =I59*G59 -> 2.780661e-32 | M59: =F59/(1-(F59*(1+H59)-F59)/(F59*(1+H59))) -> 15.9285 | N59: =M59*E59 -> 1.59285e-31 | O59: =IFERROR(VLOOKUP(C59,'PBI Open Positions'!A:F,6,0),VLOOKUP(Positions!C59,'Stock Selection'!C:H,6,0)) -> 15.17 | P59: =IFERROR(O59*E59,G59) -> 1.517e-31 | Q59: =P59-G59 -> 0 | R59: =F59/(1+I59-H59) -> 13.385688 | S59: =M59-F59 -> 0.7585 | T59: =0.5*(R59-F59) -> -0.89215609 | U59: =S59+T59 -> -0.13365609 | V59: =SUBTOTAL(4,$U$2:$U$10000)-U59 -> 29.663592 | W59: =IFERROR((SUBTOTAL(109,$V$2:$V$1048576)/V59)/SUBTOTAL(109,$V$2:$V$1048576),0) -> 0 | X59: =V59/MAX($V$2:$V$28) -> 0.17177798
A60: MISC | C60: SQM | D60: =IF(ISERROR(VLOOKUP(C60,[1]Sheet1!$C:$C,1,0)),TODAY(),_xlfn.MINIFS([1]Sheet1!$F:$F,[1]Sheet1!$C:$C,C60)) -> 45833 | E60: =IFERROR(VLOOKUP(C60,'PBI Open Positions'!A:J,4,0),1E-32) -> 1e-32 | F60: =IFERROR(VLOOKUP(C60,'PBI Open Positions'!A:J,5,0),VLOOKUP(C60,'Stock Selection'!C:H,6,0)) -> 33.95 | G60: =E60*F60 -> 3.395e-31 | H60: 0.05 | I60: 0.1833 | J60: =IFERROR(H60/I60,"") -> 0.27277687 | K60: =IFERROR(J60/SUBTOTAL(9,$J$2:$J$1048576),"") -> 0.07092055 | L60: =I60*G60 -> 6.223035e-32 | M60: =F60/(1-(F60*(1+H60)-F60)/(F60*(1+H60))) -> 35.6475 | N60: =M60*E60 -> 3.56475e-31 | O60: =IFERROR(VLOOKUP(C60,'PBI Open Positions'!A:F,6,0),VLOOKUP(Positions!C60,'Stock Selection'!C:H,6,0)) -> 33.95 | P60: =IFERROR(O60*E60,G60) -> 3.395e-31 | Q60: =P60-G60 -> 0 | R60: =F60/(1+I60-H60) -> 29.956763 | S60: =M60-F60 -> 1.6975 | T60: =0.5*(R60-F60) -> -1.9966183 | U60: =S60+T60 -> -0.29911828 | V60: =SUBTOTAL(4,$U$2:$U$10000)-U60 -> 29.829054 | W60: =IFERROR((SUBTOTAL(109,$V$2:$V$1048576)/V60)/SUBTOTAL(109,$V$2:$V$1048576),0) -> 0 | X60: =V60/MAX($V$2:$V$28) -> 0.17273615
A61: MISC | C61: VHYD.L | D61: =IF(ISERROR(VLOOKUP(C61,[1]Sheet1!$C:$C,1,0)),TODAY(),_xlfn.MINIFS([1]Sheet1!$F:$F,[1]Sheet1!$C:$C,C61)) -> 45833 | E61: =IFERROR(VLOOKUP(C61,'PBI Open Positions'!A:J,4,0),1E-32) -> 1e-32 | F61: =IFERROR(VLOOKUP(C61,'PBI Open Positions'!A:J,5,0),VLOOKUP(C61,'Stock Selection'!C:H,6,0)) -> 73.26 | G61: =E61*F61 -> 7.326e-31 | H61: 0.05 | I61: 0.1833 | J61: =IFERROR(H61/I61,"") -> 0.27277687 | K61: =IFERROR(J61/SUBTOTAL(9,$J$2:$J$1048576),"") -> 0.07092055 | L61: =I61*G61 -> 1.3428558e-31 | M61: =F61/(1-(F61*(1+H61)-F61)/(F61*(1+H61))) -> 76.923 | N61: =M61*E61 -> 7.6923e-31 | O61: =IFERROR(VLOOKUP(C61,'PBI Open Positions'!A:F,6,0),VLOOKUP(Positions!C61,'Stock Selection'!C:H,6,0)) -> 73.26 | P61: =IFERROR(O61*E61,G61) -> 7.326e-31 | Q61: =P61-G61 -> 0 | R61: =F61/(1+I61-H61) -> 64.643078 | S61: =M61-F61 -> 3.663 | T61: =0.5*(R61-F61) -> -4.3084611 | U61: =S61+T61 -> -0.64546113 | V61: =SUBTOTAL(4,$U$2:$U$10000)-U61 -> 30.175397 | W61: =IFERROR((SUBTOTAL(109,$V$2:$V$1048576)/V61)/SUBTOTAL(109,$V$2:$V$1048576),0) -> 0 | X61: =V61/MAX($V$2:$V$28) -> 0.17474177
... A63: Financial Services | C63: C | D63: =IF(ISERROR(VLOOKUP(C63,[1]Sheet1!$C:$C,1,0)),TODAY(),_xlfn.MINIFS([1]Sheet1!$F:$F,[1]Sheet1!$C:$C,C63)) -> 45818.909 | E63: =IFERROR(VLOOKUP(C63,'PBI Open Positions'!A:J,4,0),1E-32) -> 0.1284 | F63: =IFERROR(VLOOKUP(C63,'PBI Open Positions'!A:J,5,0),VLOOKUP(C63,'Stock Selection'!C:H,6,0)) -> 77.96 | G63: =E63*F63 -> 10.010064 | H63: 0.05 | I63: 0.1833 | J63: =IFERROR(H63/I63,"") -> 0.27277687 | K63: =IFERROR(J63/SUBTOTAL(9,$J$2:$J$1048576),"") -> 0.07092055 | L63: =I63*G63 -> 1.8348447 | M63: =F63/(1-(F63*(1+H63)-F63)/(F63*(1+H63))) -> 81.858 | N63: =M63*E63 -> 10.510567 | O63: =IFERROR(VLOOKUP(C63,'PBI Open Positions'!A:F,6,0),VLOOKUP(Positions!C63,'Stock Selection'!C:H,6,0)) -> 81.15 | P63: =IFERROR(O63*E63,G63) -> 10.41966 | Q63: =P63-G63 -> 0.409596 | R63: =F63/(1+I63-H63) -> 68.790259 | S63: =M63-F63 -> 3.898 | T63: =0.5*(R63-F63) -> -4.5848707 | U63: =S63+T63 -> -0.68687073 | V63: =SUBTOTAL(4,$U$2:$U$10000)-U63 -> 30.216806 | W63: =IFERROR((SUBTOTAL(109,$V$2:$V$1048576)/V63)/SUBTOTAL(109,$V$2:$V$1048576),0) -> 0 | X63: =V63/MAX($V$2:$V$28) -> 0.17498157

Sheet PBI Open Positions
A1: Ticker | B1: Entry Value | C1: Entry % | D1: Volume | E1: Open Price | F1: Market Price | G1: Market Value | H1: Unrealized Gains | I1: Gains % | J1: Volatility
A2: VWO | B2: 182.42 | C2: 0.1 | D2: 4 | E2: 45.61 | F2: 49.01 | G2: 196.04 | H2: 13.62 | I2: 0.0747 | J2: 0.19
A3: BND | B3: 147 | C3: 0.08 | D3: 2 | E3: 73.5 | F3: 73.28 | G3: 146.56 | H3: -0.44 | I3: -0.003 | J3: 0.05
A4: APA | B4: 129.96 | C4: 0.07 | D4: 6.8599 | E4: 18.94 | F4: 18.17 | G4: 124.64 | H4: -5.32 | I4: -0.0409 | J4: 0.52
A5: MO | B5: 129.74 | C5: 0.07 | D5: 2.3939 | E5: 54.2 | F5: 59.93 | G5: 143.46 | H5: 13.72 | I5: 0.1057 | J5: 0.19
A6: ACI | B6: 126.28 | C6: 0.07 | D6: 6 | E6: 21.05 | F6: 21.68 | G6: 130.08 | H6: 3.8 | I6: 0.0301 | J6: 0.25
A7: PEP | B7: 119 | C7: 0.07 | D7: 0.8085 | E7: 147.19 | F7: 131.08 | G7: 105.98 | H7: -13.02 | I7: -0.1094 | J7: 0.2
A8: BBVA.MC | B8: 89.99 | C8: 0.05 | D8: 6.0332 | E8: 14.92 | F8: 15.14 | G8: 91.33 | H8: 1.34 | I8: 0.0149 | J8: 0.3
A9: YPF | B9: 89.97 | C9: 0.05 | D9: 2.4948 | E9: 36.06 | F9: 34.37 | G9: 85.74 | H9: -4.23 | I9: -0.047 | J9: 0.48
A10: TSM | B10: 89.04 | C10: 0.05 | D10: 0.5547 | E10: 160.52 | F10: 220.05 | G10: 122.06 | H10: 33.02 | I10: 0.3708 | J10: 0.46
A11: ING | B11: 85.63 | C11: 0.05 | D11: 4.8753 | E11: 17.56 | F11: 21.35 | G11: 104.08 | H11: 18.45 | I11: 0.2155 | J11: 0.27
A12: BCS | B12: 80 | C12: 0.04 | D12: 4.8087 | E12: 16.64 | F12: 18.25 | G12: 87.76 | H12: 7.76 | I12: 0.097 | J12: 0.36
A13: NEE | B13: 69.98 | C13: 0.04 | D13: 0.9669 | E13: 72.38 | F13: 71.42 | G13: 69.06 | H13: -0.92 | I13: -0.0131 | J13: 0.29
... A27: DAR | B27: 3.67 | C27: 0 | D27: 0.1091 | E27: 33.64 | F27: 38.5 | G27: 4.2 | H27: 0.53 | I27: 0.1444 | J27: 0.45
A28: AGIO | B28: 0.55 | C28: 0 | D28: 0.0179 | E28: 30.73 | F28: 33.52 | G28: 0.6 | H28: 0.05 | I28: 0.0909 | J28: (Blank)
A29: MSFT | B29: 0.41 | C29: 0 | D29: 0.001 | E29: 410 | F29: 490 | G29: 0.49 | H29: 0.08 | I29: 0.1951 | J29: 0.26
A30: AAPL | B30: 0.02 | C30: 0 | D30: 0.0001 | E30: 200 | F30: 200 | G30: 0.02 | H30: 0 | I30: 0 | J30: 0.32

Sheet Stock Selection
A1: Sector | B1: GICS Sector | C1: Ticker | D1: Portfolio % | E1: Net Income % | F1: EBITDA Margin % | G1: Dividend | H1: Close Price | I1: EPS | J1: Forward EPS | K1: EPG Growth % | L1: PEG | M1: P/E | N1: Forward P/E | O1: Volatility | P1: MISSING
A2: Financial Services | B2: Financial Services | C2: V | D2: 0.0115 | E2: 52.210203 | F2: 69.708 | G2: 0.0069 | H2: 351.63 | I2: 9.93 | J2: 12.66 | K2: 0.2749 | L2: 1.0102731 | M2: 35.410877 | N2: 27.774881 | O2: 0.2326 | P2: =NOT(VLOOKUP(C2,Positions!C:C,1,0)=C2) -> FALSE
A3: Technology | B3: Technology | C3: NVDA | E3: 51.694442 | F3: 59.419996 | G3: 0.0003 | H3: 147.9 | I3: 3.1 | J3: 4.12 | K3: 0.329 | L3: 1.0910193 | M3: 47.70968 | N3: 35.898056 | O3: 0.5757 | P3: =NOT(VLOOKUP(C3,Positions!C:C,1,0)=C3) -> FALSE
A4: Consumer Def & Cyclical | B4: Consumer Defensive | C4: MO | D4: 0.0752 | E4: 50.301293 | F4: 61.162996 | G4: 0.0674 | H4: 59.91 | I4: 5.96 | J4: 5.35 | K4: -0.1023 | L4: -1.0941125 | M4: 10.052013 | N4: 11.198131 | O4: 0.1949 | P4: =NOT(VLOOKUP(C4,Positions!C:C,1,0)=C4) -> FALSE
A5: Financial Services | B5: Financial Services | C5: MA | D5: 0.0228 | E5: 45.213113 | F5: 61.846 | G5: 0.0056 | H5: 557.53 | I5: 14.26 | J5: 16.38 | K5: 0.1487 | L5: 2.2894863 | M5: 39.097477 | N5: 34.037243 | O5: 0.2277 | P5: =NOT(VLOOKUP(C5,Positions!C:C,1,0)=C5) -> FALSE
A6: Technology | B6: Technology | C6: TSM | D6: 0.064 | E6: 41.68677 | F6: 68.481004 | G6: 0.0156 | H6: 220.09 | I6: 8.43 | J6: 8.08 | K6: -0.0415 | L6: -6.5606742 | M6: 26.107946 | N6: 27.238861 | O6: 0.4588 | P6: =NOT(VLOOKUP(C6,Positions!C:C,1,0)=C6) -> FALSE
A7: Technology | B7: Technology | C7: MSFT | D7: 0.0003 | E7: 35.789415 | F7: 55.247 | G7: 0.0068 | H7: 490.11 | I7: 12.93 | J7: 14.95 | K7: 0.1562 | L7: 2.0984543 | M7: 37.90487 | N7: 32.783276 | O7: 0.2559 | P7: =NOT(VLOOKUP(C7,Positions!C:C,1,0)=C7) -> FALSE
A8: Financial Services | B8: Financial Services | C8: BBVA.MC | D8: 0.0479 | E8: 31.698101 | F8: 0 | G8: 0.0547 | H8: 13.11 | I8: 1.77 | J8: 0.94 | K8: -0.4689 | L8: -0.29753331 | M8: 7.4096045 | N8: 13.952127 | O8: 0.3012 | P8: =NOT(VLOOKUP(C8,Positions!C:C,1,0)=C8) -> FALSE
A9: Technology | B9: Communication Services | C9: GOOGL | D9: 0.0025 | E9: 30.85682 | F9: 37.726003 | G9: 0.0051 | H9: 166.77 | I9: 8.95 | J9: 8.96 | K9: 0.0011 | L9: 166.58388 | M9: 18.63352 | N9: 18.612724 | O9: 0.3187 | P9: =NOT(VLOOKUP(C9,Positions!C:C,1,0)=C9) -> FALSE
A10: Financial Services | B10: Financial Services | C10: BAP | D10: 0.0105 | E10: 30.761927 | F10: 0 | G10: 0.0509 | H10: 217.79 | I10: 19.8 | J10: 20.68 | K10: 0.0444 | L10: 2.369572 | M10: 10.999496 | N10: 10.531431 | O10: 0.2499 | P10: =NOT(VLOOKUP(C10,Positions!C:C,1,0)=C10) -> FALSE
A11: Energy & Utilities | B11: Technology | C11: FSLR | D11: 0.0392 | E11: 29.716644 | F11: 43.032002 | G11: 0 | H11: 151.18 | I11: 11.78 | J11: 20.86 | K11: 0.7708 | L11: 0.094024154 | M11: 12.833616 | N11: 7.2473626 | O11: 0.6306 | P11: =NOT(VLOOKUP(C11,Positions!C:C,1,0)=C11) -> FALSE
A12: Technology | B12: Technology | C12: ASML | E12: 28.334591 | F12: 36.578 | G12: 0.0107 | H12: 813.36 | I12: 25.5 | J12: 26.7 | K12: 0.0471 | L12: 6.4733705 | M12: 31.89647 | N12: 30.46292 | O12: 0.4773 | P12: =NOT(VLOOKUP(C12,Positions!C:C,1,0)=C12) -> FALSE
A13: Financial Services | B13: Financial Services | C13: CIB | D13: 0.0363 | E13: 28.104146 | F13: 0 | G13: 0.3578 | H13: 44.97 | I13: 6.45 | J13: 5.9 | K13: -0.0853 | L13: -0.89385671 | M13: 6.9720936 | N13: 7.622034 | O13: 0.3186 | P13: =NOT(VLOOKUP(C13,Positions!C:C,1,0)=C13) -> FALSE
A14: Technology | B14: Technology | C14: QCOM | E14: 26.048812 | F14: 31.573 | G14: 0.0232 | H14: 155.71 | I14: 9.8 | J14: 12.23 | K14: 0.248 | L14: 0.51346386 | M14: 15.888776 | N14: 12.731808 | O14: 0.4285 | P14: =NOT(VLOOKUP(C14,Positions!C:C,1,0)=C14) -> FALSE
A15: Financial Services | B15: Financial Services | C15: ING | D15: 0.0545 | E15: 25.98484 | F15: 0 | G15: 0.0554 | H15: 21.36 | I15: 2.27 | J15: 2.19 | K15: -0.0352 | L15: -2.7675343 | M15: 9.409692 | N15: 9.753425 | O15: 0.2737 | P15: =NOT(VLOOKUP(C15,Positions!C:C,1,0)=C15) -> FALSE
A16: Technology | B16: Technology | C16: AAPL | D16: 0 | E16: 24.301264 | F16: 34.685 | G16: 0.0052 | H16: 200.3 | I16: 6.43 | J16: 8.31 | K16: 0.2924 | L16: 0.82439061 | M16: 31.150856 | N16: 24.103489 | O16: 0.3232 | P16: =NOT(VLOOKUP(C16,Positions!C:C,1,0)=C16) -> FALSE
A17: Technology | B17: Technology | C17: AMAT | E17: 24.059241 | F17: 31.133 | G17: 0.0107 | H17: 180.18 | I17: 8.22 | J17: 9.69 | K17: 0.1788 | L17: 1.03977 | M17: 21.919706 | N17: 18.594427 | O17: 0.4882 | P17: =NOT(VLOOKUP(C17,Positions!C:C,1,0)=C17) -> FALSE
A18: Financial Services | B18: Financial Services | C18: BCS | D18: 0.046 | E18: 22.632257 | F18: 0 | G18: 0.024 | H18: 18.26 | I18: 2.02 | J18: 1.05 | K18: -0.4802 | L18: -0.36215222 | M18: 9.039604 | N18: 17.390478 | O18: 0.3595 | P18: =NOT(VLOOKUP(C18,Positions!C:C,1,0)=C18) -> FALSE
A19: Financial Services | B19: Financial Services | C19: SMFG | E19: 22.567763 | F19: 0 | G19: 0.0277 | H19: 15.17 | I19: 1.24 | J19: 0.41 | K19: -0.6694 | L19: -0.55277108 | M19: 12.233871 | N19: 37 | O19: 0.364 | P19: =NOT(VLOOKUP(C19,Positions!C:C,1,0)=C19) -> FALSE
A20: Energy & Utilities | B20: Utilities | C20: NEE | D20: 0.0362 | E20: 21.809332 | F20: 53.73 | G20: 0.032 | H20: 71.4 | I20: 2.67 | J20: 3.68 | K20: 0.3783 | L20: 0.51290896 | M20: 26.741573 | N20: 19.402174 | O20: 0.2894 | P20: =NOT(VLOOKUP(C20,Positions!C:C,1,0)=C20) -> FALSE
A21: Healthcare | B21: Healthcare | C21: GILD | E21: 20.758657 | F21: 47.761002 | G21: 0.0298 | H21: 107.2 | I21: 4.76 | J21: 7.43 | K21: 0.5609 | L21: 0.25721819 | M21: 22.521008 | N21: 14.427995 | O21: 0.2606 | P21: =NOT(VLOOKUP(C21,Positions!C:C,1,0)=C21) -> FALSE
A22: Consumer Def & Cyclical | B22: Consumer Cyclical | C22: YUM | D22: 0.0185 | E22: 18.415611 | F22: 35.5 | G22: 0.0201 | H22: 142.7 | I22: 5.02 | J22: 6.08 | K22: 0.2112 | L22: 1.1115224 | M22: 28.426294 | N22: 23.470394 | O22: 0.2203 | P22: =NOT(VLOOKUP(C22,Positions!C:C,1,0)=C22) -> FALSE
A23: Technology | B23: Technology | C23: PLTR | E23: 18.320598 | F23: 13.976 | G23: 0 | H23: 143.23 | I23: 0.22 | J23: 0.47 | K23: 1.1364 | L23: 2.681753 | M23: 651.0454 | N23: 304.74466 | O23: 0.728 | P23: =NOT(VLOOKUP(C23,Positions!C:C,1,0)=C23) -> FALSE
A24: Industrials | B24: Industrials | C24: MMM | E24: 18.031248 | F24: 21.735 | G24: 0.0198 | H24: 149.87 | I24: 8.03 | J24: 7.9 | K24: -0.0162 | L24: -11.718169 | M24: 18.663761 | N24: 18.970884 | O24: 0.3632 | P24: =NOT(VLOOKUP(C24,Positions!C:C,1,0)=C24) -> FALSE
A25: Financial Services | B25: Financial Services | C25: C | D25: 0.0055 | E25: 16.937021 | F25: 0 | G25: 0.0282 | H25: 81.14 | I25: 6.33 | J25: 7.19 | K25: 0.1359 | L25: 0.83063717 | M25: 12.818325 | N25: 11.285118 | O25: 0.3434 | P25: =NOT(VLOOKUP(C25,Positions!C:C,1,0)=C25) -> FALSE
A26: Energy & Utilities | B26: Utilities | C26: DUK | E26: 15.22024 | F26: 48.826998 | G26: 0.0357 | H26: 116.95 | I26: 6.02 | J26: 6.34 | K26: 0.0532 | L26: 3.4702235 | M26: 19.42691 | N26: 18.446371 | O26: 0.1822 | P26: =NOT(VLOOKUP(C26,Positions!C:C,1,0)=C26) -> FALSE
A27: Consumer Def & Cyclical | B27: Consumer Cyclical | C27: MC.PA | E27: 14.819976 | F27: 26.488 | G27: 0.0289 | H27: 453.55 | I27: 25.1 | J27: 29.09 | K27: 0.159 | L27: 0.98080408 | M27: 18.069721 | N27: 15.591268 | O27: 0.3176 | P27: =NOT(VLOOKUP(C27,Positions!C:C,1,0)=C27) -> FALSE
A28: Energy & Utilities | B28: Utilities | C28: AEP | E28: 13.711989 | F28: 39.543 | G28: 0.036 | H28: 103.28 | I28: 5.18 | J28: 5.89 | K28: 0.1371 | L28: 1.2792999 | M28: 19.938225 | N28: 17.534805 | O28: 0.1947 | P28: =NOT(VLOOKUP(C28,Positions!C:C,1,0)=C28) -> FALSE
A29: Basic Materials | B29: Basic Materials | C29: SQM | E29: 13.449988 | F29: 29.632 | G29: 0.0613 | H29: 33.95 | I29: 2.11 | J29: 3.98 | K29: 0.8863 | L29: 0.096249297 | M29: 16.090048 | N29: 8.530151 | O29: 0.438 | P29: =NOT(VLOOKUP(C29,Positions!C:C,1,0)=C29) -> FALSE
A30: Consumer Def & Cyclical | B30: Consumer Defensive | C30: KMB | D30: 0.0325 | E30: 12.481645 | F30: 19.545001 | G30: 0.0387 | H30: 129.95 | I30: 7.34 | J30: 7.63 | K30: 0.0395 | L30: 4.3107197 | M30: 17.70436 | N30: 17.031454 | O30: 0.1946 | P30: =NOT(VLOOKUP(C30,Positions!C:C,1,0)=C30) -> FALSE
A31: Energy & Utilities | B31: Utilities | C31: EXC | D31: 0.0157 | E31: 11.435083 | F31: 32.266998 | G31: 0.037 | H31: 43.1 | I31: 2.69 | J31: 2.63 | K31: -0.0223 | L31: -7.3472104 | M31: 16.022305 | N31: 16.38783 | O31: 0.1918 | P31: =NOT(VLOOKUP(C31,Positions!C:C,1,0)=C31) -> FALSE
A32: Consumer Def & Cyclical | B32: Consumer Defensive | C32: PEP | D32: 0.0555 | E32: 10.237864 | F32: 18.906 | G32: 0.0441 | H32: 131.05 | I32: 6.8 | J32: 8.63 | K32: 0.2691 | L32: 0.56426623 | M32: 19.272058 | N32: 15.1854 | O32: 0.1956 | P32: =NOT(VLOOKUP(C32,Positions!C:C,1,0)=C32) -> FALSE
A33: Energy & Utilities | B33: Energy | C33: APA | D33: 0.0653 | E33: 10.041388 | F33: 58.8 | G33: 0.0544 | H33: 18.18 | I33: 2.79 | J33: 2.75 | K33: -0.0143 | L33: -4.611109 | M33: 6.516129 | N33: 6.610909 | O33: 0.5247 | P33: =NOT(VLOOKUP(C33,Positions!C:C,1,0)=C33) -> FALSE
A34: Energy & Utilities | B34: Utilities | C34: PCG | E34: 9.5758126 | F34: 38.176998 | G34: 0.0072 | H34: 14.16 | I34: 1.09 | J34: 1.48 | K34: 0.3578 | L34: 0.26740123 | M34: 12.990825 | N34: 9.567567 | O34: 0.2806 | P34: =NOT(VLOOKUP(C34,Positions!C:C,1,0)=C34) -> FALSE
A35: Consumer Def & Cyclical | B35: Consumer Defensive | C35: INGR | D35: 0.0251 | E35: 8.5314496 | F35: 17.511 | G35: 0.023 | H35: 137.5 | I35: 9.48 | J35: 11.11 | K35: 0.1719 | L35: 0.71979593 | M35: 14.50422 | N35: 12.376238 | O35: 0.2578 | P35: =NOT(VLOOKUP(C35,Positions!C:C,1,0)=C35) -> FALSE
A36: Consumer Def & Cyclical | B36: Consumer Cyclical | C36: YUMC | E36: 8.087586 | F36: 15.001 | G36: 0.0218 | H36: 44.4 | I36: 2.39 | J36: 2.58 | K36: 0.0795 | L36: 2.1647492 | M36: 18.577406 | N36: 17.209303 | O36: 0.4189 | P36: =NOT(VLOOKUP(C36,Positions!C:C,1,0)=C36) -> FALSE
A37: Healthcare | B37: Healthcare | C37: HCA | E37: 8.0729203 | F37: 19.863 | G37: 0.0076 | H37: 379.02 | I37: 22.53 | J37: 24.55 | K37: 0.0897 | L37: 1.7219497 | M37: 16.822903 | N37: 15.438697 | O37: 0.2853 | P37: =NOT(VLOOKUP(C37,Positions!C:C,1,0)=C37) -> FALSE
A38: Energy & Utilities | B38: Energy | C38: YPF | D38: 0.0449 | E38: 7.9344361 | F38: 22.017 | G38: 0 | H38: 34.35 | I38: 4.29 | J38: 4.7 | K38: 0.0956 | L38: 0.76471981 | M38: 8.006992 | N38: 7.308511 | O38: 0.4789 | P38: =NOT(VLOOKUP(C38,Positions!C:C,1,0)=C38) -> FALSE
A39: Consumer Def & Cyclical | B39: Consumer Cyclical | C39: APTV | E39: 7.9340021 | F39: 15.812 | G39: 0 | H39: 68.45 | I39: 6.12 | J39: 6.98 | K39: 0.1405 | L39: 0.69786431 | M39: 11.18464 | N39: 9.80659 | O39: 0.4027 | P39: =NOT(VLOOKUP(C39,Positions!C:C,1,0)=C39) -> FALSE
A40: Consumer Def & Cyclical | B40: Consumer Cyclical | C40: LEVI | E40: 5.6327028 | F40: 14.336 | G40: 0.0289 | H40: 18.62 | I40: 0.9 | J40: 1.4 | K40: 0.5556 | L40: 0.23940002 | M40: 20.68889 | N40: 13.300001 | O40: 0.4396 | P40: =NOT(VLOOKUP(C40,Positions!C:C,1,0)=C40) -> FALSE
A41: Energy & Utilities | B41: Energy | C41: SHELL.AS | E41: 4.8087838 | F41: 18.240999 | G41: 0.0395 | H41: 30.42 | I41: 1.9 | J41: 3.82 | K41: 1.0105 | L41: 0.078803994 | M41: 16.010527 | N41: 7.963351 | O41: 0.2187 | P41: =NOT(VLOOKUP(C41,Positions!C:C,1,0)=C41) -> FALSE
A42: Consumer Def & Cyclical | B42: Consumer Defensive | C42: DAR | D42: 0.0022 | E42: 3.0228864 | F42: 14.259 | G42: 0 | H42: 38.62 | I42: 1.07 | J42: 2.99 | K42: 1.7944 | L42: 0.071981954 | M42: 36.093456 | N42: 12.916388 | O42: 0.4474 | P42: =NOT(VLOOKUP(C42,Positions!C:C,1,0)=C42) -> FALSE
A43: Consumer Def & Cyclical | B43: Consumer Defensive | C43: WMT | E43: 2.7469544 | F43: 6.241 | G43: 0.0096 | H43: 98 | I43: 2.34 | J43: 2.72 | K43: 0.1624 | L43: 2.2186531 | M43: 41.880344 | N43: 36.02941 | O43: 0.2407 | P43: =NOT(VLOOKUP(C43,Positions!C:C,1,0)=C43) -> FALSE
A44: Consumer Def & Cyclical | B44: Consumer Defensive | C44: ACI | D44: 0.0682 | E44: 1.1924236 | F44: 4.6609998 | G44: 0.0271 | H44: 21.69 | I44: 1.64 | J44: 2.27 | K44: 0.3841 | L44: 0.24873505 | M44: 13.22561 | N44: 9.555066 | O44: 0.2536 | P44: =NOT(VLOOKUP(C44,Positions!C:C,1,0)=C44) -> FALSE
A45: CFDs | B45: Unknown | C45: GC=F | G45: 0 | H45: 3340.3 | I45: 0 | J45: 0 | M45: 0 | N45: 0 | O45: 0.1828 | P45: =NOT(VLOOKUP(C45,Positions!C:C,1,0)=C45) -> FALSE
A46: CFDs | B46: Unknown | C46: JPY=X | G46: 0 | H46: 144.93 | I46: 0 | J46: 0 | M46: 0 | N46: 0 | O46: 0.1143 | P46: =NOT(VLOOKUP(C46,Positions!C:C,1,0)=C46) -> FALSE
A47: CFDs | B47: Unknown | C47: MXN=X | G47: 0 | H47: 18.98 | I47: 0 | J47: 0 | M47: 0 | N47: 0 | O47: 0.1361 | P47: =NOT(VLOOKUP(C47,Positions!C:C,1,0)=C47) -> FALSE
A48: CFDs | B48: Unknown | C48: US30 | G48: 0 | H48: 0 | I48: 0 | J48: 0 | M48: 0 | N48: 0 | P48: =NOT(VLOOKUP(C48,Positions!C:C,1,0)=C48) -> #N/A
A49: Energy & Utilities | B49: Unknown | C49: SWI.US | G49: 0 | H49: 0 | I49: 0 | J49: 0 | M49: 0 | N49: 0 | P49: =NOT(VLOOKUP(C49,Positions!C:C,1,0)=C49) -> FALSE
A50: ETF | B50: Unknown | C50: BATT.AS | D50: 0.0184 | G50: 0 | H50: 15.21 | I50: 0 | J50: 0 | M50: 0 | N50: 0 | O50: 0.255 | P50: =NOT(VLOOKUP(C50,Positions!C:C,1,0)=C50) -> FALSE
A51: ETF | B51: Unknown | C51: BND | D51: 0.0768 | G51: 0.0375 | H51: 73.28 | I51: 0 | J51: 0 | M51: 0 | N51: 0 | O51: 0.0526 | P51: =NOT(VLOOKUP(C51,Positions!C:C,1,0)=C51) -> FALSE
A52: ETF | B52: Unknown | C52: BOTZ.L | D52: 0.0216 | G52: 0 | H52: 20.55 | I52: 0 | J52: 0 | M52: 31.338074 | N52: 0 | O52: 0.2604 | P52: =NOT(VLOOKUP(C52,Positions!C:C,1,0)=C52) -> FALSE
A53: ETF | B53: Unknown | C53: FLOA.L | G53: 0 | H53: 6.27 | I53: 0 | J53: 0 | M53: 0 | N53: 0 | O53: 0.0272 | P53: =NOT(VLOOKUP(C53,Positions!C:C,1,0)=C53) -> FALSE
A54: ETF | B54: Unknown | C54: SDIA.L | G54: 0 | H54: 6.13 | I54: 0 | J54: 0 | M54: 0 | N54: 0 | O54: 0.0267 | P54: =NOT(VLOOKUP(C54,Positions!C:C,1,0)=C54) -> FALSE
A55: ETF | B55: Unknown | C55: VBTC.DE | G55: 0 | H55: 48.34 | I55: 0 | J55: 0 | M55: 0 | N55: 0 | O55: 0.4842 | P55: =NOT(VLOOKUP(C55,Positions!C:C,1,0)=C55) -> FALSE
A56: ETF | B56: Unknown | C56: VHYD.L | G56: 0.031 | H56: 73.26 | I56: 0 | J56: 0 | M56: 15.080513 | N56: 0 | O56: 0.139 | P56: =NOT(VLOOKUP(C56,Positions!C:C,1,0)=C56) -> FALSE
A57: ETF | B57: Unknown | C57: VWO | D57: 0.1027 | G57: 0.0302 | H57: 48.99 | I57: 0 | J57: 0 | M57: 15.763891 | N57: 0 | O57: 0.1875 | P57: =NOT(VLOOKUP(C57,Positions!C:C,1,0)=C57) -> FALSE
A58: Healthcare | B58: Unknown | C58: AGIO | D58: 0.0003 | G58: 0 | H58: 0 | I58: 0 | J58: 0 | M58: 0 | N58: 0 | P58: =NOT(VLOOKUP(C58,Positions!C:C,1,0)=C58) -> FALSE
A59: INDEX | B59: Unknown | C59: ^VIX | G59: 0 | H59: 17.48 | I59: 0 | J59: 0 | M59: 0 | N59: 0 | O59: 0.1748 | P59: =NOT(VLOOKUP(C59,Positions!C:C,1,0)=C59) -> #N/A
A60: INDEX | B60: Unknown | C60: SPY | G60: 0.0121 | H60: 606.78 | I60: 0 | J60: 0 | M60: 26.22943 | N60: 0 | O60: 0.2058 | P60: =NOT(VLOOKUP(C60,Positions!C:C,1,0)=C60) -> #N/A
A61: Technology | B61: Unknown | C61: AVGO | G61: 0 | H61: 0 | I61: 0 | J61: 0 | M61: 0 | N61: 0 | P61: =NOT(VLOOKUP(C61,Positions!C:C,1,0)=C61) -> FALSE
A62: Technology | B62: Unknown | C62: PANW | G62: 0 | H62: 0 | I62: 0 | J62: 0 | M62: 0 | N62: 0 | P62: =NOT(VLOOKUP(C62,Positions!C:C,1,0)=C62) -> FALSE
A63: Technology | B63: Technology | C63: CSIQ | E63: -0.1752625 | F63: 8.873 | G63: 0 | H63: 10.61 | I63: -0.34 | J63: 2.89 | K63: -9.5 | L63: -0.0038645053 | M63: 0 | N63: 3.67128 | O63: 0.838 | P63: =NOT(VLOOKUP(C63,Positions!C:C,1,0)=C63) -> FALSE
A64: Technology | B64: Technology | C64: JKS | E64: -2.2559978 | F64: 3.561 | G64: 0.1288 | H64: 20.44 | I64: -5.01 | J64: 1.93 | K64: -1.3852 | L64: -0.076454289 | M64: 0 | N64: 10.590674 | O64: 0.7329 | P64: =NOT(VLOOKUP(C64,Positions!C:C,1,0)=C64) -> FALSE
A65: Technology | B65: Technology | C65: MAXN | E65: -120.67625 | F65: -80.991 | G65: 0 | H65: 2.92 | I65: -96 | J65: -5.52 | K65: -0.9425 | L65: 0.0056125782 | M65: 0 | N65: -0.5289855 | O65: 1.6769 | P65: =NOT(VLOOKUP(C65,Positions!C:C,1,0)=C65) -> FALSE

Sheet PVT
A1: Ticker2 | B1: (All) | L1: WK50 | R1: WK05 Start | V1: WK05 | AC1: WK05 | AJ1: WK06 | AQ1: WK07 | AY1: WK08 | BG1: Weekly Return % | BH1: Annual % | BJ1: WK09 | BR1: Wkly | BS1: Annual | BU1: WK09 | CC1: Wkly | CD1: Annual | CF1: WK11 | CN1: Wkly | CO1: Annual | CQ1: WK12 | CY1: Wkly | CZ1: Annual | DB1: WK14 | DM1: WK18
L2: 46000 | R2: 45684 | V2: 45685 | AC2: 45688 | AJ2: 45695 | AQ2: 45702 | AY2: 45711 | BG2: =((AY14+BF14)/AY14)^(1/((AY2-AQ2)/7))-1 -> 0.007825058 | BH2: =(1+BG2)^(36)-1 -> 0.32393139 | BJ2: 45716 | BR2: =((BJ14+BQ14)/BJ14)^(1/((BJ2-AY2)/7))-1 -> -0.036296068 | BS2: =(1+BR2)^(36)-1 -> -0.73577694 | BU2: 45723 | CC2: =((BU14+CB14)/BU14)^(1/((BU2-BJ2)/7))-1 -> 0.001769385 | CD2: =(1+CC2)^(36)-1 -> 0.06571035 | CF2: 45730 | CN2: =((CF14+CM14)/CF14)^(1/((CF2-BU2)/7))-1 -> -0.024417601 | CO2: =(1+CN2)^(36)-1 -> -0.58932107 | CQ2: 45736 | CY2: =((CQ14+CX14)/CQ14)^(1/((CQ2-CF2)/7))-1 -> 0.016751469 | CZ2: =(1+CY2)^(36)-1 -> 0.8185829 | DB2: 45751 | DM2: 45778
A3: Row Labels | B3: Initial Volume $ | C3: $% | D3: Volatility | E3: Target Return % | F3: Target P&L | G3: Unrealized Gains % | H3: Actual P&L | K3: Row Labels | L3: Initial Volume $ | M3: $% | N3: Target Return % | O3: Target P&L | P3: Actual P&L vs LV | R3: Initial Volume $ | S3: $% | U3: Row Labels | V3: Initial Volume $ | W3: $% | X3: Target Return % | Y3: Target P&L | Z3: Actual P&L vs LV | AB3: Row Labels | AC3: Initial Volume $ | AD3: $% | AE3: Target Return % | AF3: Target P&L | AG3: Actual P&L vs LV | AI3: Row Labels | AJ3: Initial Volume $ | AK3: $% | AL3: Target Return % | AM3: Target P&L | AN3: Actual P&L vs LV | AP3: Row Labels | AQ3: Initial Volume $ | AR3: $% | AS3: Target Return % | AT3: Target P&L | AU3: Actual Return % | AV3: Actual P&L | AX3: Row Labels | AY3: Initial Volume $ | AZ3: $% | BA3: Volatility | BB3: Target Return % | BC3: Target P&L | BD3: Actual Return % | BE3: Actual P&L | BF3: P&L vs LV | BG3: P&L% Delta | BI3: Row Labels | BJ3: Initial Volume $ | BK3: $% | BL3: Volatility | BM3: Target Return % | BN3: Target P&L | BO3: Actual Return % | BP3: Actual P&L | BQ3: P&L vs LV | BR3: P&L vs Last Week | BT3: Row Labels | BU3: Initial Volume $ | BV3: $% | BW3: Volatility | BX3: Target Return % | BY3: Target P&L | BZ3: Actual Return % | CA3: Actual P&L | CB3: P&L vs LV | CC3: P&L vs Last Week | CE3: Row Labels | CF3: Initial Volume $ | CG3: $% | CH3: Volatility | CI3: Target Return % | CJ3: Target P&L | CK3: Actual Return % | CL3: Actual P&L | CM3: P&L vs LV | CN3: P&L vs Last Week | CP3: Row Labels | CQ3: Initial Volume $ | CR3: $% | CS3: Volatility | CT3: Target Return % | CU3: Target P&L | CV3: Actual Return % | CW3: Actual P&L | CX3: P&L vs LV | CY3: P&L vs LW | DA3: Row Labels | DB3: Initial Volume $ | DC3: $% | DD3: Volatility | DE3: Target Return % | DF3: Target P&L | DG3: Actual Return % | DH3: Actual P&L | DI3: P&L vs LV | DJ3: P&L vs LW | DL3: Row Labels | DM3: Initial Volume $ | DN3: $% | DO3: Volatility | DP3: Target Return % | DQ3: Target P&L | DR3: Actual Return % | DS3: Actual P&L | DT3: P&L vs LV | DU3: P&L vs LW
A4: Consumer Defensive | B4: 417.82236 | D4: 0.22359667 | E4: 0.12685759 | F4: 53.003936 | G4: -0.001429393 | H4: -0.59723237 | K4: Tech | L4: 238.61497 | M4: 0.38101622 | N4: 0.15967772 | O4: 38.101495 | P4: 1.8 | R4: 233.65909 | S4: 0.30679034 | U4: US Consumer | V4: 210.14337 | W4: 0.2982768 | X4: 0.11801519 | Y4: 24.80011 | AB4: ETF | AC4: 218.856 | AD4: 0.23199209 | AE4: 0.035865226 | AF4: 7.84932 | AI4: US Consumer | AJ4: 262.48184 | AK4: 0.25780259 | AL4: 0.11840756 | AM4: 31.079834 | AP4: US Consumer | AQ4: 262.48184 | AR4: 0.25445195 | AS4: 0.11840756 | AT4: 31.079834 | AU4: -0.028863414 | AV4: -7.576122 | AX4: US Consumer | AY4: 283.12184 | AZ4: 0.25870412 | BA4: 0.18558396 | BB4: 0.12435577 | BC4: 35.207834 | BD4: 0.014576339 | BE4: 4.12688 | BF4: =BE4-VLOOKUP(AX4,AP:AV,7,0) -> 11.703002 | BG4: =BD4-VLOOKUP(AX4,AP:AU,6,0) -> 0.043439754 | BI4: US Consumer | BJ4: 283.12184 | BK4: 0.23616254 | BL4: 0.18558396 | BM4: 0.12435577 | BN4: 35.207834 | BO4: 0.025706092 | BP4: 7.277956 | BQ4: =BP4-VLOOKUP(BI4,AX:BF,8,0) -> 3.151076 | BR4: =BO4-VLOOKUP(BI4,AX:BF,7,0) -> 0.011129753 | BT4: US Consumer | BU4: 283.12184 | BV4: 0.23616254 | BW4: 0.18558396 | BX4: 0.12435577 | BY4: 35.207834 | BZ4: 0.04781711 | CA4: 13.538068 | CB4: =CA4-VLOOKUP(BT4,BI:BQ,8,0) -> 6.260112 | CC4: =BZ4-VLOOKUP(BT4,BI:BQ,7,0) -> 0.022111018 | CE4: Energy | CF4: 305.87362 | CG4: 0.25541732 | CH4: 0.36471985 | CI4: 0.1685594 | CJ4: 51.557872 | CK4: -0.10222163 | CL4: -31.266899 | CM4: =CL4-VLOOKUP(CE4,BT:CB,8,0) -> -1.910556 | CN4: =CK4-VLOOKUP(CE4,BT:CB,7,0) -> 0.0061512168 | CP4: Energy | CQ4: 316.86786 | CR4: 0.25792607 | CS4: 0.37044757 | CT4: 0.18127728 | CU4: 57.440945 | CV4: -0.090676153 | CW4: -28.732359 | CX4: =CW4-VLOOKUP(CP4,CE:CM,8,0) -> 2.53454 | CY4: =CV4-VLOOKUP(CP4,CE:CM,7,0) -> 0.011545475 | DA4: ETF | DB4: 405.182 | DC4: 0.26577877 | DD4: 0.17020346 | DE4: 0.062412373 | DF4: 25.28837 | DG4: -0.074144459 | DH4: -30.042 | DI4: =DH4-VLOOKUP(DA4,CP:CX,8,0) -> -23.9348 | DJ4: =DG4-VLOOKUP(DA4,CP:CX,7,0) -> -0.045346692 | DL4: ETF | DM4: 442.44 | DN4: 0.28252609 | DO4: 0.17271264 | DP4: 0.065577638 | DQ4: 29.01417 | DR4: -0.011924539 | DS4: -5.2758931 | DT4: =DS4-VLOOKUP(DL4,DA:DI,8,0) -> 24.766107 | DU4: =DR4-VLOOKUP(DL4,DA:DI,7,0) -> 0.062219919
A5: ETF | B5: 358.73 | D5: 0.16612773 | E5: 0.057141443 | F5: 20.49835 | G5: -0.028316569 | H5: -10.158003 | K5: US Consumer | L5: 159.88784 | M5: 0.25530612 | N5: 0.10835767 | O5: 17.325075 | R5: 210.14337 | S5: 0.2759146 | U5: Tech | V5: 177.40437 | W5: 0.25180718 | X5: 0.17124807 | Y5: 30.380157 | AB5: US Consumer | AC5: 210.14337 | AD5: 0.22275651 | AE5: 0.11801519 | AF5: 24.80011 | AI5: ETF | AJ5: 218.856 | AK5: 0.21495447 | AL5: 0.035865226 | AM5: 7.84932 | AP5: ETF | AQ5: 218.854 | AR5: 0.21215878 | AS5: 0.035865143 | AT5: 7.84923 | AU5: 0.013728787 | AV5: 3.0046 | AX5: Energy | AY5: 245.91162 | AZ5: 0.22470308 | BA5: 0.34646738 | BB5: 0.1313696 | BC5: 32.305312 | BD5: -0.034142145 | BE5: -8.39595 | BF5: =BE5-VLOOKUP(AX5,AP:AV,7,0) -> 0.181322 | BG5: =BD5-VLOOKUP(AX5,AP:AU,6,0) -> 0.0085452192 | BI5: Energy | BJ5: 270.88283 | BK5: 0.22595352 | BL5: 0.34729982 | BM5: 0.13908262 | BN5: 37.675093 | BO5: -0.086924044 | BP5: -23.546231 | BQ5: =BP5-VLOOKUP(BI5,AX:BF,8,0) -> -15.150281 | BR5: =BO5-VLOOKUP(BI5,AX:BF,7,0) -> -0.052781899 | BT5: Energy | BU5: 270.88283 | BV5: 0.22595352 | BW5: 0.34729982 | BX5: 0.13908262 | BY5: 37.675093 | BZ5: -0.10837285 | CA5: -29.356343 | CB5: =CA5-VLOOKUP(BT5,BI:BQ,8,0) -> -5.810112 | CC5: =BZ5-VLOOKUP(BT5,BI:BQ,7,0) -> -0.021448801 | CE5: US Consumer | CF5: 283.12184 | CG5: 0.23641863 | CH5: 0.18558396 | CI5: 0.12435577 | CJ5: 35.207834 | CK5: 0.030746756 | CL5: 8.705078 | CM5: =CL5-VLOOKUP(CE5,BT:CB,8,0) -> -4.83299 | CN5: =CK5-VLOOKUP(CE5,BT:CB,7,0) -> -0.017070354 | CP5: US Consumer | CQ5: 283.12184 | CR5: 0.23045727 | CS5: 0.18558396 | CT5: 0.12435577 | CU5: 35.207834 | CV5: 0.026709229 | CW5: 7.561966 | CX5: =CW5-VLOOKUP(CP5,CE:CM,8,0) -> -1.143112 | CY5: =CV5-VLOOKUP(CP5,CE:CM,7,0) -> -0.0040375268 | DA5: Energy | DB5: 326.87036 | DC5: 0.21441032 | DD5: 0.37316653 | DE5: 0.19741586 | DF5: 64.529392 | DG5: -0.13036696 | DH5: -42.613096 | DI5: =DH5-VLOOKUP(DA5,CP:CX,8,0) -> -13.880737 | DJ5: =DG5-VLOOKUP(DA5,CP:CX,7,0) -> -0.039690809 | DL5: Energy | DM5: 315.87013 | DN5: 0.20170318 | DO5: 0.44345793 | DP5: 0.26920749 | DQ5: 85.034604 | DR5: -0.16624651 | DS5: -52.512308 | DT5: =DS5-VLOOKUP(DL5,DA:DI,8,0) -> -9.8992124 | DU5: =DR5-VLOOKUP(DL5,DA:DI,7,0) -> -0.035879553
A6: Financial Services | B6: 142.32675 | D6: 0.27379334 | E6: 0.11945581 | F6: 17.001757 | G6: 0.094559706 | H6: 13.458376 | K6: Banking | L6: 84.915516 | M6: 0.13559161 | N6: 0.28530609 | O6: 24.226914 | R6: 149.81095 | S6: 0.19669918 | U6: Energy | V6: 162.11428 | W6: 0.23010446 | X6: 0.13072197 | Y6: 21.191897 | AB6: Tech | AC6: 177.40437 | AD6: 0.18805247 | AE6: 0.17124807 | AF6: 30.380157 | AI6: Tech | AJ6: 196.93235 | AK6: 0.19342164 | AL6: 0.17126296 | AM6: 33.727218 | AP6: Energy | AQ6: 200.93234 | AR6: 0.19478539 | AS6: 0.1294557 | AT6: 26.011838 | AU6: -0.042687364 | AV6: -8.577272 | AX6: ETF | AY6: 218.852 | AZ6: 0.1999772 | BA6: 0.14808574 | BB6: 0.061035677 | BC6: 13.35778 | BD6: 0.034507338 | BE6: 7.552 | BF6: =BE6-VLOOKUP(AX6,AP:AV,7,0) -> 4.5474 | BG6: =BD6-VLOOKUP(AX6,AP:AU,6,0) -> 0.020778551 | BI6: ETF | BJ6: 263.352 | BK6: 0.21967178 | BL6: 0.15145076 | BM6: 0.064747107 | BN6: 17.05128 | BO6: -0.021568091 | BP6: -5.68 | BQ6: =BP6-VLOOKUP(BI6,AX:BF,8,0) -> -13.232 | BR6: =BO6-VLOOKUP(BI6,AX:BF,7,0) -> -0.05607543 | BT6: ETF | BU6: 263.352 | BV6: 0.21967178 | BW6: 0.15145076 | BX6: 0.064747107 | BY6: 17.05128 | BZ6: -0.022054133 | CA6: -5.808 | CB6: =CA6-VLOOKUP(BT6,BI:BQ,8,0) -> -0.128 | CC6: =BZ6-VLOOKUP(BT6,BI:BQ,7,0) -> -0.0004860415 | CE6: ETF | CF6: 212.072 | CG6: 0.17708903 | CH6: 0.17428939 | CI6: 0.070005658 | CJ6: 14.84624 | CK6: -0.057942586 | CL6: -12.288 | CM6: =CL6-VLOOKUP(CE6,BT:CB,8,0) -> -6.48 | CN6: =CK6-VLOOKUP(CE6,BT:CB,7,0) -> -0.035888453 | CP6: Tech | CQ6: 225.57202 | CR6: 0.18361251 | CS6: 0.30432885 | CT6: 0.19490798 | CU6: 43.965787 | CV6: -0.049341581 | CW6: -11.13008 | CX6: =CW6-VLOOKUP(CP6,CE:CM,8,0) -> 5.80583 | CY6: =CV6-VLOOKUP(CP6,CE:CM,7,0) -> 0.033036023 | DA6: US Consumer | DB6: 289.90282 | DC6: 0.1901615 | DD6: 0.18629771 | DE6: 0.12853695 | DF6: 37.263223 | DG6: 0.025912994 | DH6: 7.51225 | DI6: =DH6-VLOOKUP(DA6,CP:CX,8,0) -> -0.049716 | DJ6: =DG6-VLOOKUP(DA6,CP:CX,7,0) -> -0.00079623474 | DL6: Tech | DM6: 280.56124 | DN6: 0.1791562 | DO6: 0.31720021 | DP6: 0.25314434 | DQ6: 71.02249 | DR6: 0.0015712729 | DS6: 0.44083827 | DT6: =DS6-VLOOKUP(DL6,DA:DI,8,0) -> 29.394319 | DU6: =DR6-VLOOKUP(DL6,DA:DI,7,0) -> 0.10476971
A7: FOREX | B7: 3.5253721e-29 | D7: 0.48555664 | E7: 0.098802765 | F7: 3.4831651e-30 | G7: -0.040392941 | H7: -1.4240015e-30 | K7: Asia Consumer | L7: 76.938714 | M7: 0.1228544 | N7: 0.079955036 | O7: 6.1516376 | P7: -4.4 | R7: 108.03081 | S7: 0.14184258 | U7: Banking | V7: 94.882214 | W7: 0.1346755 | X7: 0.28159744 | Y7: 26.718589 | Z7: 10.31 | AB7: Energy | AC7: 172.11133 | AD7: 0.18244173 | AE7: 0.12893749 | AF7: 22.191603 | AG7: 0 | AI7: Energy | AJ7: 188.97589 | AK7: 0.18560703 | AL7: 0.14271594 | AM7: 26.969872 | AN7: 0 | AP7: Tech | AQ7: 198.38495 | AR7: 0.19231592 | AS7: 0.16268683 | AT7: 32.274618 | AU7: 0.035134339 | AV7: 6.970124 | AX7: Tech | AY7: 155.61477 | AZ7: 0.14219384 | BA7: 0.28791727 | BB7: 0.16617376 | BC7: 25.859091 | BD7: 0.0068824508 | BE7: 1.071011 | BF7: =BE7-VLOOKUP(AX7,AP:AV,7,0) -> -5.899113 | BG7: =BD7-VLOOKUP(AX7,AP:AU,6,0) -> -0.028251888 | BI7: Tech | BJ7: 190.59815 | BK7: 0.15898506 | BL7: 0.30298317 | BM7: 0.18573439 | BN7: 35.400631 | BO7: -0.043316255 | BP7: -8.255998 | BQ7: =BP7-VLOOKUP(BI7,AX:BF,8,0) -> -9.327009 | BR7: =BO7-VLOOKUP(BI7,AX:BF,7,0) -> -0.050198705 | BT7: Tech | BU7: 190.59815 | BV7: 0.15898506 | BW7: 0.30298317 | BX7: 0.18573439 | BY7: 35.400631 | BZ7: -0.057042238 | CA7: -10.872145 | CB7: =CA7-VLOOKUP(BT7,BI:BQ,8,0) -> -2.616147 | CC7: =BZ7-VLOOKUP(BT7,BI:BQ,7,0) -> -0.013725983 | CE7: Tech | CF7: 205.58877 | CG7: 0.17167526 | CH7: 0.30786973 | CI7: 0.19583772 | CJ7: 40.262035 | CK7: -0.082377604 | CL7: -16.93591 | CM7: =CL7-VLOOKUP(CE7,BT:CB,8,0) -> -6.063765 | CN7: =CK7-VLOOKUP(CE7,BT:CB,7,0) -> -0.025335366 | CP7: ETF | CQ7: 212.072 | CR7: 0.17262368 | CS7: 0.17428939 | CT7: 0.070005658 | CU7: 14.84624 | CV7: -0.028797767 | CW7: -6.1072 | CX7: =CW7-VLOOKUP(CP7,CE:CM,8,0) -> 6.1808 | CY7: =CV7-VLOOKUP(CP7,CE:CM,7,0) -> 0.029144819 | DA7: Tech | DB7: 280.56124 | DC7: 0.18403389 | DD7: 0.31720021 | DE7: 0.25314434 | DF7: 71.02249 | DG7: -0.10319844 | DH7: -28.953481 | DI7: =DH7-VLOOKUP(DA7,CP:CX,8,0) -> -17.823401 | DJ7: =DG7-VLOOKUP(DA7,CP:CX,7,0) -> -0.053856856 | DL7: US Consumer | DM7: 275.15882 | DN7: 0.17570641 | DO7: 0.18645298 | DP7: 0.13167357 | DQ7: 36.231143 | DR7: 0.0048114124 | DS7: 1.3239025 | DT7: =DS7-VLOOKUP(DL7,DA:DI,8,0) -> -6.1883475 | DU7: =DR7-VLOOKUP(DL7,DA:DI,7,0) -> -0.021101582
A8: Consumer Cyclical | B8: #N/A | D8: #N/A | E8: #N/A | F8: #N/A | G8: #N/A | H8: #N/A | K8: Energy | L8: 65.902309 | M8: 0.10523166 | N8: 0.29383162 | O8: 19.364182 | R8: 59.980461 | S8: 0.078753306 | U8: Asia Consumer | V8: 59.980461 | W8: 0.085136066 | X8: 0.091757028 | Y8: 5.5036289 | AB8: Banking | AC8: 94.882214 | AD8: 0.1005772 | AE8: 0.28159744 | AF8: 26.718589 | AI8: Banking | AJ8: 94.882214 | AK8: 0.093190754 | AL8: 0.28159744 | AM8: 26.718589 | AP8: Banking | AQ8: 94.882214 | AR8: 0.091979562 | AS8: 0.28159744 | AT8: 26.718589 | AU8: 0.1235719 | AV8: 11.724775 | AX8: Banking | AY8: 114.87946 | AZ8: 0.10497173 | BA8: 0.33977481 | BB8: 0.29350438 | BC8: 33.717626 | BD8: 0.092931231 | BE8: 10.67589 | BF8: =BE8-VLOOKUP(AX8,AP:AV,7,0) -> -1.048885 | BG8: =BD8-VLOOKUP(AX8,AP:AU,6,0) -> -0.030640664 | BI8: Banking | BJ8: 114.87946 | BK8: 0.095825268 | BL8: 0.33977481 | BM8: 0.29350438 | BN8: 33.717626 | BO8: 0.12785504 | BP8: 14.687918 | BQ8: =BP8-VLOOKUP(BI8,AX:BF,8,0) -> 4.012028 | BR8: =BO8-VLOOKUP(BI8,AX:BF,7,0) -> 0.034923805 | BT8: Banking | BU8: 114.87946 | BV8: 0.095825268 | BW8: 0.33977481 | BX8: 0.29350438 | BY8: 33.717626 | BZ8: 0.17852522 | CA8: 20.508882 | CB8: =CA8-VLOOKUP(BT8,BI:BQ,8,0) -> 5.820964 | CC8: =BZ8-VLOOKUP(BT8,BI:BQ,7,0) -> 0.050670188 | CE8: Banking | CF8: 114.87946 | CG8: 0.095929179 | CH8: 0.33977481 | CI8: 0.29350438 | CJ8: 33.717626 | CK8: 0.12259087 | CL8: 14.083174 | CM8: =CL8-VLOOKUP(CE8,BT:CB,8,0) -> -6.425708 | CN8: =CK8-VLOOKUP(CE8,BT:CB,7,0) -> -0.055934349 | CP8: Banking | CQ8: 114.87946 | CR8: 0.0935103 | CS8: 0.33977481 | CT8: 0.29350438 | CU8: 33.717626 | CV8: 0.14711167 | CW8: 16.90011 | CX8: =CW8-VLOOKUP(CP8,CE:CM,8,0) -> 2.816936 | CY8: =CV8-VLOOKUP(CP8,CE:CM,7,0) -> 0.024520797 | DA8: Banking | DB8: 145.98324 | DC8: 0.095757579 | DD8: 0.34942834 | DE8: 0.10057388 | DF8: 14.682101 | DG8: 0.041389545 | DH8: 6.04218 | DI8: =DH8-VLOOKUP(DA8,CP:CX,8,0) -> -10.85793 | DJ8: =DG8-VLOOKUP(DA8,CP:CX,7,0) -> -0.10572213 | DL8: Banking | DM8: 165.97831 | DN8: 0.10598771 | DO8: 0.34047415 | DP8: 0.10150463 | DQ8: 16.847567 | DR8: 0.10193837 | DS8: 16.919559 | DT8: =DS8-VLOOKUP(DL8,DA:DI,8,0) -> 10.877379 | DU8: =DR8-VLOOKUP(DL8,DA:DI,7,0) -> 0.060548827
A9: Industrials | B9: #N/A | D9: #N/A | E9: #N/A | F9: #N/A | G9: #N/A | H9: #N/A | K9: Forex | L9: 2.9170552e-16 | M9: 4.6579028e-19 | N9: 0.097993642 | O9: 2.8585286e-17 | R9: 2.9170552e-16 | S9: 3.8300429e-19 | U9: Forex | V9: 2.9170552e-16 | W9: 4.1404584e-19 | X9: 0.097993642 | Y9: 2.8585286e-17 | AB9: Asia Consumer | AC9: 59.980461 | AD9: 0.063580585 | AE9: 0.091757028 | AF9: 5.5036289 | AI9: Asia Consumer | AJ9: 46.022979 | AK9: 0.04520253 | AL9: 0.12015729 | AM9: 5.5299966 | AN9: 2.76 | AP9: Asia Consumer | AQ9: 46.022979 | AR9: 0.044615037 | AS9: 0.12015729 | AT9: 5.5299966 | AU9: -0.038592156 | AV9: -1.776126 | AX9: Asia Consumer | AY9: 66.0058 | AZ9: 0.060313158 | BA9: 0.35603887 | BB9: 0.1049725 | BC9: 6.9287941 | BD9: -0.012304873 | BE9: -0.812193 | BF9: =BE9-VLOOKUP(AX9,AP:AV,7,0) -> 0.963933 | BG9: =BD9-VLOOKUP(AX9,AP:AU,6,0) -> 0.026287283 | BI9: Asia Consumer | BJ9: 66.009601 | BK9: 0.055061083 | BL9: 0.35602772 | BM9: 0.10497049 | BN9: 6.9290601 | BO9: -0.024279029 | BP9: -1.602649 | BQ9: =BP9-VLOOKUP(BI9,AX:BF,8,0) -> -0.790456 | BR9: =BO9-VLOOKUP(BI9,AX:BF,7,0) -> -0.011974156 | BT9: Asia Consumer | BU9: 66.009601 | BV9: 0.055061083 | BW9: 0.35602772 | BX9: 0.10497049 | BY9: 6.9290601 | BZ9: -0.031025805 | CA9: -2.048001 | CB9: =CA9-VLOOKUP(BT9,BI:BQ,8,0) -> -0.445352 | CC9: =BZ9-VLOOKUP(BT9,BI:BQ,7,0) -> -0.0067467761 | CE9: Asia Consumer | CF9: 66.009601 | CG9: 0.05512079 | CH9: 0.35602772 | CI9: 0.10497049 | CJ9: 6.9290601 | CK9: -0.084474787 | CL9: -5.576147 | CM9: =CL9-VLOOKUP(CE9,BT:CB,8,0) -> -3.528146 | CN9: =CK9-VLOOKUP(CE9,BT:CB,7,0) -> -0.053448982 | CP9: Asia Consumer | CQ9: 66.009601 | CR9: 0.053730905 | CS9: 0.35602772 | CT9: 0.10497049 | CU9: 6.9290601 | CV9: -0.060642709 | CW9: -4.003001 | CX9: =CW9-VLOOKUP(CP9,CE:CM,8,0) -> 1.573146 | CY9: =CV9-VLOOKUP(CP9,CE:CM,7,0) -> 0.023832079 | DA9: Asia Consumer | DB9: 66.009601 | DC9: 0.043298939 | DD9: 0.35602772 | DE9: 0.10497049 | DF9: 6.9290601 | DG9: -0.055669568 | DH9: -3.674726 | DI9: =DH9-VLOOKUP(DA9,CP:CX,8,0) -> 0.328275 | DJ9: =DG9-VLOOKUP(DA9,CP:CX,7,0) -> 0.0049731402 | DL9: Asia Consumer | DM9: 66.009601 | DN9: 0.042151331 | DO9: 0.35602772 | DP9: 0.10497049 | DQ9: 6.9290601 | DR9: -0.044952372 | DS9: -2.9672881 | DT9: =DS9-VLOOKUP(DL9,DA:DI,8,0) -> 0.70743788 | DU9: =DR9-VLOOKUP(DL9,DA:DI,7,0) -> 0.010717197
A10: Energy & Utilities | B10: #N/A | D10: #N/A | E10: #N/A | F10: #N/A | G10: #N/A | H10: #N/A | K10: Health | L10: 3.8292e-17 | M10: 6.1143997e-20 | N10: 0.2 | O10: 7.6584e-18 | R10: 3.8292e-17 | S10: 5.0276733e-20 | U10: Health | V10: 3.8292e-17 | W10: 5.4351537e-20 | X10: 0.2 | Y10: 7.6584e-18 | AB10: Health | AC10: 9.99925 | AD10: 0.010599421 | AE10: 0.2 | AF10: 1.99985 | AI10: Health | AJ10: 9.99925 | AK10: 0.0098209939 | AL10: 0.2 | AM10: 1.99985 | AP10: Health | AQ10: 9.99925 | AR10: 0.0096933514 | AS10: 0.2 | AT10: 1.99985 | AU10: -0.044853364 | AV10: -0.4485 | AX10: Health | AY10: 9.99925 | AZ10: 0.009136869 | BA10: 0.2 | BB10: 0.2 | BC10: 1.99985 | BD10: 0.012650949 | BE10: 0.1265 | BF10: =BE10-VLOOKUP(AX10,AP:AV,7,0) -> 0.575 | BG10: =BD10-VLOOKUP(AX10,AP:AU,6,0) -> 0.057504313 | BI10: Health | BJ10: 9.99925 | BK10: 0.0083407493 | BL10: 0.2 | BM10: 0.2 | BN10: 1.99985 | BO10: 0.021851639 | BP10: 0.2185 | BQ10: =BP10-VLOOKUP(BI10,AX:BF,8,0) -> 0.092 | BR10: =BO10-VLOOKUP(BI10,AX:BF,7,0) -> 0.0092006901 | BT10: Health | BU10: 9.99925 | BV10: 0.0083407493 | BW10: 0.2 | BX10: 0.2 | BY10: 1.99985 | BZ10: -0.074180564 | CA10: -0.74175 | CB10: =CA10-VLOOKUP(BT10,BI:BQ,8,0) -> -0.96025 | CC10: =BZ10-VLOOKUP(BT10,BI:BQ,7,0) -> -0.096032202 | CE10: Health | CF10: 9.99925 | CG10: 0.0083497939 | CH10: 0.2 | CI10: 0.2 | CJ10: 1.99985 | CK10: -0.074180564 | CL10: -0.74175 | CM10: =CL10-VLOOKUP(CE10,BT:CB,8,0) -> 0 | CN10: =CK10-VLOOKUP(CE10,BT:CB,7,0) -> 0 | CP10: Health | CQ10: 9.99925 | CR10: 0.0081392516 | CS10: 0.2 | CT10: 0.2 | CU10: 1.99985 | CV10: -0.089131685 | CW10: -0.89125 | CX10: =CW10-VLOOKUP(CP10,CE:CM,8,0) -> -0.1495 | CY10: =CV10-VLOOKUP(CP10,CE:CM,7,0) -> -0.014951121 | DA10: Health | DB10: 9.99925 | DC10: 0.0065589992 | DD10: 0.2 | DE10: 0.2 | DF10: 1.99985 | DG10: -0.23361127 | DH10: -2.3359375 | DI10: =DH10-VLOOKUP(DA10,CP:CX,8,0) -> -1.4446875 | DJ10: =DG10-VLOOKUP(DA10,CP:CX,7,0) -> -0.14447959 | DL10: Health | DM10: 19.996548 | DN10: 0.012769068 | DO10: 0.2 | DP10: 0.2 | DQ10: 3.9993096 | DR10: -0.065190664 | DS10: -1.3035882 | DT10: =DS10-VLOOKUP(DL10,DA:DI,8,0) -> 1.0323493 | DU10: =DR10-VLOOKUP(DL10,DA:DI,7,0) -> 0.16842061
A11: APA | B11: 119.94008 | D11: 0.4029 | E11: 0.41307815 | F11: 49.544628 | G11: -0.14274322 | H11: -17.120634 | K11: Industrials | L11: 1.3353e-17 | M11: 2.1321837e-20 | N11: 0.07 | O11: 9.3471e-19 | R11: 1.3353e-17 | S11: 1.7532258e-20 | U11: Industrials | V11: 1.3353e-17 | W11: 1.8953204e-20 | X11: 0.07 | Y11: 9.3471e-19 | AB11: Forex | AC11: 2.9170552e-16 | AD11: 3.0921415e-19 | AE11: 0.097993642 | AF11: 2.8585286e-17 | AI11: Forex | AJ11: 2.9170552e-16 | AK11: 2.865053e-19 | AL11: 0.097993642 | AM11: 2.8585286e-17 | AP11: Forex | AQ11: 2.9136552e-16 | AR11: 2.8245202e-19 | AS11: 0.099274912 | AT11: 2.8925286e-17 | AU11: -0.94049399 | AV11: -2.7402752e-16 | AX11: Forex | AY11: 2.9136552e-16 | AZ11: 2.6623683e-19 | BA11: 0.48159902 | BB11: 0.099274912 | BC11: 2.8925286e-17 | BD11: -0.94150046 | BE11: -2.7432077e-16 | BF11: =BE11-VLOOKUP(AX11,AP:AV,7,0) -> -2.9325e-19 | BG11: =BD11-VLOOKUP(AX11,AP:AU,6,0) -> -0.0010064678 | BI11: Forex | BJ11: 2.9136552e-16 | BK11: 2.430389e-19 | BL11: 0.48159902 | BM11: 0.099274912 | BN11: 2.8925286e-17 | BO11: -0.94102185 | BP11: -2.7418132e-16 | BQ11: =BP11-VLOOKUP(BI11,AX:BF,8,0) -> 1.3945e-19 | BR11: =BO11-VLOOKUP(BI11,AX:BF,7,0) -> 0.00047860845 | BT11: Forex | BU11: 2.9136552e-16 | BV11: 2.430389e-19 | BW11: 0.48159902 | BX11: 0.099274912 | BY11: 2.8925286e-17 | BZ11: -0.94205464 | CA11: -2.7448224e-16 | CB11: =CA11-VLOOKUP(BT11,BI:BQ,8,0) -> -3.0092e-19 | CC11: =BZ11-VLOOKUP(BT11,BI:BQ,7,0) -> -0.0010327921 | CE11: Forex | CF11: 2.9136552e-16 | CG11: 2.4330245e-19 | CH11: 0.48159902 | CI11: 0.099274912 | CJ11: 2.8925286e-17 | CK11: 0 | CL11: 0 | CM11: =CL11-VLOOKUP(CE11,BT:CB,8,0) -> 2.7448224e-16 | CN11: =CK11-VLOOKUP(CE11,BT:CB,7,0) -> 0.94205464 | CP11: Forex | CQ11: 2.9136552e-16 | CR11: 2.3716752e-19 | CS11: 0.48159902 | CT11: 0.099274912 | CU11: 2.8925286e-17 | CV11: 0 | CW11: 0 | CX11: =CW11-VLOOKUP(CP11,CE:CM,8,0) -> 0 | CY11: =CV11-VLOOKUP(CP11,CE:CM,7,0) -> 0 | DA11: Forex | DB11: 2.9136552e-16 | DC11: 1.9112095e-19 | DD11: 0.48159902 | DE11: 0.099274912 | DF11: 2.8925286e-17 | DG11: 0 | DH11: 0 | DI11: =DH11-VLOOKUP(DA11,CP:CX,8,0) -> 0 | DJ11: =DG11-VLOOKUP(DA11,CP:CX,7,0) -> 0 | DL11: Forex | DM11: 2.9136552e-16 | DN11: 1.8605543e-19 | DO11: 0.48159902 | DP11: 0.099274912 | DQ11: 2.8925286e-17 | DR11: 0.16349509 | DS11: 4.7636831e-17 | DT11: =DS11-VLOOKUP(DL11,DA:DI,8,0) -> 4.7636831e-17 | DU11: =DR11-VLOOKUP(DL11,DA:DI,7,0) -> 0.16349509
A12: YPF | B12: 80.001305 | D12: 0.5311 | E12: 0.37779002 | F12: 30.223695 | G12: -0.19647286 | H12: -15.718085 | K12: Automotive | L12: 5.6e-18 | M12: 8.9419822e-21 | N12: 0.07 | O12: 3.92e-19 | R12: 5.6e-18 | S12: 7.352703e-21 | U12: Automotive | V12: 5.6e-18 | W12: 7.9486213e-21 | X12: 0.07 | Y12: 3.92e-19 | AB12: Industrials | AC12: 1.3353e-17 | AD12: 1.4154469e-20 | AE12: 0.07 | AF12: 9.3471e-19 | AI12: Industrials | AJ12: 1.3353e-17 | AK12: 1.3114957e-20 | AL12: 0.07 | AM12: 9.3471e-19 | AP12: Industrials | AQ12: 1.3353e-17 | AR12: 1.2944503e-20 | AS12: 0.07 | AT12: 9.3471e-19 | AU12: 0.11300831 | AV12: 1.509e-18 | AX12: Industrials | AY12: 1.3353e-17 | AZ12: 1.2201376e-20 | BA12: 0.2 | BB12: 0.07 | BC12: 9.3471e-19 | BD12: 0.085748521 | BE12: 1.145e-18 | BF12: =BE12-VLOOKUP(AX12,AP:AV,7,0) -> -3.64e-19 | BG12: =BD12-VLOOKUP(AX12,AP:AU,6,0) -> -0.027259792 | BI12: Industrials | BJ12: 1.3353e-17 | BK12: 1.1138238e-20 | BL12: 0.2 | BM12: 0.07 | BN12: 9.3471e-19 | BO12: 0.16168651 | BP12: 2.159e-18 | BQ12: =BP12-VLOOKUP(BI12,AX:BF,8,0) -> 1.014e-18 | BR12: =BO12-VLOOKUP(BI12,AX:BF,7,0) -> 0.075937991 | BT12: Industrials | BU12: 1.3353e-17 | BV12: 1.1138238e-20 | BW12: 0.2 | BX12: 0.07 | BY12: 9.3471e-19 | BZ12: 0.09563394 | CA12: 1.277e-18 | CB12: =CA12-VLOOKUP(BT12,BI:BQ,8,0) -> -8.82e-19 | CC12: =BZ12-VLOOKUP(BT12,BI:BQ,7,0) -> -0.066052572 | CE12: Industrials | CF12: 1.3353e-17 | CG12: 1.1150316e-20 | CH12: 0.2 | CI12: 0.07 | CJ12: 9.3471e-19 | CK12: 0 | CL12: 0 | CM12: =CL12-VLOOKUP(CE12,BT:CB,8,0) -> -1.277e-18 | CN12: =CK12-VLOOKUP(CE12,BT:CB,7,0) -> -0.09563394 | CP12: Industrials | CQ12: 1.3353e-17 | CR12: 1.0869158e-20 | CS12: 0.2 | CT12: 0.07 | CU12: 9.3471e-19 | CV12: 0 | CW12: 0 | CX12: =CW12-VLOOKUP(CP12,CE:CM,8,0) -> 0 | CY12: =CV12-VLOOKUP(CP12,CE:CM,7,0) -> 0 | DA12: Industrials | DB12: 1.3353e-17 | DC12: 8.7588885e-21 | DD12: 0.2 | DE12: 0.07 | DF12: 9.3471e-19 | DG12: 0 | DH12: 0 | DI12: =DH12-VLOOKUP(DA12,CP:CX,8,0) -> 0 | DJ12: =DG12-VLOOKUP(DA12,CP:CX,7,0) -> 0 | DL12: Industrials | DM12: 1.3353e-17 | DN12: 8.5267402e-21 | DO12: 0.2 | DP12: 0.07 | DQ12: 9.3471e-19 | DR12: 0.043772935 | DS12: 5.845e-19 | DT12: =DS12-VLOOKUP(DL12,DA:DI,8,0) -> 5.845e-19 | DU12: =DR12-VLOOKUP(DL12,DA:DI,7,0) -> 0.043772935
A13: NextEra Energy | B13: 54.980109 | D13: 0.2786 | E13: 0.05 | F13: 2.7490054 | G13: -0.1018456 | H13: -5.5994823 | K13: Grand Total | L13: 626.25935 | M13: 1 | N13: 0.16793251 | O13: 105.1693 | P13: =SUM(P4:P12) -> -2.6 | R13: 761.62467 | S13: 1 | U13: Grand Total | V13: 704.52469 | W13: 1 | X13: 0.1541385 | Y13: 108.59438 | Z13: =SUM(Z4:Z12) -> 10.31 | AB13: Automotive | AC13: 5.6e-18 | AD13: 5.936121e-21 | AE13: 0.07 | AF13: 3.92e-19 | AI13: Automotive | AJ13: 5.6e-18 | AK13: 5.5001691e-21 | AL13: 0.07 | AM13: 3.92e-19 | AP13: Automotive | AQ13: 5.6e-18 | AR13: 5.4286839e-21 | AS13: 0.07 | AT13: 3.92e-19 | AU13: 0.19642857 | AV13: 1.1e-18 | AX13: Automotive | AY13: 5.6e-18 | AZ13: 5.1170304e-21 | BA13: 0.19 | BB13: 0.07 | BC13: 3.92e-19 | BD13: 0.19071429 | BE13: 1.068e-18 | BF13: =BE13-VLOOKUP(AX13,AP:AV,7,0) -> -3.2e-20 | BG13: =BD13-VLOOKUP(AX13,AP:AU,6,0) -> -0.0057142857 | BI13: Automotive | BJ13: 5.6e-18 | BK13: 4.6711699e-21 | BL13: 0.19 | BM13: 0.07 | BN13: 3.92e-19 | BO13: 0.16285714 | BP13: 9.12e-19 | BQ13: =BP13-VLOOKUP(BI13,AX:BF,8,0) -> -1.56e-19 | BR13: =BO13-VLOOKUP(BI13,AX:BF,7,0) -> -0.027857143 | BT13: Automotive | BU13: 5.6e-18 | BV13: 4.6711699e-21 | BW13: 0.19 | BX13: 0.07 | BY13: 3.92e-19 | BZ13: 0.19339286 | CA13: 1.083e-18 | CB13: =CA13-VLOOKUP(BT13,BI:BQ,8,0) -> 1.71e-19 | CC13: =BZ13-VLOOKUP(BT13,BI:BQ,7,0) -> 0.030535714 | CE13: Automotive | CF13: 5.6e-18 | CG13: 4.6762353e-21 | CH13: 0.19 | CI13: 0.07 | CJ13: 3.92e-19 | CK13: 0 | CL13: 0 | CM13: =CL13-VLOOKUP(CE13,BT:CB,8,0) -> -1.083e-18 | CN13: =CK13-VLOOKUP(CE13,BT:CB,7,0) -> -0.19339286 | CP13: Automotive | CQ13: 5.6e-18 | CR13: 4.5583228e-21 | CS13: 0.19 | CT13: 0.07 | CU13: 3.92e-19 | CV13: 0 | CW13: 0 | CX13: =CW13-VLOOKUP(CP13,CE:CM,8,0) -> 0 | CY13: =CV13-VLOOKUP(CP13,CE:CM,7,0) -> 0 | DA13: Automotive | DB13: 5.6e-18 | DC13: 3.673315e-21 | DD13: 0.19 | DE13: 0.07 | DF13: 3.92e-19 | DG13: 0 | DH13: 0 | DI13: =DH13-VLOOKUP(DA13,CP:CX,8,0) -> 0 | DJ13: =DG13-VLOOKUP(DA13,CP:CX,7,0) -> 0 | DL13: Automotive | DM13: 5.6e-18 | DN13: 3.5759564e-21 | DO13: 0.19 | DP13: 0.07 | DQ13: 3.92e-19 | DR13: 0.021071434 | DS13: 1.1800003e-19 | DT13: =DS13-VLOOKUP(DL13,DA:DI,8,0) -> 1.1800003e-19 | DU13: =DR13-VLOOKUP(DL13,DA:DI,7,0) -> 0.021071434
A14: First Solar | B14: 38.330673 | D14: 0.5203 | E14: 0.5173001 | F14: 19.828461 | G14: -0.018964333 | H14: -0.72691563 | AB14: Grand Total | AC14: 943.377 | AD14: 1 | AE14: 0.12661243 | AF14: 119.44326 | AG14: =SUM(AG4:AG13) -> 0 | AI14: Grand Total | AJ14: 1018.1505 | AK14: 1 | AL14: 0.1314881 | AM14: 133.87468 | AN14: =SUM(AN4:AN13) -> 2.76 | AP14: Grand Total | AQ14: 1031.5576 | AR14: 1 | AS14: 0.12744219 | AT14: 131.46395 | AU14: 0.0032198678 | AV14: 3.321479 | AX14: Grand Total | AY14: 1094.3847 | AZ14: 1 | BA14: 0.25538541 | BB14: 0.13649339 | BC14: 149.37629 | BD14: 0.013107034 | BE14: 14.344138 | BF14: =BE14-VLOOKUP(AX14,AP:AV,7,0) -> 11.022659 | BG14: =BD14-VLOOKUP(AX14,AP:AU,6,0) -> 0.0098871662 | BI14: Grand Total | BJ14: 1198.8431 | BK14: 1 | BL14: 0.25757128 | BM14: 0.14011956 | BN14: 167.98137 | BO14: -0.014097344 | BP14: -16.900504 | BQ14: =BP14-VLOOKUP(BI14,AX:BF,8,0) -> -31.244642 | BR14: =BO14-VLOOKUP(BI14,AX:BF,7,0) -> -0.027204378 | BT14: Grand Total | BU14: 1198.8431 | BV14: 1 | BW14: 0.25757128 | BX14: 0.14011956 | BY14: 167.98137 | BZ14: -0.012327959 | CA14: -14.779289 | CB14: =CA14-VLOOKUP(BT14,BI:BQ,8,0) -> 2.121215 | CC14: =BZ14-VLOOKUP(BT14,BI:BQ,7,0) -> 0.001769385 | CE14: Grand Total | CF14: 1197.5445 | CG14: 1 | CH14: 0.27463843 | CI14: 0.15408238 | CJ14: 184.52052 | CK14: -0.036758929 | CL14: -44.020454 | CM14: =CL14-VLOOKUP(CE14,BT:CB,8,0) -> -29.241165 | CN14: =CK14-VLOOKUP(CE14,BT:CB,7,0) -> -0.02443097 | CP14: Grand Total | CQ14: 1228.522 | CR14: 1 | CS14: 0.27681231 | CT14: 0.1580007 | CU14: 194.10734 | CV14: -0.021490713 | CW14: -26.401814 | CX14: =CW14-VLOOKUP(CP14,CE:CM,8,0) -> 17.61864 | CY14: =CV14-VLOOKUP(CP14,CE:CM,7,0) -> 0.015268216 | DA14: Grand Total | DB14: 1524.5085 | DC14: 1 | DD14: 0.2692373 | DE14: 0.14543342 | DF14: 221.71449 | DG14: -0.061701729 | DH14: -94.06481 | DI14: =DH14-VLOOKUP(DA14,CP:CX,8,0) -> -67.662996 | DJ14: =DG14-VLOOKUP(DA14,CP:CX,7,0) -> -0.040211016 | DL14: Grand Total | DM14: 1566.0146 | DN14: 1 | DO14: 0.281479 | DP14: 0.15905237 | DQ14: 249.07834 | DR14: -0.027697556 | DS14: -43.374778 | DT14: =DS14-VLOOKUP(DL14,DA:DI,8,0) -> 50.690032 | DU14: =DR14-VLOOKUP(DL14,DA:DI,7,0) -> 0.034004173
A15: Excelon | B15: 20.002244 | D15: 0.2029 | E15: 0.05 | F15: 1.0001122 | G15: 0.075282415 | H15: 1.5058172
A16: Duke Energy | B16: 1.1649e-30 | D16: 0.1768 | E16: 0.040003453 | F16: 4.6600021e-32 | G16: 0.046270062 | H16: 5.3899994e-32
A17: SolarWinds | B17: #N/A | D17: #N/A | E17: #N/A | F17: #N/A | G17: #N/A | H17: #N/A
A18: PG&E | B18: #N/A | D18: #N/A | E18: #N/A | F18: #N/A | G18: #N/A | H18: #N/A
A19: Technology | B19: #N/A | D19: #N/A | E19: #N/A | F19: #N/A | G19: #N/A | H19: #N/A | BJ19: 45715
A20: Healthcare | B20: #N/A | D20: #N/A | E20: #N/A | F20: #N/A | G20: #N/A | H20: #N/A | BI20: Row Labels | BJ20: Initial Volume $ | BK20: $% | BL20: Volatility | BM20: Target Return % | BN20: Target P&L | BO20: Actual Return % | BP20: Actual P&L
A21: Grand Total | B21: #N/A | D21: #N/A | E21: #N/A | F21: #N/A | G21: #N/A | H21: #N/A | BI21: US Consumer | BJ21: 283.12184 | BK21: 0.25636243 | BL21: 0.18558396 | BM21: 0.12435577 | BN21: 35.207834 | BO21: 0.01335524 | BP21: 3.78116
BI22: Energy | BJ22: 255.90805 | BK22: 0.23172076 | BL22: 0.34074598 | BM22: 0.13014423 | BN22: 33.304954 | BO22: -0.094427078 | BP22: -24.164649
BI23: ETF | BJ23: 218.852 | BK23: 0.19816709 | BL23: 0.14808574 | BM23: 0.061035677 | BN23: 13.35778 | BO23: -0.010491108 | BP23: -2.296
BI24: Tech | BJ24: 155.61477 | BK24: 0.14090676 | BL24: 0.28791727 | BM24: 0.16617376 | BN24: 25.859091 | BO24: -0.058240834 | BP24: -9.063134
BI25: Banking | BJ25: 114.87946 | BK25: 0.10402157 | BL25: 0.33977481 | BM25: 0.29350438 | BN25: 33.717626 | BO25: 0.11658636 | BP25: 13.393378
BI26: Asia Consumer | BJ26: 66.0058 | BK26: 0.059767227 | BL26: 0.35603887 | BM26: 0.1049725 | BN26: 6.9287941 | BO26: -0.020911405 | BP26: -1.380274
BI27: Health | BJ27: 9.99925 | BK27: 0.0090541656 | BL27: 0.2 | BM27: 0.2 | BN27: 1.99985 | BO27: -0.016963772 | BP27: -0.169625
BI28: Forex | BJ28: 2.9136552e-16 | BK28: 2.6382695e-19 | BL28: 0.48159902 | BM28: 0.099274912 | BN28: 2.8925286e-17 | BO28: -0.94159329 | BP28: -2.7434782e-16
BI29: Industrials | BJ29: 1.3353e-17 | BK29: 1.2090934e-20 | BL29: 0.2 | BM29: 0.07 | BN29: 9.3471e-19 | BO29: 0.10409646 | BP29: 1.39e-18
BI30: Automotive | BJ30: 5.6e-18 | BK30: 5.0707131e-21 | BL30: 0.19 | BM30: 0.07 | BN30: 3.92e-19 | BO30: 0.1825 | BP30: 1.022e-18
BI31: Grand Total | BJ31: 1104.3812 | BK31: 1 | BL31: 0.25488408 | BM31: 0.13616307 | BN31: 150.37593 | BO31: -0.018018366 | BP31: -19.899144

Sheet Sheet3

Sheet Sheet1
B2: Expected | C2: Portfolio | D2: Return: | E2: 0.0887 | G2: Expected | H2: Portfolio | I2: Return: | J2: 0.2413 | M2: Expected | N2: Portfolio | O2: Return: | P2: 0.4495 | R2: Expected | S2: Portfolio | T2: Return: | U2: 0.545 | X2: Expected | Y2: Portfolio | Z2: Return: | AA2: 0.0869 | AD2: Expected | AE2: Portfolio | AF2: Return: | AG2: 0.1434 | AL2: Expected | AM2: Portfolio | AN2: Return: | AO2: 0.2345
B3: Expected | C3: Portfolio | D3: Volatility: | E3: 0.1077 | G3: Expected | H3: Portfolio | I3: Volatility: | J3: 0.3071 | M3: Expected | N3: Portfolio | O3: Volatility: | P3: 0.4685 | R3: Expected | S3: Portfolio | T3: Volatility: | U3: 0.3967 | X3: Expected | Y3: Portfolio | Z3: Volatility: | AA3: 0.1148 | AD3: Expected | AE3: Portfolio | AF3: Volatility: | AG3: 0.1569 | AL3: Expected | AM3: Portfolio | AN3: Volatility: | AO3: 0.2189
X4: Risk Aversion: | AA4: 1 | AD4: Risk Aversion: | AG4: 0.65 | AL4: Risk Aversion: | AO4: 1
B5: Ticker | C5: Volume | D5: Optimal | E5: Delta | G5: Ticker | H5: Volume | I5: Optimal | J5: Delta | M5: Ticker | N5: Volume | O5: Optimal | P5: Delta | R5: Ticker | S5: Volume | T5: Optimal | U5: Delta | X5: Consumer | AC5: Merged | AD5: Consumer | AL5: Tech
B6: APA | C6: 0.2544 | D6: 0 | E6: =D6-C6 -> -0.2544 | G6: APA | H6: 0.2544 | I6: 0.2651 | J6: =I6-H6 -> 0.0107 | M6: ING | N6: 0.0414 | O6: 0.5952 | P6: =O6-N6 -> 0.5538 | R6: ING | S6: 0.0414 | T6: 0 | U6: =T6-S6 -> -0.0414 | X6: Ticker | Y6: Volume | Z6: Optimal | AA6: Delta | AD6: Ticker | AE6: Volume | AF6: % | AG6: Delta | AI6: Avg | AJ6: Delta | AL6: Ticker | AM6: Volume | AN6: % | AO6: Delta
B7: MAXN | C7: 0 | D7: 0 | E7: =D7-C7 -> 0 | G7: MAXN | H7: 0 | I7: 0.1207 | J7: =I7-H7 -> 0.1207 | M7: APA | N7: 0.0569 | O7: 0 | P7: =O7-N7 -> -0.0569 | R7: APA | S7: 0.0569 | T7: 0 | U7: =T7-S7 -> -0.0569 | X7: ACI | Y7: 0.1174 | Z7: 0.0585 | AA7: =Z7-Y7 -> -0.0589 | AC7: 0 | AD7: ACI | AE7: 0.1174 | AF7: 0.204 | AG7: =AF7-AE7 -> 0.0866 | AI7: =(Z7+AF7)/2 -> 0.13125 | AJ7: =AI7-AE7 -> 0.01385 | AL7: TSM | AM7: 0.5009 | AN7: 0.156 | AO7: =AN7-AM7 -> -0.3449
B8: NEE | C8: 0.2158 | D8: 0.0521 | E8: =D8-C8 -> -0.1637 | G8: NEE | H8: 0.2158 | I8: 0.0549 | J8: =I8-H8 -> -0.1609 | M8: MO | N8: 0.1242 | O8: 0 | P8: =O8-N8 -> -0.1242 | R8: MO | S8: 0.1242 | T8: 0 | U8: =T8-S8 -> -0.1242 | X8: MO | Y8: 0.2578 | Z8: 0.113 | AA8: =Z8-Y8 -> -0.1448 | AC8: 1 | AD8: MO | AE8: 0.2578 | AF8: 0.2581 | AG8: =AF8-AE8 -> 0.0003 | AI8: =(Z8+AF8)/2 -> 0.18555 | AJ8: =AI8-AE8 -> -0.07225 | AL8: MSFT | AM8: 0.4347 | AN8: 0.3094 | AO8: =AN8-AM8 -> -0.1253
B9: YPF | C9: 0.1852 | D9: 0.1951 | E9: =D9-C9 -> 0.0099 | G9: YPF | H9: 0.1852 | I9: 0.2769 | J9: =I9-H9 -> 0.0917 | M9: YPF | N9: 0.0552 | O9: 0 | P9: =O9-N9 -> -0.0552 | R9: YPF | S9: 0.0552 | T9: 0 | U9: =T9-S9 -> -0.0552 | X9: KMB | Y9: 0.2039 | Z9: 0.1642 | AA9: =Z9-Y9 -> -0.0397 | AC9: 2 | AD9: KMB | AE9: 0.2039 | AF9: 0 | AG9: =AF9-AE9 -> -0.2039 | AI9: =(Z9+AF9)/2 -> 0.0821 | AJ9: =AI9-AE9 -> -0.1218 | AL9: GOOGL | AM9: 0.0642 | AN9: 0.1463 | AO9: =AN9-AM9 -> 0.0821
B10: FSLR | C10: 0.2772 | D10: 0 | E10: =D10-C10 -> -0.2772 | G10: FSLR | H10: 0.2772 | I10: 0 | J10: =I10-H10 -> -0.2772 | M10: NEE | N10: 0.0483 | O10: 0 | P10: =O10-N10 -> -0.0483 | R10: NEE | S10: 0.0483 | T10: 0 | U10: =T10-S10 -> -0.0483 | X10: PEP | Y10: 0.2319 | Z10: 0.2298 | AA10: =Z10-Y10 -> -0.0021 | AC10: 3 | AD10: PEP | AE10: 0.2319 | AF10: 0 | AG10: =AF10-AE10 -> -0.2319 | AI10: =(Z10+AF10)/2 -> 0.1149 | AJ10: =AI10-AE10 -> -0.117 | AL10: AAPL | AM10: 0.0001 | AN10: 0.351 | AO10: =AN10-AM10 -> 0.3509
B11: DUK | C11: 0 | D11: 0.3391 | E11: =D11-C11 -> 0.3391 | G11: DUK | H11: 0 | I11: 0 | J11: =I11-H11 -> 0 | M11: PEP | N11: 0.0966 | O11: 0 | P11: =O11-N11 -> -0.0966 | R11: PEP | S11: 0.0966 | T11: 0 | U11: =T11-S11 -> -0.0966 | X11: INGR | Y11: 0.1317 | Z11: 0.1551 | AA11: =Z11-Y11 -> 0.0234 | AC11: 4 | AD11: INGR | AE11: 0.1317 | AF11: 0.0382 | AG11: =AF11-AE11 -> -0.0935 | AI11: =(Z11+AF11)/2 -> 0.09665 | AJ11: =AI11-AE11 -> -0.03505 | AL11: QCOM | AM11: 0 | AN11: 0 | AO11: =AN11-AM11 -> 0
B12: JKS | C12: 0 | D12: 0 | E12: =D12-C12 -> 0 | G12: JKS | H12: 0 | I12: 0 | J12: =I12-H12 -> 0 | M12: TSM | N12: 0.1076 | O12: 0 | P12: =O12-N12 -> -0.1076 | R12: TSM | S12: 0.1076 | T12: 0 | U12: =T12-S12 -> -0.1076 | X12: YUM | Y12: 0.0001 | Z12: 0.081 | AA12: =Z12-Y12 -> 0.0809 | AC12: 5 | AD12: YUM | AE12: 0.0001 | AF12: 0 | AG12: =AF12-AE12 -> -0.0001 | AI12: =(Z12+AF12)/2 -> 0.0405 | AJ12: =AI12-AE12 -> 0.0404 | AL12: ASML | AM12: 0 | AN12: 0 | AO12: =AN12-AM12 -> 0
B13: SWI | C13: 0 | D13: 0 | E13: =D13-C13 -> 0 | G13: SWI | H13: 0 | I13: 0 | J13: =I13-H13 -> 0 | M13: KMB | N13: 0.0693 | O13: 0 | P13: =O13-N13 -> -0.0693 | R13: KMB | S13: 0.0693 | T13: 0 | U13: =T13-S13 -> -0.0693 | X13: MC.PA | Y13: 0 | Z13: 0 | AA13: =Z13-Y13 -> 0 | AC13: 6 | AD13: MC.PA | AE13: 0 | AF13: 0.2001 | AG13: =AF13-AE13 -> 0.2001 | AI13: =(Z13+AF13)/2 -> 0.10005 | AJ13: =AI13-AE13 -> 0.10005 | AL13: NVDA | AM13: 0 | AN13: 0.0374 | AO13: =AN13-AM13 -> 0.0374
B14: CSIQ | C14: 0 | D14: 0 | E14: =D14-C14 -> 0 | G14: CSIQ | H14: 0 | I14: 0 | J14: =I14-H14 -> 0 | M14: AGIO | N14: 0.0138 | O14: 0 | P14: =O14-N14 -> -0.0138 | R14: AGIO | S14: 0.0138 | T14: 0 | U14: =T14-S14 -> -0.0138 | X14: WMT | Y14: 0 | Z14: 0.1796 | AA14: =Z14-Y14 -> 0.1796 | AC14: 7 | AD14: WMT | AE14: 0 | AF14: 0.2995 | AG14: =AF14-AE14 -> 0.2995 | AI14: =(Z14+AF14)/2 -> 0.23955 | AJ14: =AI14-AE14 -> 0.23955 | AL14: AMAT | AM14: 0 | AN14: 0 | AO14: =AN14-AM14 -> 0
B15: EXC | C15: 0.0674 | D15: 0.1965 | E15: =D15-C15 -> 0.1291 | G15: EXC | H15: 0.0674 | I15: 0.1642 | J15: =I15-H15 -> 0.0968 | M15: EXC | N15: 0.0151 | O15: 0 | P15: =O15-N15 -> -0.0151 | R15: EXC | S15: 0.0151 | T15: 0 | U15: =T15-S15 -> -0.0151 | X15: YUMC | Y15: 0 | Z15: 0 | AA15: =Z15-Y15 -> 0 | AC15: 8 | AD15: YUMC | AE15: 0 | AF15: 0 | AG15: =AF15-AE15 -> 0 | AI15: =(Z15+AF15)/2 -> 0 | AJ15: =AI15-AE15 -> 0 | AL15: PLTR | AM15: 0 | AN15: 0 | AO15: =AN15-AM15 -> 0
B16: PCG | C16: 0 | D16: 0.2172 | E16: =D16-C16 -> 0.2172 | G16: PCG | H16: 0 | I16: 0.1183 | J16: =I16-H16 -> 0.1183 | M16: YUM | N16: 0.0469 | O16: 0 | P16: =O16-N16 -> -0.0469 | R16: YUM | S16: 0.0469 | T16: 0 | U16: =T16-S16 -> -0.0469 | X16: DAR | Y16: 0.0572 | Z16: 0.0189 | AA16: =Z16-Y16 -> -0.0383 | AC16: 9 | AD16: DAR | AE16: 0.0572 | AF16: 0 | AG16: =AF16-AE16 -> -0.0572 | AI16: =(Z16+AF16)/2 -> 0.00945 | AJ16: =AI16-AE16 -> -0.04775
M17: FSLR | N17: 0.062 | O17: 0 | P17: =O17-N17 -> -0.062 | R17: FSLR | S17: 0.062 | T17: 0 | U17: =T17-S17 -> -0.062
M18: INGR | N18: 0.0359 | O18: 0 | P18: =O18-N18 -> -0.0359 | R18: INGR | S18: 0.0359 | T18: 0 | U18: =T18-S18 -> -0.0359 | X18: Consider Dividend Kings | AD18: Expected | AE18: Portfolio | AF18: Return: | AG18: 0.1334 | AL18: *Good moment to buy as prices just droped
B19: Expected | C19: Portfolio | D19: Return: | E19: 0.1563 | M19: AAPL | N19: 0.0591 | O19: 0 | P19: =O19-N19 -> -0.0591 | R19: AAPL | S19: 0.0591 | T19: 0 | U19: =T19-S19 -> -0.0591 | X19: Ticker | Y19: Dividend | AD19: Expected | AE19: Portfolio | AF19: Volatility: | AG19: 0.1357
B20: Expected | C20: Portfolio | D20: Volatility: | E20: 0.1726 | M20: MSFT | N20: 0.0782 | O20: 0 | P20: =O20-N20 -> -0.0782 | R20: MSFT | S20: 0.0782 | T20: 0 | U20: =T20-S20 -> -0.0782 | X20: ACI | Y20: 0.025 | AD20: Risk Aversion: | AG20: 0.81
B21: Risk Aversion: | E21: 0.81 | M21: MA | N21: 0.0896 | O21: 0 | P21: =O21-N21 -> -0.0896 | R21: MA | S21: 0.0896 | T21: 0 | U21: =T21-S21 -> -0.0896 | X21: MO | Y21: 0.082 | AD21: Consumer
B22: DataFrame: | M22: MAXN | N22: 0 | O22: 0.1867 | P22: =O22-N22 -> 0.1867 | R22: MAXN | S22: 0 | T22: 0 | U22: =T22-S22 -> 0 | X22: KMB | Y22: 0.034 | AD22: Ticker | AE22: Volume | AF22: % | AG22: Delta
B23: Ticker | C23: Volume | D23: Optimal | E23: Delta | M23: V | N23: 0 | O23: 0.2181 | P23: =O23-N23 -> 0.2181 | R23: V | S23: 0 | T23: 0 | U23: =T23-S23 -> 0 | X23: PEP | Y23: 0.028 | AD23: PEP | AE23: 0.2319 | AF23: 0.0601 | AG23: =AF23-AE23 -> -0.1718
B24: YPF | C24: 0.2216 | D24: 0 | E24: =D24-C24 -> -0.2216 | F24: Evaluate an exit stragety | M24: QCOM | N24: 0 | O24: 0 | P24: =O24-N24 -> 0 | R24: QCOM | S24: 0 | T24: 0 | U24: =T24-S24 -> 0 | X24: INGR | Y24: 0.026 | AD24: DAR | AE24: 0.0572 | AF24: 0.0241 | AG24: =AF24-AE24 -> -0.0331
B25: FSLR | C25: 0.2212 | D25: 0.0831 | E25: =D25-C25 -> -0.1381 | M25: GOOGL | N25: 0 | O25: 0 | P25: =O25-N25 -> 0 | R25: GOOGL | S25: 0 | T25: 0 | U25: =T25-S25 -> 0 | X25: *It dosent matter the individual returns when distributing a portafolio at max aversion. | AD25: INGR | AE25: 0.1317 | AF25: 0.0217 | AG25: =AF25-AE25 -> -0.11
B26: NEE | C26: 0.203 | D26: 0.5692 | E26: =D26-C26 -> 0.3662 | M26: MC.PA | N26: 0 | O26: 0 | P26: =O26-N26 -> 0 | R26: MC.PA | S26: 0 | T26: 0 | U26: =T26-S26 -> 0 | X26: *Plan exit stragety for KMB, 7% profit | AD26: YUMC | AE26: 0 | AF26: 0 | AG26: =AF26-AE26 -> 0
B27: APA | C27: 0.2398 | D27: 0 | E27: =D27-C27 -> -0.2398 | M27: ASML | N27: 0 | O27: 0 | P27: =O27-N27 -> 0 | R27: ASML | S27: 0 | T27: 0 | U27: =T27-S27 -> 0 | AD27: WMT | AE27: 0 | AF27: 0.4125 | AG27: =AF27-AE27 -> 0.4125
B28: PCG | C28: 0 | D28: 0 | E28: =D28-C28 -> 0 | M28: NVDA | N28: 0 | O28: 0 | P28: =O28-N28 -> 0 | R28: NVDA | S28: 0 | T28: 0.7324 | U28: =T28-S28 -> 0.7324 | AD28: MC.PA | AE28: 0 | AF28: 0.1847 | AG28: =AF28-AE28 -> 0.1847
B29: MAXN | C29: 0 | D29: 0 | E29: =D29-C29 -> 0 | M29: AMAT | N29: 0 | O29: 0 | P29: =O29-N29 -> 0 | R29: AMAT | S29: 0 | T29: 0 | U29: =T29-S29 -> 0 | AD29: YUM | AE29: 0.0001 | AF29: 0.1294 | AG29: =AF29-AE29 -> 0.1293
B30: CSIQ | C30: 0 | D30: 0 | E30: =D30-C30 -> 0 | M30: DUK | N30: 0 | O30: 0 | P30: =O30-N30 -> 0 | R30: DUK | S30: 0 | T30: 0 | U30: =T30-S30 -> 0 | AD30: ACI | AE30: 0.1174 | AF30: 0.1335 | AG30: =AF30-AE30 -> 0.0161
B31: JKS | C31: 0 | D31: 0 | E31: =D31-C31 -> 0 | M31: PLTR | N31: 0 | O31: 0 | P31: =O31-N31 -> 0 | R31: PLTR | S31: 0 | T31: 0.2676 | U31: =T31-S31 -> 0.2676 | AD31: KMB | AE31: 0.2039 | AF31: 0 | AG31: =AF31-AE31 -> -0.2039
B32: DUK | C32: 0 | D32: 0 | E32: =D32-C32 -> 0 | M32: JKS | N32: 0 | O32: 0 | P32: =O32-N32 -> 0 | R32: JKS | S32: 0 | T32: 0 | U32: =T32-S32 -> 0 | AD32: MO | AE32: 0.2578 | AF32: 0.034 | AG32: =AF32-AE32 -> -0.2238
B33: SWI | C33: 0 | D33: 0.0497 | E33: =D33-C33 -> 0.0497 | M33: SWI | N33: 0 | O33: 0 | P33: =O33-N33 -> 0 | R33: SWI | S33: 0 | T33: 0 | U33: =T33-S33 -> 0
B34: EXC | C34: 0.1144 | D34: 0.298 | E34: =D34-C34 -> 0.1836 | M34: CSIQ | N34: 0 | O34: 0 | P34: =O34-N34 -> 0 | R34: CSIQ | S34: 0 | T34: 0 | U34: =T34-S34 -> 0
M35: WMT | N35: 0 | O35: 0 | P35: =O35-N35 -> 0 | R35: WMT | S35: 0 | T35: 0 | U35: =T35-S35 -> 0
M36: APTV | N36: 0 | O36: 0 | P36: =O36-N36 -> 0 | R36: APTV | S36: 0 | T36: 0 | U36: =T36-S36 -> 0
M37: YUMC | N37: 0 | O37: 0 | P37: =O37-N37 -> 0 | R37: YUMC | S37: 0 | T37: 0 | U37: =T37-S37 -> 0
M38: DAR | N38: 0 | O38: 0 | P38: =O38-N38 -> 0 | R38: DAR | S38: 0 | T38: 0 | U38: =T38-S38 -> 0
M39: MMM | N39: 0 | O39: 0 | P39: =O39-N39 -> 0 | R39: MMM | S39: 0 | T39: 0 | U39: =T39-S39 -> 0
M40: PCG | N40: 0 | O40: 0 | P40: =O40-N40 -> 0 | R40: PCG | S40: 0 | T40: 0 | U40: =T40-S40 -> 0
M41: ACI | N41: 0 | O41: 0 | P41: =O41-N41 -> 0 | R41: ACI | S41: 0 | T41: 0 | U41: =T41-S41 -> 0
M42: HCA | N42: 0 | O42: 0 | P42: =O42-N42 -> 0 | R42: HCA | S42: 0 | T42: 0 | U42: =T42-S42 -> 0
